Workbook

Sheet Summary
A1: YukthiX product tracker
A2: Generated 2026-10-07 from docs/yukthix (design docs, roadmap, go-live) and the code in: exam-app-org, exam-app-ws
A4: Design rules
A5: Built + tested | B5: =COUNTIF(Rules!$H$2:$H$982,"Built + tested")
A6: Built, no test cites it | B6: =COUNTIF(Rules!$H$2:$H$982,"Built, no test cites it")
A7: Tested, code not linked | B7: =COUNTIF(Rules!$H$2:$H$982,"Tested, code not linked")
A8: UI prototype only | B8: =COUNTIF(Rules!$H$2:$H$982,"UI prototype only")
A9: Verify (step done, not linked) | B9: =COUNTIF(Rules!$H$2:$H$982,"Verify (step done, not linked)")
A10: In progress | B10: =COUNTIF(Rules!$H$2:$H$982,"In progress")
A11: Not started | B11: =COUNTIF(Rules!$H$2:$H$982,"Not started")
A12: Not needed | B12: =COUNTIF(Rules!$H$2:$H$982,"Not needed")
A13: All rules | B13: =COUNTA(Rules!$A$2:$A$982)
A14: % built + tested | B14: =COUNTIF(Rules!$H$2:$H$982,"Built + tested")/COUNTA(Rules!$A$2:$A$982)
A16: Work
A17: Open work items not done | B17: =COUNTA('Open work'!A2:A16)-COUNTIF('Open work'!E2:E16,"Done")
A18: Deferred items still open | B18: =COUNTA(Deferred!A2:A106)-COUNTIF(Deferred!G2:G106,"Done")-COUNTIF(Deferred!G2:G106,"Accepted*")-COUNTIF(Deferred!G2:G106,"Moved*")
A19: Go-live items not done | B19: =COUNTA('Go-live'!A2:A13)-COUNTIF('Go-live'!F2:F13,"Done")
A21: UI
A22: Screen files | B22: 102
A23: Screen files wired to the API | B23: 23
A24: Storybook stories | B24: 2975
A26: Design
A27: Design docs | B27: 52
A28: PRs (YukthiX branches) | B28: 4
A30: Backlog
A31: Epics | B31: =COUNTIF(Backlog!$C$2:$C$1564,"Epic")
A32: Features | B32: =COUNTIF(Backlog!$C$2:$C$1564,"Feature")
A33: Stories | B33: =COUNTIF(Backlog!$C$2:$C$1564,"Story")
A34: Stories Done | B34: =COUNTIFS(Backlog!$C$2:$C$1564,"Story",Backlog!$I$2:$I$1564,"Done")
A35: Stories Active | B35: =COUNTIFS(Backlog!$C$2:$C$1564,"Story",Backlog!$I$2:$I$1564,"Active")
A36: Stories New | B36: =COUNTIFS(Backlog!$C$2:$C$1564,"Story",Backlog!$I$2:$I$1564,"New")
A37: Story points total | B37: =SUMIFS(Backlog!$K$2:$K$1564,Backlog!$C$2:$C$1564,"Story")
A38: % points done | B38: =SUMIFS(Backlog!$K$2:$K$1564,Backlog!$C$2:$C$1564,"Story",Backlog!$I$2:$I$1564,"Done")/SUMIFS(Backlog!$K$2:$K$1564,Backlog!$C$2:$C$1564,"Story")
A39: Rules not covered by a story | B39: =COUNTA(Coverage!A2:A1031)
A42: How to read this
A43: Rules: every YX-... rule in the design docs. "Built + tested" means a code file and a test file cite the rule ID.
A44: "Verify" means its roadmap step is done but no code or test cites the rule: confirm it is built and add the ID to its test, or build it.
A45: Override (you) on the Rules sheet replaces the automatic status (e.g. "Not needed" with a note).
A46: Deferred: things each build job reported as left out. Close, move to a step, or accept each one.
A47: Columns marked (you) are kept when the tracker is regenerated. Everything else is rebuilt from the docs and the code.
A48: Rebuild: python docs/yukthix/tracker/build_tracker.py --code <each worktree with unmerged work>

Sheet Rules
A1: Rule ID | B1: Doc | C1: Area | D1: Roadmap step | E1: Rule (from the design doc) | F1: Status (auto) | G1: Override (you) | H1: Status | I1: Code files | J1: Test files | K1: UI files | L1: Where (first 3) | M1: Notes (you)
A2: YX-ORG-23 | B2: APX-E | C2: YX-ORG | D2: 6+ | E2: Setup hub. Setup steps are registered in code per module with card, required / optional flag, dependencies, a computed completion check, the starter keys they apply and the editor they open; the hub shows one card per area for the products the tenant has switched on. Starter templates are applied when a product or wave is switched on, each labelled "YukthiX starter — edit for your company" and recorded in starter_applications; a starter flagged ⚑ stays "unreviewed" until a person keeps or edits it, and later YukthiX starter versions never overwrite a company value. | F2: Not started | H2: =IF(G2<>"",G2,F2) | I2: 0 | J2: 0 | K2: 0
A3: YX-ORG-24 | B3: APX-E | C3: YX-ORG | D3: 6+ | E3: Go-live readiness. Each module has registered readiness checks, each blocking or advisory (§2). A module's employee-facing features (self-service requests, mobile invites, employee notifications for that module) are switched on for a legal entity only when all its blocking checks pass and the module owner has signed off; admins can configure and test before. Sign-off records the owner, time, readiness score and an acknowledgement note for every open advisory; it cannot be given while a blocking check fails. After go-live the checks keep running as health checks and a regression alerts the owne | F3: Not started | H3: =IF(G3<>"",G3,F3) | I3: 0 | J3: 0 | K3: 0
A4: YX-ORG-25 | B4: APX-E | C4: YX-ORG | D4: 6+ | E4: Every company policy has an editor. Every setting key and policy record registered by a module declares its editor screen, Settings group, allowed scopes, dated flag and either a starter template or a P07 legal source; a CI check fails the build if a registered policy key has no editor route or no starter / legal source. Legal values (P07) are shown read-only with source and version and are never starters (spec D17). | F4: Not started | H4: =IF(G4<>"",G4,F4) | I4: 0 | J4: 0 | K4: 0
A5: YX-DOC-20 | B5: APX-F | C5: YX-DOC | D5: 6+ | E5: Starter library. Every template in this library ships as a versioned starter template labelled "YukthiX starter — edit for your company" in the template list and editor (never printed on issued documents). The company edits a copy; a later YukthiX starter version never overwrites a company-edited template and is offered as "new starter version available" with a diff. Issuing from a starter that nobody has reviewed shows the issuer a one-time warning and counts as an advisory readiness finding (APX-E YX-ORG-24). | F5: Not started | H5: =IF(G5<>"",G5,F5) | I5: 0 | J5: 0 | K5: 0
A6: YX-DOC-21 | B6: APX-F | C6: YX-DOC | D6: 6+ | E6: Restricted-area letters on the verify page. Letters issued from a restricted-area case (POSH, disciplinary, grievance, whistleblower; P02) keep QR verification on by default (P05 Q5), but the public verify page shows the letter type only as "Confidential HR letter", with company, name, date and current / superseded status; the case type never appears outside the app. | F6: Not started | H6: =IF(G6<>"",G6,F6) | I6: 0 | J6: 0 | K6: 0
A7: YX-DOC-22 | B7: APX-F | C7: YX-DOC | D7: 6+ | E7: Legally mandatory content is locked. For templates whose content is prescribed by law (statutory forms, GST tax invoice and credit note, wage slip / payslip, legally required notice wording) the editor locks the mandatory fields and blocks; the company may change branding, layout of non-mandatory parts, optional fields and language. A template cannot be activated when a mandatory field is missing (extends YX-DOC-15); the mandatory field list comes from P07 and changes with it. | F7: Not started | H7: =IF(G7<>"",G7,F7) | I7: 0 | J7: 0 | K7: 0
A8: YX-EMP-01 | B8: M01 | C8: YX-EMP | D8: 2 | E8: Identity fields are validated on entry (PAN format + verification, Aadhaar checksum, UAN/ESIC/IFSC formats); Aadhaar is stored encrypted and displayed masked (P02 YX-SEC-08). | F8: Built + tested | H8: =IF(G8<>"",G8,F8) | I8: 1 | J8: 2 | K8: 2 | L8: exam-app-org:apps/api/src/access/scope.spec.ts exam-app-org:apps/api/src/people/profile.dto.ts exam-app-org:apps/api/test/access-privacy.e2e-spec.ts
A9: YX-EMP-02 | B9: M01 | C9: YX-EMP | D9: 2 | E9: Duplicate PAN, Aadhaar or salary bank account across active employees raises a blocking warning with the conflicting record (HR may override with reason). | F9: Built + tested | H9: =IF(G9<>"",G9,F9) | I9: 4 | J9: 2 | K9: 2 | L9: exam-app-org:apps/api/prisma/migrations/20261010000000_access_privacy/migration.sql exam-app-org:apps/api/prisma/schema.prisma exam-app-org:apps/api/src/people/profile.dto.ts
A10: YX-EMP-03 | B10: M01 | C10: YX-EMP | D10: 2 | E10: Custom fields carry a sensitivity class and self-edit flag; P02 rules apply to them like built-in fields. | F10: Verify (step done, not linked) | H10: =IF(G10<>"",G10,F10) | I10: 0 | J10: 0 | K10: 0
A11: YX-EMP-04 | B11: M01 | C11: YX-EMP | D11: 2 | E11: Dotted-line managers never enter approval chains unless a policy explicitly names them. | F11: Built + tested | H11: =IF(G11<>"",G11,F11) | I11: 3 | J11: 2 | K11: 1 | L11: exam-app-org:apps/api/prisma/migrations/20261009000000_people_core/migration.sql exam-app-org:apps/api/prisma/schema.prisma exam-app-org:apps/api/src/employee-history/history-rules.ts
A12: YX-EMP-05 | B12: M01 | C12: YX-EMP | D12: 2 | E12: Every job change is a P06 change with a type, impact preview, approval and (where configured) a letter; a promotion that changes pay updates compensation in the same change. | F12: Verify (step done, not linked) | H12: =IF(G12<>"",G12,F12) | I12: 0 | J12: 0 | K12: 0
A13: YX-EMP-06 | B13: M01 | C13: YX-EMP | D13: 2 | E13: Long absence (sabbatical, long LWP, maternity, long-term disability) is a dated absence status on the employment with an expected return date; starting, changing and ending it are P06 changes, the return fires return-to-work tasks, and its payroll / leave / statutory effects come from M02 / M03. Sabbatical eligibility, length and pay are company policy (starter template). | F13: Verify (step done, not linked) | H13: =IF(G13<>"",G13,F13) | I13: 0 | J13: 0 | K13: 0
A14: YX-EMP-07 | B14: M01 | C14: YX-EMP | D14: 2 | E14: An assignment with host fields takes its holiday calendar, PT state and geofence from the host location for the assignment's dates while the home entity stays the employer; a recharge flag lists it in the recharge report. Bulk restructures use one wizard with YX-ORG-17 options as editable defaults; an entity is closed only when it has no active employments and its last payroll period is locked. | F14: Verify (step done, not linked) | H14: =IF(G14<>"",G14,F14) | I14: 0 | J14: 0 | K14: 0
A15: YX-EMP-08 | B15: M01 | C15: YX-EMP | D15: 2 | E15: Every inter-entity transfer opens a continuity checklist (UAN transfer, ESI IP, Form 12B into the new entity, declarations / proofs, loans re-parented when "no F&F", leave-ledger transfer entries, gratuity exemption carried across payouts); open items are visible on the change and in M03 pre-flight. | F15: Verify (step done, not linked) | H15: =IF(G15<>"",G15,F15) | I15: 0 | J15: 0 | K15: 0
A16: YX-EMP-09 | B16: M01 | C16: YX-EMP | D16: 2 | E16: Positions (B16): in position-based mode every assignment references a position of the same entity; the sum of incumbents' FTE never exceeds the position's FTE (job-share allowed); creating, re-grading or closing a position is a P03 request; a position becomes vacant on its incumbent's exit or transfer and "Open requisition" on a vacant / approved position creates an M10 requisition linked to it and its plan line; in job-based mode (starter) positions are optional and nothing is blocked. | F16: Verify (step done, not linked) | H16: =IF(G16<>"",G16,F16) | I16: 0 | J16: 0 | K16: 0
A17: YX-EMP-10 | B17: M01 | C17: YX-EMP | D17: 2 | E17: Workforce scenarios (B16): a scenario never changes live data; its forecast = current headcount and cost ± planned changes, reduced by the scenario's attrition rate per department with backfill lag; costs use M03 compensation and employer contributions (new hires at band midpoint); only an approved scenario (P03) creates positions / M10 headcount-plan lines; scenarios are Confidential (HR, finance, leadership). | F17: Verify (step done, not linked) | H17: =IF(G17<>"",G17,F17) | I17: 0 | J17: 0 | K17: 0
A18: YX-EMP-11 | B18: M01 | C18: YX-EMP | D18: 2 | E18: Career paths & IDPs (B16) — owned by M06. Rules are YX-PERF-14 (IDP) and YX-PERF-15 (career paths); M01 only displays them (Me › Career, succession view) and never keeps its own copy. | F18: Verify (step done, not linked) | H18: =IF(G18<>"",G18,F18) | I18: 0 | J18: 0 | K18: 0
A19: YX-EMP-12 | B19: M01 | C19: YX-EMP | D19: 2 | E19: Attrition-risk signal (B16) — owned by M06. Rules are YX-PERF-17 (HR only, advisory, never read by any workflow, approval, rating, pay, notification or selection step). M01 workforce scenarios (YX-EMP-10) use only the aggregate P09 attrition rate, never individual bands. | F19: Verify (step done, not linked) | H19: =IF(G19<>"",G19,F19) | I19: 0 | J19: 0 | K19: 0
A20: YX-EMP-13 | B20: M01 | C20: YX-EMP | D20: 2 | E20: Annual health check-up (C1): where P07 IN.OSH prescribes it, eligible workers (currently aged 40+) are listed yearly per establishment, get a scheduling task and a free check-up record; outcomes and reports are Special class (P02), hidden from managers (who see scheduled / done only), and nothing is charged to the employee. | F20: Verify (step done, not linked) | H20: =IF(G20<>"",G20,F20) | I20: 0 | J20: 0 | K20: 0
A21: YX-EMP-14 | B21: M01 | C21: YX-EMP | D21: 2 | E21: Disability declaration (R8). Disability status is voluntary and recorded only with explicit, withdrawable consent; it is Special class (P02): never shown to the manager, used by payroll only as the ESI PwD ceiling flag (P07 IN.ESI), and reported only in aggregate with small-cell suppression; the equal-opportunity policy (M08, starter template) is linked from the declaration. Withdrawal hides the data from all but the audit trail within the retention rule. | F21: Verify (step done, not linked) | H21: =IF(G21<>"",G21,F21) | I21: 0 | J21: 0 | K21: 0
A22: YX-EMP-15 | B22: M01 | C22: YX-EMP | D22: 2 | E22: Union register and membership (J4). Unions, their recognition (basis and dates, per IR Code negotiating-union rules, verify) and dated employee memberships with check-off consent are kept per legal entity / establishment; membership is Confidential (P02: HR-IR role and payroll for dues only), never used by other modules; lay-off, strike and lockout days from M02 (YX-AT-27) appear on the employee timeline. | F22: Verify (step done, not linked) | H22: =IF(G22<>"",G22,F22) | I22: 0 | J22: 0 | K22: 0
A23: YX-EMP-16 | B23: M01 | C23: YX-EMP | D23: 2 | E23: Periodic re-verification (V11, T22). Re-verification runs only per a company rule (periodic N years, role change into a sensitive role, client mandate), each cycle with fresh consent via the P10 BGV connector; results are Confidential (adverse findings Special), open an HR review task, and never trigger an automatic status change. | F23: Verify (step done, not linked) | H23: =IF(G23<>"",G23,F23) | I23: 0 | J23: 0 | K23: 2
... A25: YX-EMP-18 | B25: M01 | C25: YX-EMP | D25: 2 | E25: Insider-trading designated persons (V12). Designated persons (SEBI PIT Regulations 2015, verify) file holdings and relatives disclosures on designation and yearly, and need pre-clearance for trades above the company threshold; a pre-clearance is valid for the company's window (starter 7 trading days, verify) and blocked during a trading-window closure; the trade is reported back and late / missing reports alert the compliance officer. | F25: Verify (step done, not linked) | H25: =IF(G25<>"",G25,F25) | I25: 0 | J25: 0 | K25: 2
A26: YX-LC-01 | B26: M01 | C26: YX-LC | D26: 2 | E26: Probation reviews are created N days before the end; unresolved reviews escalate to HR on the end date; no auto-confirmation unless the tenant enables it. | F26: Built + tested | H26: =IF(G26<>"",G26,F26) | I26: 5 | J26: 2 | K26: 4 | L26: exam-app-org:apps/api/prisma/migrations/20261009000000_people_core/migration.sql exam-app-org:apps/api/src/jobs/scheduled-sweeps.queue.ts exam-app-org:apps/api/src/jobs/scheduled-sweeps.worker.service.ts
A27: YX-LC-02 | B27: M01 | C27: YX-LC | D27: 2 | E27: Onboarding and offboarding tasks use relative due dates (negative allowed), named owners and SLA reminders; progress is shown on the employee record. | F27: Verify (step done, not linked) | H27: =IF(G27<>"",G27,F27) | I27: 0 | J27: 0 | K27: 2
A28: YX-LC-03 | B28: M01 | C28: YX-LC | D28: 2 | E28: Pre-boarding data becomes employee data on joining without re-entry; unverified mandatory documents are flagged in payroll pre-flight (P05 YX-DOC-17). | F28: Verify (step done, not linked) | H28: =IF(G28<>"",G28,F28) | I28: 0 | J28: 0 | K28: 0
A29: YX-LC-04 | B29: M01 | C29: YX-LC | D29: 2 | E29: Resignation notice is computed from the policy valid on the submission date; early release, buy-out and withdrawal each require approval and are recorded on the exit case. | F29: Verify (step done, not linked) | H29: =IF(G29<>"",G29,F29) | I29: 0 | J29: 0 | K29: 4
A30: YX-LC-05 | B30: M01 | C30: YX-LC | D30: 2 | E30: On the last working day: access converts to alumni, implicit grants end, open approvals are reassigned and pending onboarding/exit tasks are escalated. | F30: Verify (step done, not linked) | H30: =IF(G30<>"",G30,F30) | I30: 0 | J30: 0 | K30: 0
A31: YX-LC-06 | B31: M01 | C31: YX-LC | D31: 2 | E31: F&F is calculated (not just tracked): final salary, encashment, bonus, gratuity, reimbursements, arrears, notice pay in lieu minus notice shortfall, negative leave, expense advances (M05 Q6), salary advances / loans (M03 Q4), assets, training-bond recovery (M07 Q5), joining / retention bonus clawback (M10 Q3), other, with TDS; every line is explained. | F31: Verify (step done, not linked) | H31: =IF(G31<>"",G31,F31) | I31: 0 | J31: 0 | K31: 2
A32: YX-LC-07 | B32: M01 | C32: YX-LC | D32: 2 | E32: Open expense advances (M05 Q6), salary advances / loans (M03 Q4), unreturned assets, negative leave balances, confirmed training-bond recoveries (M07 Q5) and bonus clawbacks (M10 Q3) are pulled into the F&F automatically and refreshed until the F&F is approved (fixes U65). | F32: Verify (step done, not linked) | H32: =IF(G32<>"",G32,F32) | I32: 0 | J32: 0 | K32: 2
A33: YX-LC-08 | B33: M01 | C33: YX-LC | D33: 2 | E33: F&F due dates follow the legal deadline: wages due on exit are paid within 2 working days of the LWD for every exit type (P07 IN.WAGES-CODE, from 21 Nov 2025) and other dues by their own P07 deadlines; holds, open clearance and missing payee details never move the due date (wage lines may be paid in a first F&F run); overdue settlements are flagged to HR/Payroll. *(Amended by Correction C1.)* | F33: Verify (step done, not linked) | H33: =IF(G33<>"",G33,F33) | I33: 0 | J33: 0 | K33: 4
A34: YX-LC-09 | B34: M01 | C34: YX-LC | D34: 2 | E34: Exit interview answers marked confidential are visible only to HR roles, never to the leaver's manager. | F34: Verify (step done, not linked) | H34: =IF(G34<>"",G34,F34) | I34: 0 | J34: 0 | K34: 0
A35: YX-LC-10 | B35: M01 | C35: YX-LC | D35: 2 | E35: Rehire-eligibility flags are HR-only and surface when the person reappears in the ATS. | F35: Verify (step done, not linked) | H35: =IF(G35<>"",G35,F35) | I35: 0 | J35: 0 | K35: 0
A36: YX-LC-11 | B36: M01 | C36: YX-LC | D36: 2 | E36: Onboarding branches by person type (M10 hand-off matrix): a new person gets a new employee record; an ex-employee rehire gets a new employment on the existing record (rehire_of, P01 YX-ORG-19 continuity options, pre-filled from the old record); an internal move is a P06 transfer / promotion effective on a release date agreed with the current manager, never an onboarding; a contractor conversion is a P06 employment-type change. Amended 28 Sep 2026 (J15): the person type is decided from the P01 person record (YX-ORG-26 / 27), not from the offer or name. | F36: Verify (step done, not linked) | H36: =IF(G36<>"",G36,F36) | I36: 0 | J36: 0 | K36: 0
A37: YX-LC-12 | B37: M01 | C37: YX-LC | D37: 2 | E37: A pre-boarder who did not join, reneged or whose offer was withdrawn after acceptance (manual, reason mandatory, withdrawal letter) is unwound in one audited action: employee, employment, draft compensation and pre-boarding login are cancelled (kept, not deleted), the M10 headcount-plan slot is released and the requisition reopened, and the candidate is marked reneged / withdrawn. Pre-boarders are never counted as active employees for billing. | F37: Verify (step done, not linked) | H37: =IF(G37<>"",G37,F37) | I37: 0 | J37: 0 | K37: 0
A38: YX-LC-13 | B38: M01 | C38: YX-LC | D38: 2 | E38: Changing a pre-boarder's joining date re-anchors the journey: every open task's due date, the draft compensation, the assignment start and the probation dates move with the new joining date; completed tasks are untouched. | F38: Verify (step done, not linked) | H38: =IF(G38<>"",G38,F38) | I38: 0 | J38: 0 | K38: 2
... A61: YX-AT-03 | B61: M02 | C61: YX-AT | D61: 4 | E61: Day status is derived by the day engine; a missing punch yields "missing check-in/out", never a threshold-based status. | F61: Not started | H61: =IF(G61<>"",G61,F61) | I61: 0 | J61: 0 | K61: 0
A62: YX-AT-04 | B62: M02 | C62: YX-AT | D62: 4 | E62: Overtime counts only beyond the policy minimum, rounded down to the policy unit, capped per P07 statutory limits, and reaches payroll only when approved (Q7). | F62: Tested, code not linked | H62: =IF(G62<>"",G62,F62) | I62: 0 | J62: 2 | K62: 2 | L62: exam-app-org:packages/yx-ui/src/screens/time/time.test.tsx exam-app-ws:packages/yx-ui/src/screens/time/time.test.tsx
A63: YX-AT-05 | B63: M02 | C63: YX-AT | D63: 4 | E63: Late penalties follow the tenant's policy (Q4) and appear on the day card and muster before they affect pay. | F63: Not started | H63: =IF(G63<>"",G63,F63) | I63: 0 | J63: 0 | K63: 0
A64: YX-AT-06 | B64: M02 | C64: YX-AT | D64: 4 | E64: Regularisation and WFH/on-duty limits per month are enforced; beyond the limit, requests route to HR (Q5). | F64: Not started | H64: =IF(G64<>"",G64,F64) | I64: 0 | J64: 0 | K64: 0
A65: YX-AT-07 | B65: M02 | C65: YX-AT | D65: 4 | E65: Rosters flag overlaps and minimum-rest violations; publishing notifies affected employees. | F65: Not started | H65: =IF(G65<>"",G65,F65) | I65: 0 | J65: 0 | K65: 0
A66: YX-AT-08 | B66: M02 | C66: YX-AT | D66: 4 | E66: Attendance exceptions must be resolved before payroll approval (P08 YX-LOCK-07/08) — for Punch-mode groups with the block switch on (YX-AT-09). | F66: Not started | H66: =IF(G66<>"",G66,F66) | I66: 0 | J66: 0 | K66: 0
A67: YX-AT-09 | B67: M02 | C67: YX-AT | D67: 4 | E67: Every employee resolves to one attendance mode — Punch, Assumed present or Timesheet — from the scoped P01 setting (entity / location / department / employment type). Missing-punch exceptions exist only in Punch mode, where the company chooses block (default) or warn for payroll approval; Assumed-present groups never block payroll (LOP entered by HR, M03); Timesheet groups raise "no approved timesheet" instead (D1). | F67: Not started | H67: =IF(G67<>"",G67,F67) | I67: 0 | J67: 0 | K67: 0
A68: YX-AT-10 | B68: M02 | C68: YX-AT | D68: 4 | E68: The expected status of a day follows employment status first: suspended, long leave (maternity / sabbatical / LWP), absconding in process, pre-boarding and exited days raise no exceptions, late penalties or nudges (D10). | F68: UI prototype only | H68: =IF(G68<>"",G68,F68) | I68: 0 | J68: 0 | K68: 2
A69: YX-AT-11 | B69: M02 | C69: YX-AT | D69: 4 | E69: A public holiday falling on a weekly off is handled per the calendar's company setting — substitute day / comp-off / none (starter: none) (D17). | F69: Not started | H69: =IF(G69<>"",G69,F69) | I69: 0 | J69: 0 | K69: 0
A70: YX-AT-12 | B70: M02 | C70: YX-AT | D70: 4 | E70: On a half-day leave date, grace applies from the start of the working half, the leave half carries no late penalty, and OT is measured against the half-day's expected hours. | F70: Not started | H70: =IF(G70<>"",G70,F70) | I70: 0 | J70: 0 | K70: 0
A71: YX-AT-13 | B71: M02 | C71: YX-AT | D71: 4 | E71: A punch for a shift that started before the lock attaches to that shift without a late request; a biometric batch arriving after the freeze is applied only through an audited HR bulk "device backfill" correction (P08); an employee can have two shifts in one day, each evaluated separately. | F71: Not started | H71: =IF(G71<>"",G71,F71) | I71: 0 | J71: 0 | K71: 0
A72: YX-AT-14 | B72: M02 | C72: YX-AT | D72: 4 | E72: The Today board, muster, team calendar and attendance calendar open in the viewer's widest P02 scope (manager: team; HR: entity), never self-only; the personal view is the employee's mobile Time tab (fixes U16). | F72: Not started | H72: =IF(G72<>"",G72,F72) | I72: 0 | J72: 0 | K72: 0
A73: YX-AT-15 | B73: M02 | C73: YX-AT | D73: 4 | E73: The day card shows each punch's source, map pin, distance to the nearest allowed location and verdict (inside / outside / field-recorded) to viewers in scope (fixes U17). | F73: UI prototype only | H73: =IF(G73<>"",G73,F73) | I73: 0 | J73: 0 | K73: 2
A74: YX-AT-16 | B74: M02 | C74: YX-AT | D74: 4 | E74: Field-force location trail (B2): location points are collected only when the employee's group has field-force tracking on and the employee's consent is on record, and only between duty check-in and check-out within the shift window + grace; never on leave, weekly offs, holidays or after check-out unless an approved on-duty request covers the day. The app shows "Tracking on" while collecting; withdrawing consent stops collection at once. Trails are Confidential (own + manager / HR in scope, duty time only) and deleted after the company's retention period (starter 90 days), keeping only daily di | F74: Not started | H74: =IF(G74<>"",G74,F74) | I74: 0 | J74: 0 | K74: 0
... A80: YX-AT-22 | B80: M02 | C80: YX-AT | D80: 4 | E80: Visitor management (C1): every visitor enters a location through a pre-registration or a host-approved walk-in; check-in and check-out are logged per location with badge / QR, required acknowledgements (NDA / safety) are captured before entry per the location's rules, blocked visitors are stopped at reception, an "on site now" list is available for emergencies, and visitor data (Confidential) is deleted after the company's retention period (starter 90 days; ID images 30 days). | F80: UI prototype only | H80: =IF(G80<>"",G80,F80) | I80: 0 | J80: 0 | K80: 2
A81: YX-AT-23 | B81: M02 | C81: YX-AT | D81: 4 | E81: Geofence transparency and failed attempts (G7): before a mobile check-in is submitted the employee sees their GPS pin, the accuracy radius and the allowed geofence(s), can retry location, and is told in plain words why a punch would be refused ("Outside Chennai HQ, 850 m away", "Location accuracy 300 m, move outdoors"); every refused or abandoned attempt is logged (time, location, accuracy, distance, reason, device) as an attendance exception the employee and HR can see, so HR can regularise the day from the attempt (P03 request or one-click approval) without the employee being marked late or | F81: Tested, code not linked | H81: =IF(G81<>"",G81,F81) | I81: 0 | J81: 2 | K81: 6 | L81: exam-app-org:packages/yx-ui/src/screens/time/time.test.tsx exam-app-ws:packages/yx-ui/src/screens/time/time.test.tsx
A82: YX-AT-24 | B82: M02 | C82: YX-AT | D82: 4 | E82: Offline check-in (G8, wave 2): when the phone has no connectivity the punch is queued on the device with device time, GPS fix and accuracy, shown in the card's offline queue with a "pending sync" chip, and synced automatically when online; the synced punch is stored with both device time and server receipt time, flagged offline, evaluated by the day engine (§B3) on device time, and listed for HR with the offline flag; the server rejects a queued punch older than the company's limit (starter 48 h) or with a device clock drift beyond tolerance, raising an exception instead of a silent drop. Self | F82: Not started | H82: =IF(G82<>"",G82,F82) | I82: 0 | J82: 0 | K82: 0
A83: YX-AT-25 | B83: M02 | C83: YX-AT | D83: 4 | E83: Women's night-shift guard (C1, law): no roster path (manual edit, pattern, swap, open-shift claim, bid award, auto-roster) places a woman on a shift overlapping the legal night window of P07 IN.OSH for the location's state (transitional Factories Act s.66 / state S&E values where OSH rules are not notified) unless, for that date, her written consent is on record and not withdrawn and the establishment's safeguards checklist is valid; the company's night definition (D17) may be wider but never narrower than the legal window; the guard has no company switch or override; refusing or withdrawing c | F83: Not started | H83: =IF(G83<>"",G83,F83) | I83: 0 | J83: 0 | K83: 0
A84: YX-AT-26 | B84: M02 | C84: YX-AT | D84: 4 | E84: Night-work records (C1): consents (P05 documents), safeguard attestations with evidence and review dates, and a register of women night-shift workers per establishment and period (generated from roster and punches in the dated P07 format, frozen with the period lock) are kept; a lapsed safeguard item alerts the location admin and HR before its review date. | F84: Not started | H84: =IF(G84<>"",G84,F84) | I84: 0 | J84: 0 | K84: 0
A85: YX-AT-27 | B85: M02 | C85: YX-AT | D85: 4 | E85: Industrial-action statuses (J4). Days in a recorded strike, lockout or lay-off event get that status (not Absent / LOP); M03 pays lay-off compensation per P07 IN.IR (verify) and strike / lockout days per legality and company policy (D17), never below the legal floor; the event and its legality are audited and changing legality recomputes the affected days before the period lock. | F85: Not started | H85: =IF(G85<>"",G85,F85) | I85: 0 | J85: 0 | K85: 0
A86: YX-AT-28 | B86: M02 | C86: YX-AT | D86: 4 | E86: Standby and call-out (V7). A standby slot is not a working shift; a call-out logged during it is paid at least the company's call-out minimum (D17) and counts for hours, OT and minimum-rest checks; standby allowance per slot feeds M03. | F86: Not started | H86: =IF(G86<>"",G86,F86) | I86: 0 | J86: 0 | K86: 0
A87: YX-AT-29 | B87: M02 | C87: YX-AT | D87: 4 | E87: Licence gate (V13). No roster path, trip or assignment places a person on a date where a licence required by the role / skill / shift is missing or expired; legally required licences have no override, company-required ones allow an HR override with reason (audited). | F87: Not started | H87: =IF(G87<>"",G87,F87) | I87: 0 | J87: 0 | K87: 0
A88: YX-AT-30 | B88: M02 | C88: YX-AT | D88: 4 | E88: Hybrid office days (T7). Office-day compliance per week is computed from office-geofence / kiosk / badge evidence against the group's policy, pro-rated for leave, holidays and approved travel; it is visible to the employee and manager, and never feeds pay, LOP or ratings unless the company sets a P19 rule to do so. | F88: Not started | H88: =IF(G88<>"",G88,F88) | I88: 0 | J88: 0 | K88: 0
A89: YX-LV-01 | B89: M02 | C89: YX-LV | D89: 4 | E89: A leave balance is always the sum of its ledger entries; no screen or report computes it differently. | F89: Not started | H89: =IF(G89<>"",G89,F89) | I89: 0 | J89: 0 | K89: 0
A90: YX-LV-02 | B90: M02 | C90: YX-LV | D90: 4 | E90: Accruals follow the type's frequency, basis (upfront / days worked / LOP-reduced) and rounding; the last accrual of the leave year trues up to the exact entitlement (L4). | F90: Not started | H90: =IF(G90<>"",G90,F90) | I90: 0 | J90: 0 | K90: 0
A91: YX-LV-03 | B91: M02 | C91: YX-LV | D91: 4 | E91: Day counting applies the type's sandwich mode, holiday/weekly-off treatment and half-day rules (L3), using the employee's location calendar and weekly-off resolution. | F91: Tested, code not linked | H91: =IF(G91<>"",G91,F91) | I91: 0 | J91: 2 | K91: 2 | L91: exam-app-org:packages/yx-ui/src/screens/time/time.test.tsx exam-app-ws:packages/yx-ui/src/screens/time/time.test.tsx
A92: YX-LV-04 | B92: M02 | C92: YX-LV | D92: 4 | E92: Negative balances stay within the type's limit; future accruals repay first; on exit the remainder follows L6. | F92: Not started | H92: =IF(G92<>"",G92,F92) | I92: 0 | J92: 0 | K92: 0
A93: YX-LV-05 | B93: M02 | C93: YX-LV | D93: 4 | E93: Eligibility, notice, maximum per request/month, block dates and mandatory-attachment rules are checked before submission and shown in the live summary. | F93: UI prototype only | H93: =IF(G93<>"",G93,F93) | I93: 0 | J93: 0 | K93: 2
A94: YX-LV-06 | B94: M02 | C94: YX-LV | D94: 4 | E94: Comp-off credits expire after the type's window; expiry posts a ledger entry and notifies the employee in advance. | F94: Not started | H94: =IF(G94<>"",G94,F94) | I94: 0 | J94: 0 | K94: 0
A95: YX-LV-07 | B95: M02 | C95: YX-LV | D95: 4 | E95: Year-end processing (carry forward, lapse, encash) runs only through the year-end wizard with preview and approval. | F95: UI prototype only | H95: =IF(G95<>"",G95,F95) | I95: 0 | J95: 0 | K95: 2
A96: YX-LV-08 | B96: M02 | C96: YX-LV | D96: 4 | E96: Leave affecting a locked period can only be corrected via a late request / correction with effect in the next payroll (P08). | F96: Not started | H96: =IF(G96<>"",G96,F96) | I96: 0 | J96: 0 | K96: 0
A97: YX-LV-09 | B97: M02 | C97: YX-LV | D97: 4 | E97: A mandatory attachment of a medical nature is stored as a P05 "Medical certificate" document (Special class) and verified by HR; approvers and managers see only "certificate attached · verified / pending", never the file (D9). | F97: Not started | H97: =IF(G97<>"",G97,F97) | I97: 0 | J97: 0 | K97: 0
A98: YX-LV-10 | B98: M02 | C98: YX-LV | D98: 4 | E98: Maternity follows the P07 IN.LEAVE template: 80 days in the preceding 12 months for eligibility; 26 weeks (max 8 before delivery), 12 weeks for adopting / commissioning mothers or the 3rd child, 6 weeks for miscarriage / MTP, 2 weeks for tubectomy. For ESIC-covered employees the leave is recorded but pay is by ESIC (M03 YX-PAY-26). Dismissal during maternity leave is blocked (law); crèche and post-maternity WFH are company settings (D17). | F98: Not started | H98: =IF(G98<>"",G98,F98) | I98: 0 | J98: 0 | K98: 0
A99: YX-LV-11 | B99: M02 | C99: YX-LV | D99: 4 | E99: During sabbatical, long LWP or maternity, accrual pauses or continues per leave type as the company sets (D17); statutory values are enforced where the law fixes them. | F99: Not started | H99: =IF(G99<>"",G99,F99) | I99: 0 | J99: 0 | K99: 0
A100: YX-LV-12 | B100: M02 | C100: YX-LV | D100: 4 | E100: Leave during the notice period follows the type's company policy — allowed (starter) / LOP / extends LWD / blocked (D17); the apply sheet warns, and the LWD / notice-shortfall effect is sent to the M01 exit case. | F100: UI prototype only | H100: =IF(G100<>"",G100,F100) | I100: 0 | J100: 0 | K100: 2
A101: YX-LV-13 | B101: M02 | C101: YX-LV | D101: 4 | E101: A leave-year change creates a short year with pro-rata entitlements and a carry-forward transition wizard; on transfer the holiday calendar switches on the transfer date and optional holidays are prorated or reset per company setting. | F101: Not started | H101: =IF(G101<>"",G101,F101) | I101: 0 | J101: 0 | K101: 0
A102: YX-LV-14 | B102: M02 | C102: YX-LV | D102: 4 | E102: Unpaid (LWP) leave types carry no balance: the balance card, reports and mobile show "taken this year", never a negative closing balance; negative balances exist only for paid types within their L6 limit (fixes U7). | F102: UI prototype only | H102: =IF(G102<>"",G102,F102) | I102: 0 | J102: 0 | K102: 4
A103: YX-LV-15 | B103: M02 | C103: YX-LV | D103: 4 | E103: Injury leave (J6): injury leave is posted only from an M08 workplace accident / injury case (YX-CASE-14) for the days the person cannot work; it has no balance or accrual, counts as service and never as LOP; pay follows the company policy (D17) but never below the statutory floor — ESIC benefit for ESI-covered persons, P07 IN.EC compensation otherwise (M03 YX-PAY-50); medical evidence is a Special document (YX-LV-09) and the manager sees only the dates. | F103: Not started | H103: =IF(G103<>"",G103,F103) | I103: 0 | J103: 0 | K103: 0
... A223: YX-EXP-16 | B223: M05 | C223: YX-EXP | D223: 6+ | E223: Field-force mileage (B2): a draft mileage line created from M02 field-force distance is not submitted until the employee confirms or edits it (edits keep the system distance for the approver to compare); rates, limits and approvals are those of an ordinary mileage line; one draft per employee per duty day. | F223: Not started | H223: =IF(G223<>"",G223,F223) | I223: 0 | J223: 0 | K223: 0
A224: YX-PERF-01 | B224: M06 | C224: YX-PERF | D224: 6+ | E224: Goal progress is calculated from its key results, or from its children's weighted progress. It is never typed when key results exist. A goal's parent may be owned by anyone (fixes U70, U71). | F224: Tested, code not linked | H224: =IF(G224<>"",G224,F224) | I224: 0 | J224: 2 | K224: 4 | L224: exam-app-org:packages/yx-ui/src/screens/growth/growth.test.tsx exam-app-ws:packages/yx-ui/src/screens/growth/growth.test.tsx
A225: YX-PERF-02 | B225: M06 | C225: YX-PERF | D225: 6+ | E225: Scores include only completed sections. Missing inputs show "pending" and never count as 0. A section without goals is excluded, with a warning (fixes U69, PF-D3). | F225: Tested, code not linked | H225: =IF(G225<>"",G225,F225) | I225: 0 | J225: 2 | K225: 4 | L225: exam-app-org:packages/yx-ui/src/screens/growth/growth.test.tsx exam-app-ws:packages/yx-ui/src/screens/growth/growth.test.tsx
A226: YX-PERF-03 | B226: M06 | C226: YX-PERF | D226: 6+ | E226: The manager rating is a separate stage from peer feedback. Peer input is advisory and never averaged into the manager rating unless the template says so (fixes U72). | F226: Not started | H226: =IF(G226<>"",G226,F226) | I226: 0 | J226: 0 | K226: 0
A227: YX-PERF-04 | B227: M06 | C227: YX-PERF | D227: 6+ | E227: Only nominated and approved reviewers can give 360° feedback on a review. Quick feedback outside a review goes to any colleague, but follows the visibility rule (fixes PF-D1). | F227: UI prototype only | H227: =IF(G227<>"",G227,F227) | I227: 0 | J227: 0 | K227: 2
A228: YX-PERF-05 | B228: M06 | C228: YX-PERF | D228: 6+ | E228: Anonymity per Q4. Anonymous feedback is shown only when at least 3 responses exist for that relationship group. Otherwise it is merged into "others" or held back. | F228: Tested, code not linked | H228: =IF(G228<>"",G228,F228) | I228: 0 | J228: 2 | K228: 2 | L228: exam-app-org:packages/yx-ui/src/screens/growth/growth.test.tsx exam-app-ws:packages/yx-ui/src/screens/growth/growth.test.tsx
A229: YX-PERF-06 | B229: M06 | C229: YX-PERF | D229: 6+ | E229: Each stage has an owner and a deadline, with reminders and escalation via P03. The employee always sees the current stage and the next step (fixes U73). | F229: UI prototype only | H229: =IF(G229<>"",G229,F229) | I229: 0 | J229: 0 | K229: 2
A230: YX-PERF-07 | B230: M06 | C230: YX-PERF | D230: 6+ | E230: The final score maps to a band label (e.g. "Exceeds expectations"). Bands and scale come from the cycle (Q3). | F230: UI prototype only | H230: =IF(G230<>"",G230,F230) | I230: 0 | J230: 0 | K230: 4
A231: YX-PERF-08 | B231: M06 | C231: YX-PERF | D231: 6+ | E231: Any calibration change records the before value, after value, reason and who made it. The employee sees only the released final rating. | F231: UI prototype only | H231: =IF(G231<>"",G231,F231) | I231: 0 | J231: 0 | K231: 4
A232: YX-PERF-09 | B232: M06 | C232: YX-PERF | D232: 6+ | E232: Ratings are released to employees only at the cycle's release step. A released review can only be reopened by HR with a reason, and this is audited. | F232: Not started | H232: =IF(G232<>"",G232,F232) | I232: 0 | J232: 0 | K232: 0
A233: YX-PERF-10 | B233: M06 | C233: YX-PERF | D233: 6+ | E233: Comp proposals come from the matrix (Q6). Changes outside the matrix range need a justification and an extra approval. Approved proposals create dated compensation or promotion changes (P06) and letters (P05). | F233: Tested, code not linked | H233: =IF(G233<>"",G233,F233) | I233: 0 | J233: 2 | K233: 4 | L233: exam-app-org:packages/yx-ui/src/screens/growth/growth.test.tsx exam-app-ws:packages/yx-ui/src/screens/growth/growth.test.tsx
A234: YX-PERF-11 | B234: M06 | C234: YX-PERF | D234: 6+ | E234: A PIP needs HR approval to start, has fixed check-ins and ends with a recorded outcome. "Not met" can start an M01 exit case, but never automatically. | F234: UI prototype only | H234: =IF(G234<>"",G234,F234) | I234: 0 | J234: 0 | K234: 2
A235: YX-PERF-12 | B235: M06 | C235: YX-PERF | D235: 6+ | E235: Cycle funnel counts are clickable and lead to the list of names (fixes U74). | F235: UI prototype only | H235: =IF(G235<>"",G235,F235) | I235: 0 | J235: 0 | K235: 2
A236: YX-PERF-13 | B236: M06 | C236: YX-PERF | D236: 6+ | E236: When a manager leaves or changes mid-cycle, in-flight artefacts transfer on the effective date and each transfer is logged: a pending manager-review stage → new manager (the old manager may be added as a named reviewer for input if still employed); 360° nominations awaiting approval → new manager; calibration sessions the old manager facilitated → HR reassigns; comp proposals they authored → new manager or HR; PIP ownership and check-ins → new manager, HR notified; 1-on-1 threads: shared notes and open action items move, private notes stay with their author; goals whose parent is the old manag | F236: UI prototype only | H236: =IF(G236<>"",G236,F236) | I236: 0 | J236: 0 | K236: 2
A237: YX-PERF-14 | B237: M06 | C237: YX-PERF | D237: 6+ | E237: IDP (B16). An employee has at most one active IDP per period; the employee drafts it, the manager approves it (P03). A course item creates an M07 enrolment request that follows M07 approval and budget rules (YX-LRN-07); learning.enrolment.completed marks the item done and YX-LRN-03 updates the competency. A competency item is done when the competency rating reaches the target level (review or skills test evidence). A mentor item is active only after the mentor accepts; the mentor sees only the items they are named on, never ratings. IDP check-ins reuse 1-on-1s. On a manager change the IDP foll | F237: Not started | H237: =IF(G237<>"",G237,F237) | I237: 0 | J237: 0 | K237: 0
A238: YX-PERF-15 | B238: M06 | C238: YX-PERF | D238: 6+ | E238: Career paths (B16). Paths, steps and required competency levels are company data (D17; starter template labelled as such). An employee's gap for a next role = required level − current rated level per competency; missing ratings show "not assessed", never 0 (as YX-PERF-02). Gaps can be added to the IDP in one click. A path never promotes anyone: promotions still come only from comp review / P06 changes (YX-PERF-10). | F238: UI prototype only | H238: =IF(G238<>"",G238,F238) | I238: 0 | J238: 0 | K238: 2
A239: YX-PERF-16 | B239: M06 | C239: YX-PERF | D239: 6+ | E239: Talent pools and succession (B16). Pool membership comes from the 9-box / calibration outcome or an HR nomination, always with a reason and audited. Membership is Confidential, HR and leadership only; it is shown to the employee only if the company turns on "tell pool members" (D17, off in the starter template). HR can propose a pool member as a successor on an M01 critical position (M01 Q8); readiness is kept in one place (M01 succession_candidates) and shown here read-only. A successor's IDP is linked from the succession view. | F239: Not started | H239: =IF(G239<>"",G239,F239) | I239: 0 | J239: 0 | K239: 0
A240: YX-PERF-17 | B240: M06 | C240: YX-PERF | D240: 6+ | E240: Attrition-risk signal (B16; P10). Opt-in per company. Scored in-region by YukthiX (no external LLM for the score) from permitted inputs only: tenure, time since last promotion / increment, compa-ratio, rating trend, manager changes, internal-mobility applications, engagement survey aggregates (M09, respecting its anonymity). Never used as inputs: Special data (health, disability, POSH, disciplinary, biometrics), protected attributes (gender, age, religion, caste, marital status, maternity / paternity leave) or individual survey answers. Output is a band with top factors, shown to HR only; ever | F240: Not started | H240: =IF(G240<>"",G240,F240) | I240: 0 | J240: 0 | K240: 0
A241: YX-PERF-18 | B241: M06 | C241: YX-PERF | D241: 6+ | E241: Pay equity (C3). Inside a comp review (and in HR analytics), HR and finance approvers see pay gaps by gender, grade, role and location: mean and median, raw and adjusted (same grade and role), both before and after the current proposals. Results are Confidential; groups below the P09 threshold show "suppressed" (YX-MET-04), including in exports. Employees whose pay sits below their grade-and-role peer median by more than a company-set threshold (starter template 10 %) are flagged as advisory for the reviewer; nothing is adjusted automatically. Managers proposing inside their own comp review se | F241: Not started | H241: =IF(G241<>"",G241,F241) | I241: 0 | J241: 0 | K241: 0
A242: YX-PERF-19 | B242: M06 | C242: YX-PERF | D242: 6+ | E242: Market benchmarks (C3; D18). The partner benchmarking feed is a paid add-on (third-party data, D18 (3)); a company may instead upload its own survey data at no charge. HR maps designation / grade / location to the source's job codes. The comp review sheet shows the market P25–P75 range and the market ratio (pay ÷ P50) beside the compa-ratio; the company chooses whether the comp matrix uses internal grade ranges or market position (D17). YukthiX sends no employee-level data to the benchmark partner; only the job-code query goes out. Each figure shows its source and effective date; stale data (o | F242: Not started | H242: =IF(G242<>"",G242,F242) | I242: 0 | J242: 0 | K242: 0
A243: YX-PERF-20 | B243: M06 | C243: YX-PERF | D243: 6+ | E243: Skills library and mapped views (T2). Competencies, T01 question tags and M10 scorecard skills each reference a company_skills row through skill_mappings; a skill in use can't be deleted, only retired or merged, and every view follows. AI skill suggestions (P10 AI credits and data tiers, YX-AI-02) stay pending until the employee or their manager confirms; a rejected suggestion isn't re-offered from the same evidence. Only confirmed skills feed career-path gaps, IDPs, talent pools, M07 recommendations and staffing search, and each skill shows its source (self, manager, test, course, project, AI | F243: UI prototype only | H243: =IF(G243<>"",G243,F243) | I243: 0 | J243: 0 | K243: 2
A244: YX-PERF-21 | B244: M06 | C244: YX-PERF | D244: 6+ | E244: Cycle eligibility and proration (J11). When a cycle starts, each employee gets a review_eligibility record from the company rules (starter template, D17: joined after the 3-month cut-off → excluded or probation review instead; mid-cycle joiner → goals for months served; leaver → closed without a rating unless the company opts in; transfer → both managers' inputs weighted by months; maternity or long leave of 3+ months → protected: no rating lowered for the leave period, not counted in forced distribution). Increments are prorated by eligible months ÷ cycle months unless the rule says full; lea | F244: Tested, code not linked | H244: =IF(G244<>"",G244,F244) | I244: 0 | J244: 2 | K244: 8 | L244: exam-app-org:packages/yx-ui/src/screens/growth/growth.test.tsx exam-app-ws:packages/yx-ui/src/screens/growth/growth.test.tsx
A245: YX-PERF-22 | B245: M06 | C245: YX-PERF | D245: 6+ | E245: Own pay band and pay-gap hooks (T4). With the setting on, an employee sees their own grade's min / mid / max from P01 grade_pay_ranges for their entity and currency on the effective date, and their position (below / within / above, quartile), never anyone else's pay; a grade without a range shows "no range set". The YX-PERF-18 engine exposes gender pay-gap figures as P09 metrics for the legal pay-gap reports (EU Directive, US state formats) and the right-to-information answer (average pay by gender for the same grade / work), with P09 suppression. | F245: Not started | H245: =IF(G245<>"",G245,F245) | I245: 0 | J245: 0 | K245: 0
A246: YX-LRN-01 | B246: M07 | C246: YX-LRN | D246: 6+ | E246: Completion requires meeting the course's completion criteria: attendance ≥ the threshold for sessions, all required items for self-paced courses, and a pass score when an assessment is attached (taken from the enrolment's T03 employee invitation result). An absent attendee is never marked completed (fixes MS-D1). | F246: Tested, code not linked | H246: =IF(G246<>"",G246,F246) | I246: 0 | J246: 2 | K246: 2 | L246: exam-app-org:packages/yx-ui/src/screens/growth/growth.test.tsx exam-app-ws:packages/yx-ui/src/screens/growth/growth.test.tsx
A247: YX-LRN-02 | B247: M07 | C247: YX-LRN | D247: 6+ | E247: Completing a course with a certificate template issues the certificate automatically as a P05 document with QR verification (fixes MS-D2, U86). | F247: Not started | H247: =IF(G247<>"",G247,F247) | I247: 0 | J247: 0 | K247: 0
...

Sheet Design docs
A1: Doc | B1: Title | C1: Roadmap step | D1: Rules | E1: Built + tested | F1: Built, no test | G1: Verify | H1: Not started | I1: % built | J1: Build wave | K1: Design status | L1: File | M1: Notes (you)
A2: M01 | B2: M01 · Core HR & Employee Lifecycle | C2: 2 | D2: 51 | E2: =COUNTIFS(Rules!$B$2:$B$982,$A2,Rules!$H$2:$H$982,"Built +*") | F2: =COUNTIFS(Rules!$B$2:$B$982,$A2,Rules!$H$2:$H$982,"Built,*") | G2: =COUNTIFS(Rules!$B$2:$B$982,$A2,Rules!$H$2:$H$982,"Verify*") | H2: =COUNTIFS(Rules!$B$2:$B$982,$A2,Rules!$H$2:$H$982,"Not started*") | I2: =IF(D2=0,"",E2/D2) | J2: Core HR in wave 1; onboarding, offboarding, F&F, letters, assets in wave 4 (spec §4). | K2: ✅ Decided, 25 Sep 2026. All 8 questions answered (§11). Extended 26 Sep 2026 (gap register, user decision): position management, workforce-planning scenarios, career paths & IDPs, attrition-risk signal (GAP B16, §3.9, wave 5); §11 B16. Career paths, IDPs, talent pools and the attrition-risk signal a | L2: M01-core-hr-and-lifecycle.md
A3: M02 | B3: M02 · Leave & Attendance | C3: 4 | D3: 46 | E3: =COUNTIFS(Rules!$B$2:$B$982,$A3,Rules!$H$2:$H$982,"Built +*") | F3: =COUNTIFS(Rules!$B$2:$B$982,$A3,Rules!$H$2:$H$982,"Built,*") | G3: =COUNTIFS(Rules!$B$2:$B$982,$A3,Rules!$H$2:$H$982,"Verify*") | H3: =COUNTIFS(Rules!$B$2:$B$982,$A3,Rules!$H$2:$H$982,"Not started*") | I3: =IF(D3=0,"",E3/D3) | J3: 2 (with basic mobile), feeding payroll in wave 3. | K3: ✅ Decided (7/7), 25 Sep 2026. The 6 Leave decisions (23 Sep) and the attendance device question (P10 Q4) are already decided. Extended 26 Sep 2026 (gap register, user decision): field-force tracking (GAP B2, §B8, wave 5), auto-rostering, open shifts & shift bidding (GAP B3, §B9, designed now, built | L3: M02-leave-and-attendance.md
A4: M03 | B4: M03 · Payroll & India Statutory | C4: 5 | D4: 84 | E4: =COUNTIFS(Rules!$B$2:$B$982,$A4,Rules!$H$2:$H$982,"Built +*") | F4: =COUNTIFS(Rules!$B$2:$B$982,$A4,Rules!$H$2:$H$982,"Built,*") | G4: =COUNTIFS(Rules!$B$2:$B$982,$A4,Rules!$H$2:$H$982,"Verify*") | H4: =COUNTIFS(Rules!$B$2:$B$982,$A4,Rules!$H$2:$H$982,"Not started*") | I4: =IF(D4=0,"",E4/D4) | J4: 3. The private pilot starts here. | K4: ✅ Decided (8/8), 25 Sep 2026. Extended 26 Sep 2026: consultant / contractor payouts (GAP A8) and always-on digital registers (GAP A9), §11 A8-Q1 / A9-Q2 / A9-Q3. Extended 26 Sep 2026 (gap register, user decision): earned wage access (GAP B10), multi-country payroll readiness with UAE / GCC / US-1099 | L4: M03-payroll-and-statutory.md
A5: M04 | B5: M04 · Mobile App (Employee & Manager) | C5: 6+ | D5: 19 | E5: =COUNTIFS(Rules!$B$2:$B$982,$A5,Rules!$H$2:$H$982,"Built +*") | F5: =COUNTIFS(Rules!$B$2:$B$982,$A5,Rules!$H$2:$H$982,"Built,*") | G5: =COUNTIFS(Rules!$B$2:$B$982,$A5,Rules!$H$2:$H$982,"Verify*") | H5: =COUNTIFS(Rules!$B$2:$B$982,$A5,Rules!$H$2:$H$982,"Not started*") | I5: =IF(D5=0,"",E5/D5) | J5: basic mobile in wave 2 (Time, leave, approvals), and each later module adds its mobile screens in its own wave. No module ships without its employee-facing mobile flow (fixes U95). | K5: ✅ Decided (8/8), 25 Sep 2026. Extended 26 Sep 2026 (gap register, user decision): mobile flows for field force (B2), open shifts & bids (B3), earned wage access (B10), visitor approvals (C1), career / IDP (B16), equity (C4) and M12 timesheets (B1), §3.1; §11 B2 / B3 / B10 / C1 / B1 / B16-C4-B18. Val | L5: M04-mobile-app.md
A6: M05 | B6: M05 · Expenses, Advances & Travel | C6: 6+ | D6: 16 | E6: =COUNTIFS(Rules!$B$2:$B$982,$A6,Rules!$H$2:$H$982,"Built +*") | F6: =COUNTIFS(Rules!$B$2:$B$982,$A6,Rules!$H$2:$H$982,"Built,*") | G6: =COUNTIFS(Rules!$B$2:$B$982,$A6,Rules!$H$2:$H$982,"Verify*") | H6: =COUNTIFS(Rules!$B$2:$B$982,$A6,Rules!$H$2:$H$982,"Not started*") | I6: =IF(D6=0,"",E6/D6) | J6: 5 (mobile-first, M04). Salary advances and loans stay in M03. | K6: ✅ Decided (8/8), 25 Sep 2026. Extended 26 Sep 2026 (gap register, user decision): multi-currency expenses with FX (GAP B18) and field-force distance → mileage lines (GAP B2, M02 §B8); §11 B18 / B2. | L6: M05-expenses-advances-travel.md
A7: M06 | B7: M06 · Performance | C7: 6+ | D7: 22 | E7: =COUNTIFS(Rules!$B$2:$B$982,$A7,Rules!$H$2:$H$982,"Built +*") | F7: =COUNTIFS(Rules!$B$2:$B$982,$A7,Rules!$H$2:$H$982,"Built,*") | G7: =COUNTIFS(Rules!$B$2:$B$982,$A7,Rules!$H$2:$H$982,"Verify*") | H7: =COUNTIFS(Rules!$B$2:$B$982,$A7,Rules!$H$2:$H$982,"Not started*") | I7: =IF(D7=0,"",E7/D7) | J7: 5. Basic (guided) calibration was deliberately moved to wave 5 by Q5; only the 9-box and enforced distribution remain in wave 6 (spec §4). | K7: ✅ Decided (8/8), 25 Sep 2026. Extended 26 Sep 2026: career paths & IDPs, talent pools / succession link, attrition-risk signal (GAP B16); pay-equity analysis and compensation benchmarking (GAP C3); §11 B16 / C3. | L7: M06-performance.md
A8: M07 | B8: M07 · Learning & Development | C8: 6+ | D8: 15 | E8: =COUNTIFS(Rules!$B$2:$B$982,$A8,Rules!$H$2:$H$982,"Built +*") | F8: =COUNTIFS(Rules!$B$2:$B$982,$A8,Rules!$H$2:$H$982,"Built,*") | G8: =COUNTIFS(Rules!$B$2:$B$982,$A8,Rules!$H$2:$H$982,"Verify*") | H8: =COUNTIFS(Rules!$B$2:$B$982,$A8,Rules!$H$2:$H$982,"Not started*") | I8: =IF(D8=0,"",E8/D8) | J8: 5. | K8: ✅ Decided (8/8), 25 Sep 2026. Extended 26 Sep 2026: content marketplace & provider connectors, live-class auto-creation, gamification (GAP C2); Open Badges 3.0 / Credly and an LTI 1.3 tool (GAP B15 part); §11 C2 / B15. | L8: M07-learning-and-development.md
A9: M08 | B9: M08 · Helpdesk, Grievance, POSH, Disciplinary & Policies | C9: 3b | D9: 32 | E9: =COUNTIFS(Rules!$B$2:$B$982,$A9,Rules!$H$2:$H$982,"Built +*") | F9: =COUNTIFS(Rules!$B$2:$B$982,$A9,Rules!$H$2:$H$982,"Built,*") | G9: =COUNTIFS(Rules!$B$2:$B$982,$A9,Rules!$H$2:$H$982,"Verify*") | H9: =COUNTIFS(Rules!$B$2:$B$982,$A9,Rules!$H$2:$H$982,"Not started*") | I9: =IF(D9=0,"",E9/D9) | J9: POSH and workplace accident / injury (J6) in wave 4; helpdesk, grievance, disciplinary, policies and whistleblower in wave 5 (spec §4). | K9: ✅ Decided (8/8), 25 Sep 2026. Correction C1 (validation pass 3), 28 Sep 2026: IR Code (P07 IN.IR, in force 21 Nov 2025) Grievance Redressal Committee for 20+ workers and standing orders at 300+ workers linked to the misconduct matrix (YX-CASE-12/13); §11 C1. Validation pass 3 Must J6, 28 Sep 2026: n | L9: M08-helpdesk-cases-policies.md
A10: M09 | B10: M09 · Engage: Communication, Recognition & Surveys | C10: 6+ | D10: 11 | E10: =COUNTIFS(Rules!$B$2:$B$982,$A10,Rules!$H$2:$H$982,"Built +*") | F10: =COUNTIFS(Rules!$B$2:$B$982,$A10,Rules!$H$2:$H$982,"Built,*") | G10: =COUNTIFS(Rules!$B$2:$B$982,$A10,Rules!$H$2:$H$982,"Verify*") | H10: =COUNTIFS(Rules!$B$2:$B$982,$A10,Rules!$H$2:$H$982,"Not started*") | I10: =IF(D10=0,"",E10/D10) | J10: 5. Simple announcements already ship with P04 in wave 1. | K10: ✅ Decided (8/8), 25 Sep 2026. | L10: M09-engage.md
A11: M10 | B11: M10 · ATS: Internal Hiring, Staffing Desk & Client Helpdesk | C11: 6+ | D11: 45 | E11: =COUNTIFS(Rules!$B$2:$B$982,$A11,Rules!$H$2:$H$982,"Built +*") | F11: =COUNTIFS(Rules!$B$2:$B$982,$A11,Rules!$H$2:$H$982,"Built,*") | G11: =COUNTIFS(Rules!$B$2:$B$982,$A11,Rules!$H$2:$H$982,"Verify*") | H11: =COUNTIFS(Rules!$B$2:$B$982,$A11,Rules!$H$2:$H$982,"Not started*") | I11: =IF(D11=0,"",E11/D11) | J11: 7, after HRMS wave 5 (spec §4, P2-6). The internal ATS already exists in the exam app. This doc defines the deltas: what we keep, what we change so it becomes part of HRMS, and what is new. | K11: ✅ Decided (8/8), 25 Sep 2026. Extended 26 Sep 2026: talent CRM, job-board connectors and panel auto-slotting (GAP B8); vendor / sub-vendor portal for the staffing desk (GAP C7, reversing the spec's "out of scope"); §11 B8 / C7. Validation pass 3 Must (T10), founder decision 28 Sep 2026: identity cha | L11: M10-ats.md
A12: M11 | B12: M11 · Benefits Administration & Flexible Benefit Plan | C12: 6+ | D12: 11 | E12: =COUNTIFS(Rules!$B$2:$B$982,$A12,Rules!$H$2:$H$982,"Built +*") | F12: =COUNTIFS(Rules!$B$2:$B$982,$A12,Rules!$H$2:$H$982,"Built,*") | G12: =COUNTIFS(Rules!$B$2:$B$982,$A12,Rules!$H$2:$H$982,"Verify*") | H12: =COUNTIFS(Rules!$B$2:$B$982,$A12,Rules!$H$2:$H$982,"Not started*") | I12: =IF(D12=0,"",E12/D12) | J12: 3 (with payroll, for the pilot). Insurer / broker connectors can follow in a later wave. | K12: ✅ Decided (5/5), 26 Sep 2026. | L12: M11-benefits-fbp.md
A13: M12 | B13: M12 · Projects & Timesheets | C13: 6+ | D13: 17 | E13: =COUNTIFS(Rules!$B$2:$B$982,$A13,Rules!$H$2:$H$982,"Built +*") | F13: =COUNTIFS(Rules!$B$2:$B$982,$A13,Rules!$H$2:$H$982,"Built,*") | G13: =COUNTIFS(Rules!$B$2:$B$982,$A13,Rules!$H$2:$H$982,"Verify*") | H13: =COUNTIFS(Rules!$B$2:$B$982,$A13,Rules!$H$2:$H$982,"Not started*") | I13: =IF(D13=0,"",E13/D13) | J13: 5. | K13: ✅ Decided (by principle), 26 Sep 2026. The user decided on 26 Sep 2026 to include GAP-REGISTER B1; the 4 design questions (§10) were settled by principle (D17 / D18) with the recommended options (§11). Validation pass 3 Shoulds added 28 Sep 2026 (§8b). | L13: M12-projects-timesheets.md
A14: M13 | B14: M13 · Contract Labour (CLRA) — Principal-Employer Compliance | C14: 6+ | D14: 15 | E14: =COUNTIFS(Rules!$B$2:$B$982,$A14,Rules!$H$2:$H$982,"Built +*") | F14: =COUNTIFS(Rules!$B$2:$B$982,$A14,Rules!$H$2:$H$982,"Built,*") | G14: =COUNTIFS(Rules!$B$2:$B$982,$A14,Rules!$H$2:$H$982,"Verify*") | H14: =COUNTIFS(Rules!$B$2:$B$982,$A14,Rules!$H$2:$H$982,"Not started*") | I14: =IF(D14=0,"",E14/D14) | J14: 5. | K14: ✅ Decided (by principle), 26 Sep 2026. 4 questions decided by principle (D17 / D18), §11. Correction C1 (validation pass 3), 28 Sep 2026: contract labour is governed by the OSH Code (contract-labour chapter) since 21 Nov 2025; the design maps to it (§1 mapping, YX-CLRA-13); §11 C1. Validation pass 3 | L14: M13-contract-labour-clra.md
A15: M14 | B15: M14 · YukthiX Service Desk (ITSM + ESM) | C15: 3b | D15: 0 | E15: =COUNTIFS(Rules!$B$2:$B$982,$A15,Rules!$H$2:$H$982,"Built +*") | F15: =COUNTIFS(Rules!$B$2:$B$982,$A15,Rules!$H$2:$H$982,"Built,*") | G15: =COUNTIFS(Rules!$B$2:$B$982,$A15,Rules!$H$2:$H$982,"Verify*") | H15: =COUNTIFS(Rules!$B$2:$B$982,$A15,Rules!$H$2:$H$982,"Not started*") | I15: =IF(D15=0,"",E15/D15) | K15: 📝 Scope agreed with the founder, 6 Oct 2026. Detailed design (rules, data model, decisions) to be written before the build, in the same format as the other M docs. | L15: M14-itsm-service-desk.md
A16: P01 | B16: P01 · Tenancy & Organisation Model | C16: 0, 2 | D16: 27 | E16: =COUNTIFS(Rules!$B$2:$B$982,$A16,Rules!$H$2:$H$982,"Built +*") | F16: =COUNTIFS(Rules!$B$2:$B$982,$A16,Rules!$H$2:$H$982,"Built,*") | G16: =COUNTIFS(Rules!$B$2:$B$982,$A16,Rules!$H$2:$H$982,"Verify*") | H16: =COUNTIFS(Rules!$B$2:$B$982,$A16,Rules!$H$2:$H$982,"Not started*") | I16: =IF(D16=0,"",E16/D16) | K16: ✅ Decided, 24 Sep 2026. All 8 questions answered (§11). Validation pass 3 Must (J15), founder decision 28 Sep 2026: one persons record per tenant with role attachments, matching / merge rules, conversions with history, total-workforce view (§4.5a, YX-ORG-26 / 27); §11 J15. Validation pass 3 Shoulds | L16: P01-tenancy-and-organisation.md
A17: P02 | B17: P02 · Roles, Data Visibility & Privacy | C17: 2 | D17: 38 | E17: =COUNTIFS(Rules!$B$2:$B$982,$A17,Rules!$H$2:$H$982,"Built +*") | F17: =COUNTIFS(Rules!$B$2:$B$982,$A17,Rules!$H$2:$H$982,"Built,*") | G17: =COUNTIFS(Rules!$B$2:$B$982,$A17,Rules!$H$2:$H$982,"Verify*") | H17: =COUNTIFS(Rules!$B$2:$B$982,$A17,Rules!$H$2:$H$982,"Not started*") | I17: =IF(D17=0,"",E17/D17) | K17: ✅ Decided, 24 Sep 2026. All 8 questions answered (§11). Extended 26 Sep 2026 (gap-register user decision): DPDP / GDPR programme tooling (B12, §6.1), §11 row B12. Corrected 28 Sep 2026 (validation pass 3, C3): DPDP Rules 2025 dated milestones and readiness plan (§6.2), YX-SEC-32 breach clocks, YX-SE | L17: P02-access-visibility-privacy.md
A18: P03 | B18: P03 · Workflow & Approval Engine | C18: 4 | D18: 19 | E18: =COUNTIFS(Rules!$B$2:$B$982,$A18,Rules!$H$2:$H$982,"Built +*") | F18: =COUNTIFS(Rules!$B$2:$B$982,$A18,Rules!$H$2:$H$982,"Built,*") | G18: =COUNTIFS(Rules!$B$2:$B$982,$A18,Rules!$H$2:$H$982,"Verify*") | H18: =COUNTIFS(Rules!$B$2:$B$982,$A18,Rules!$H$2:$H$982,"Not started*") | I18: =IF(D18=0,"",E18/D18) | K18: ✅ Decided, 24 Sep 2026. All 8 questions answered (§11). | L18: P03-workflow-approval-engine.md
A19: P04 | B19: P04 · Notification Engine | C19: 1 | D19: 17 | E19: =COUNTIFS(Rules!$B$2:$B$982,$A19,Rules!$H$2:$H$982,"Built +*") | F19: =COUNTIFS(Rules!$B$2:$B$982,$A19,Rules!$H$2:$H$982,"Built,*") | G19: =COUNTIFS(Rules!$B$2:$B$982,$A19,Rules!$H$2:$H$982,"Verify*") | H19: =COUNTIFS(Rules!$B$2:$B$982,$A19,Rules!$H$2:$H$982,"Not started*") | I19: =IF(D19=0,"",E19/D19) | K19: ✅ Decided, 24 Sep 2026. All 8 questions answered (§11). Extended 26 Sep 2026 (gap-register user decision): password-protected payslip PDF by email as a company option (B19, §4.5b), Slack & Microsoft Teams apps (B9, §4.9), desk-UI internationalisation (B18 part, §4.10); §11 rows B19 / B9 / B18. | L19: P04-notification-engine.md
A20: P05 | B20: P05 · Letters, Documents & E-sign | C20: 6+ | D20: 19 | E20: =COUNTIFS(Rules!$B$2:$B$982,$A20,Rules!$H$2:$H$982,"Built +*") | F20: =COUNTIFS(Rules!$B$2:$B$982,$A20,Rules!$H$2:$H$982,"Built,*") | G20: =COUNTIFS(Rules!$B$2:$B$982,$A20,Rules!$H$2:$H$982,"Verify*") | H20: =COUNTIFS(Rules!$B$2:$B$982,$A20,Rules!$H$2:$H$982,"Not started*") | I20: =IF(D20=0,"",E20/D20) | K20: ✅ Decided, 24 Sep 2026. All 8 questions answered (§11). | L20: P05-letters-documents-esign.md
A21: P06 | B21: P06 · Effective-Dated History & Scheduled Changes | C21: 2 | D21: 15 | E21: =COUNTIFS(Rules!$B$2:$B$982,$A21,Rules!$H$2:$H$982,"Built +*") | F21: =COUNTIFS(Rules!$B$2:$B$982,$A21,Rules!$H$2:$H$982,"Built,*") | G21: =COUNTIFS(Rules!$B$2:$B$982,$A21,Rules!$H$2:$H$982,"Verify*") | H21: =COUNTIFS(Rules!$B$2:$B$982,$A21,Rules!$H$2:$H$982,"Not started*") | I21: =IF(D21=0,"",E21/D21) | K21: ✅ Decided, 25 Sep 2026. All 8 questions answered (§11). | L21: P06-effective-dated-history.md
A22: P07 | B22: P07 · Statutory Rules as Dated Data (Country Packs) | C22: 4, 5 | D22: 32 | E22: =COUNTIFS(Rules!$B$2:$B$982,$A22,Rules!$H$2:$H$982,"Built +*") | F22: =COUNTIFS(Rules!$B$2:$B$982,$A22,Rules!$H$2:$H$982,"Built,*") | G22: =COUNTIFS(Rules!$B$2:$B$982,$A22,Rules!$H$2:$H$982,"Verify*") | H22: =COUNTIFS(Rules!$B$2:$B$982,$A22,Rules!$H$2:$H$982,"Not started*") | I22: =IF(D22=0,"",E22/D22) | K22: ✅ Decided, 25 Sep 2026. All 8 questions answered (§11). Extended 26 Sep 2026: non-salary TDS (GAP A8) and IN.REGISTERS (GAP A9), §11 A8-Q1 / A9-Q2 / A9-Q3. Extended 26 Sep 2026 (gap-register user decision): labour-law advisory feed and IN.CLRA (B17, §4.3a), ESOP perquisite valuation and country-pack | L22: P07-statutory-rules-as-data.md
A23: P08 | B23: P08 · Period Locks & Audit | C23: 5 | D23: 18 | E23: =COUNTIFS(Rules!$B$2:$B$982,$A23,Rules!$H$2:$H$982,"Built +*") | F23: =COUNTIFS(Rules!$B$2:$B$982,$A23,Rules!$H$2:$H$982,"Built,*") | G23: =COUNTIFS(Rules!$B$2:$B$982,$A23,Rules!$H$2:$H$982,"Verify*") | H23: =COUNTIFS(Rules!$B$2:$B$982,$A23,Rules!$H$2:$H$982,"Not started*") | I23: =IF(D23=0,"",E23/D23) | K23: ✅ Decided, 25 Sep 2026. All 8 questions answered (§11). | L23: P08-period-locks-and-audit.md
A24: P09 | B24: P09 · Metric Layer & Analytics Platform | C24: 6+ | D24: 24 | E24: =COUNTIFS(Rules!$B$2:$B$982,$A24,Rules!$H$2:$H$982,"Built +*") | F24: =COUNTIFS(Rules!$B$2:$B$982,$A24,Rules!$H$2:$H$982,"Built,*") | G24: =COUNTIFS(Rules!$B$2:$B$982,$A24,Rules!$H$2:$H$982,"Verify*") | H24: =COUNTIFS(Rules!$B$2:$B$982,$A24,Rules!$H$2:$H$982,"Not started*") | I24: =IF(D24=0,"",E24/D24) | K24: ✅ Decided, 25 Sep 2026. All 8 questions answered (§11). Extended 26 Sep 2026 (gap register, user decision): DEI dashboard template and pay-gap metric (GAP C3), tenant-health metrics feed for customer success (C8), workforce-planning / attrition-risk metric references (B16) and AI-quality metrics (B1 | L24: P09-metric-layer-analytics.md
A25: P10 | B25: P10 · AI Layer & Integration Hub (HR additions) | C25: 6+ | D25: 27 | E25: =COUNTIFS(Rules!$B$2:$B$982,$A25,Rules!$H$2:$H$982,"Built +*") | F25: =COUNTIFS(Rules!$B$2:$B$982,$A25,Rules!$H$2:$H$982,"Built,*") | G25: =COUNTIFS(Rules!$B$2:$B$982,$A25,Rules!$H$2:$H$982,"Verify*") | H25: =COUNTIFS(Rules!$B$2:$B$982,$A25,Rules!$H$2:$H$982,"Not started*") | I25: =IF(D25=0,"",E25/D25) | K25: ✅ Decided, 25 Sep 2026. All 8 questions answered (§11). Extended 26 Sep 2026 (gap-register user decision): AI governance (B13, §A4), Slack / Teams apps (B9), external-ATS connectors (B6), earned wage access (B10), QuickBooks / Busy / Marg, mailbox sync, Aadhaar eKYC / DigiLocker (C6); §11 rows B13 / | L25: P10-ai-layer-integration-hub.md
A26: P11 | B26: P11 · API-First (Headless) Architecture | C26: 6+ | D26: 16 | E26: =COUNTIFS(Rules!$B$2:$B$982,$A26,Rules!$H$2:$H$982,"Built +*") | F26: =COUNTIFS(Rules!$B$2:$B$982,$A26,Rules!$H$2:$H$982,"Built,*") | G26: =COUNTIFS(Rules!$B$2:$B$982,$A26,Rules!$H$2:$H$982,"Verify*") | H26: =COUNTIFS(Rules!$B$2:$B$982,$A26,Rules!$H$2:$H$982,"Not started*") | I26: =IF(D26=0,"",E26/D26) | J26: the conventions start in wave 1. Every module after that ships with its API. The public developer portal opens with the pilot in wave 3. | K26: ✅ Decided (8/8), 25 Sep 2026 — TR1 (Salesforce-style extensibility) open for team review. Extended 26 Sep 2026 (gap-register user decision): custom-object APIs cross-reference to P18 (B20), YX-API-16, §11 row B20. | L26: P11-api-first-headless.md
A27: P12 | B27: P12 · Identity, Authentication & Security Programme | C27: 1 | D27: 23 | E27: =COUNTIFS(Rules!$B$2:$B$982,$A27,Rules!$H$2:$H$982,"Built +*") | F27: =COUNTIFS(Rules!$B$2:$B$982,$A27,Rules!$H$2:$H$982,"Built,*") | G27: =COUNTIFS(Rules!$B$2:$B$982,$A27,Rules!$H$2:$H$982,"Verify*") | H27: =COUNTIFS(Rules!$B$2:$B$982,$A27,Rules!$H$2:$H$982,"Not started*") | I27: =IF(D27=0,"",E27/D27) | J27: identity core in wave 1. Security programme milestones are tied to the pilot (wave 3) and public launch. | K27: ✅ Decided (8/8), 26 Sep 2026. Corrected 28 Sep 2026 (validation pass 3, C3): log retention at least 1 year (DPDP Rules 2025) and DPDP breach clocks; Q6 amended, YX-SECOPS-07 updated. Validation pass 3 Shoulds added 28 Sep 2026 (§8b). | L27: P12-identity-security.md
A28: P13 | B28: P13 · Infrastructure & Operations — brief for the engineering team | C28: 6+ | D28: 0 | E28: =COUNTIFS(Rules!$B$2:$B$982,$A28,Rules!$H$2:$H$982,"Built +*") | F28: =COUNTIFS(Rules!$B$2:$B$982,$A28,Rules!$H$2:$H$982,"Built,*") | G28: =COUNTIFS(Rules!$B$2:$B$982,$A28,Rules!$H$2:$H$982,"Verify*") | H28: =COUNTIFS(Rules!$B$2:$B$982,$A28,Rules!$H$2:$H$982,"Not started*") | I28: =IF(D28=0,"",E28/D28) | K28: ⏸ Parked for the engineering team (26 Sep 2026). The founder asked for this doc to be decided by the team, not in the product design sessions. | L28: P13-infrastructure-operations-TEAM-BRIEF.md
A29: P14 | B29: P14 · Billing, Tenant Lifecycle & Platform Console | C29: 3 | D29: 38 | E29: =COUNTIFS(Rules!$B$2:$B$982,$A29,Rules!$H$2:$H$982,"Built +*") | F29: =COUNTIFS(Rules!$B$2:$B$982,$A29,Rules!$H$2:$H$982,"Built,*") | G29: =COUNTIFS(Rules!$B$2:$B$982,$A29,Rules!$H$2:$H$982,"Verify*") | H29: =COUNTIFS(Rules!$B$2:$B$982,$A29,Rules!$H$2:$H$982,"Not started*") | I29: =IF(D29=0,"",E29/D29) | J29: billing core and tenant lifecycle before the wave-3 paid pilot. Self-serve sign-up and trial before public launch. | K29: ✅ Decided (8/8), 26 Sep 2026. Extended 26 Sep 2026 (gap register, user decision): customer-success tooling (GAP C8: health score, in-app messages to tenant admins, churn-risk alerts; §3, YX-CONSOLE-05/06, flow 6) and new partner add-ons in the catalogue (earned wage access B10, compensation benchmar | L29: P14-billing-tenant-lifecycle.md
A30: P15 | B30: P15 · Migration, Implementation & Sandbox | C30: 6+ | D30: 15 | E30: =COUNTIFS(Rules!$B$2:$B$982,$A30,Rules!$H$2:$H$982,"Built +*") | F30: =COUNTIFS(Rules!$B$2:$B$982,$A30,Rules!$H$2:$H$982,"Built,*") | G30: =COUNTIFS(Rules!$B$2:$B$982,$A30,Rules!$H$2:$H$982,"Verify*") | H30: =COUNTIFS(Rules!$B$2:$B$982,$A30,Rules!$H$2:$H$982,"Not started*") | I30: =IF(D30=0,"",E30/D30) | K30: ✅ Decided (6/6), 26 Sep 2026. Market analysis addition (G11, 26 Sep 2026): mappers for Freshteam, OrangeHRM, Horilla and a generic ATS CSV, plus a "Freshteam switch kit" page (YX-MIG-14; §11 G11). Validation pass 3 Must J3, 28 Sep 2026: month-wise as-paid pay lines per component for the current tax | L30: P15-migration-implementation-sandbox.md
A31: P16 | B31: P16 · Partner & Accountant Console | C31: 6+ | D31: 14 | E31: =COUNTIFS(Rules!$B$2:$B$982,$A31,Rules!$H$2:$H$982,"Built +*") | F31: =COUNTIFS(Rules!$B$2:$B$982,$A31,Rules!$H$2:$H$982,"Built,*") | G31: =COUNTIFS(Rules!$B$2:$B$982,$A31,Rules!$H$2:$H$982,"Verify*") | H31: =COUNTIFS(Rules!$B$2:$B$982,$A31,Rules!$H$2:$H$982,"Not started*") | I31: =IF(D31=0,"",E31/D31) | K31: ✅ Decided (6/6), 26 Sep 2026. Q5 and Q6 are decided by principle (D15 / D17). | L31: P16-partner-accountant-console.md
A32: P17 | B32: P17 · Global Search & Command Palette | C32: 6+ | D32: 12 | E32: =COUNTIFS(Rules!$B$2:$B$982,$A32,Rules!$H$2:$H$982,"Built +*") | F32: =COUNTIFS(Rules!$B$2:$B$982,$A32,Rules!$H$2:$H$982,"Built,*") | G32: =COUNTIFS(Rules!$B$2:$B$982,$A32,Rules!$H$2:$H$982,"Verify*") | H32: =COUNTIFS(Rules!$B$2:$B$982,$A32,Rules!$H$2:$H$982,"Not started*") | I32: =IF(D32=0,"",E32/D32) | J32: wave 2 (records and actions for the modules live by then); every later module registers its sources in its own wave. | K32: ✅ Decided (by principle), 26 Sep 2026. The 3 questions (§10) were decided by spec principles D17 / D18 and the user decision of 26 Sep 2026 (all B items included, recommended options adopted); see §11. | L32: P17-global-search.md
A33: P18 | B33: P18 · Custom Objects, Form & Page-Layout Builder | C33: 6+ | D33: 11 | E33: =COUNTIFS(Rules!$B$2:$B$982,$A33,Rules!$H$2:$H$982,"Built +*") | F33: =COUNTIFS(Rules!$B$2:$B$982,$A33,Rules!$H$2:$H$982,"Built,*") | G33: =COUNTIFS(Rules!$B$2:$B$982,$A33,Rules!$H$2:$H$982,"Verify*") | H33: =COUNTIFS(Rules!$B$2:$B$982,$A33,Rules!$H$2:$H$982,"Not started*") | I33: =IF(D33=0,"",E33/D33) | J33: wave 6. Custom *fields* on core entities (P01) remain wave 1; P18 adds objects, layouts and builders on top. | K33: ✅ Decided (by principle), 26 Sep 2026. The 4 questions (§10) were decided by spec principles D17 / D18 and the user decision of 26 Sep 2026 (B20 designed now, built in wave 6; recommended options adopted); see §11. | L33: P18-custom-objects-form-builder.md
A34: P19 | B34: P19 · Policy Rule Builder | C34: 6+ | D34: 14 | E34: =COUNTIFS(Rules!$B$2:$B$982,$A34,Rules!$H$2:$H$982,"Built +*") | F34: =COUNTIFS(Rules!$B$2:$B$982,$A34,Rules!$H$2:$H$982,"Built,*") | G34: =COUNTIFS(Rules!$B$2:$B$982,$A34,Rules!$H$2:$H$982,"Verify*") | H34: =COUNTIFS(Rules!$B$2:$B$982,$A34,Rules!$H$2:$H$982,"Not started*") | I34: =IF(D34=0,"",E34/D34) | K34: ✅ Decided (6/6), 26 Sep 2026. Q4–Q6 are decided by principle (D17 / D18 / P06). | L34: P19-policy-rule-builder.md
A35: P20 | B35: P20 · Growth, Trial & Customer Operations | C35: 3 | D35: 17 | E35: =COUNTIFS(Rules!$B$2:$B$982,$A35,Rules!$H$2:$H$982,"Built +*") | F35: =COUNTIFS(Rules!$B$2:$B$982,$A35,Rules!$H$2:$H$982,"Built,*") | G35: =COUNTIFS(Rules!$B$2:$B$982,$A35,Rules!$H$2:$H$982,"Verify*") | H35: =COUNTIFS(Rules!$B$2:$B$982,$A35,Rules!$H$2:$H$982,"Not started*") | I35: =IF(D35=0,"",E35/D35) | K35: ✅ Decided (5/5), 28 Sep 2026 (founder decisions on validation pass 3 Musts S1, S2, S3, S10, S11). Validation pass 3 Shoulds added 28 Sep 2026 (§8b). | L35: P20-growth-trial-customer-operations.md
A36: P21 | B36: P21 · Global Readiness | C36: 6+ | D36: 16 | E36: =COUNTIFS(Rules!$B$2:$B$982,$A36,Rules!$H$2:$H$982,"Built +*") | F36: =COUNTIFS(Rules!$B$2:$B$982,$A36,Rules!$H$2:$H$982,"Built,*") | G36: =COUNTIFS(Rules!$B$2:$B$982,$A36,Rules!$H$2:$H$982,"Verify*") | H36: =COUNTIFS(Rules!$B$2:$B$982,$A36,Rules!$H$2:$H$982,"Not started*") | I36: =IF(D36=0,"",E36/D36) | K36: ✅ Decided by founder 28 Sep 2026: design now, build before the first customer in each region (validation pass 3 Shoulds, "Global prerequisites", option A). | L36: P21-global-readiness.md
A37: P22 | B37: P22 · Workflow Studio & AI Assistant | C37: 6+ | D37: 20 | E37: =COUNTIFS(Rules!$B$2:$B$982,$A37,Rules!$H$2:$H$982,"Built +*") | F37: =COUNTIFS(Rules!$B$2:$B$982,$A37,Rules!$H$2:$H$982,"Built,*") | G37: =COUNTIFS(Rules!$B$2:$B$982,$A37,Rules!$H$2:$H$982,"Verify*") | H37: =COUNTIFS(Rules!$B$2:$B$982,$A37,Rules!$H$2:$H$982,"Not started*") | I37: =IF(D37=0,"",E37/D37) | K37: ✅ Decided (founder decisions 1–3), 28 Sep 2026. | L37: P22-workflow-studio-ai-assistant.md
A38: P23 | B38: P23 · Employee & Manager Assistants and Marketplaces | C38: 6+ | D38: 19 | E38: =COUNTIFS(Rules!$B$2:$B$982,$A38,Rules!$H$2:$H$982,"Built +*") | F38: =COUNTIFS(Rules!$B$2:$B$982,$A38,Rules!$H$2:$H$982,"Built,*") | G38: =COUNTIFS(Rules!$B$2:$B$982,$A38,Rules!$H$2:$H$982,"Verify*") | H38: =COUNTIFS(Rules!$B$2:$B$982,$A38,Rules!$H$2:$H$982,"Not started*") | I38: =IF(D38=0,"",E38/D38) | K38: ✅ Decided (founder selected these 9 features), 28 Sep 2026. | L38: P23-employee-manager-assistants-marketplaces.md
A39: T01 | B39: T01 · Question Bank & Content | C39: 6+ | D39: 17 | E39: =COUNTIFS(Rules!$B$2:$B$982,$A39,Rules!$H$2:$H$982,"Built +*") | F39: =COUNTIFS(Rules!$B$2:$B$982,$A39,Rules!$H$2:$H$982,"Built,*") | G39: =COUNTIFS(Rules!$B$2:$B$982,$A39,Rules!$H$2:$H$982,"Verify*") | H39: =COUNTIFS(Rules!$B$2:$B$982,$A39,Rules!$H$2:$H$982,"Not started*") | I39: =IF(D39=0,"",E39/D39) | K39: ✅ Decided (8/8), 25 Sep 2026. Extended 26 Sep 2026 with GAP-REGISTER B4 (job-role profiles for starter tests / JD assembly) and B14 (language proficiency and typing item types) — see §3 "Gap-register extensions" and §11. | L39: T01-question-bank.md
A40: T02 | B40: T02 · Test Builder, Adaptive Testing & Psychometrics | C40: 6+ | D40: 19 | E40: =COUNTIFS(Rules!$B$2:$B$982,$A40,Rules!$H$2:$H$982,"Built +*") | F40: =COUNTIFS(Rules!$B$2:$B$982,$A40,Rules!$H$2:$H$982,"Built,*") | G40: =COUNTIFS(Rules!$B$2:$B$982,$A40,Rules!$H$2:$H$982,"Verify*") | H40: =COUNTIFS(Rules!$B$2:$B$982,$A40,Rules!$H$2:$H$982,"Not started*") | I40: =IF(D40=0,"",E40/D40) | K40: ✅ Decided (8/8), 25 Sep 2026. Extended 26 Sep 2026 with GAP-REGISTER B4 (starter tests, JD-based assembly, sectional cut-offs) and B15 (equating across parallel forms, cut-score studies) — see §3 "Gap-register extensions" and §11. Personality / behavioural psychometrics are T06; fairness / validity | L40: T02-test-builder-adaptive.md
A41: T03 | B41: T03 · Test Delivery: Scheduling, Drives, Continuity & Accessibility | C41: 6+ | D41: 23 | E41: =COUNTIFS(Rules!$B$2:$B$982,$A41,Rules!$H$2:$H$982,"Built +*") | F41: =COUNTIFS(Rules!$B$2:$B$982,$A41,Rules!$H$2:$H$982,"Built,*") | G41: =COUNTIFS(Rules!$B$2:$B$982,$A41,Rules!$H$2:$H$982,"Verify*") | H41: =COUNTIFS(Rules!$B$2:$B$982,$A41,Rules!$H$2:$H$982,"Not started*") | I41: =IF(D41=0,"",E41/D41) | K41: ✅ Decided (8/8), 25 Sep 2026. Extended 26 Sep 2026 with GAP-REGISTER B7 (campus drive kit, native candidate app) and C5 (test-centre / offline hybrid mode, invigilator app, post-test candidate survey) — see §3 "Gap-register extensions" and §11. These amend Q3 (offline centre mode now in scope) and Q | L41: T03-delivery.md
A42: T04 | B42: T04 · Proctoring Controls, AI-Assistance Detection & Monitoring | C42: 6+ | D42: 20 | E42: =COUNTIFS(Rules!$B$2:$B$982,$A42,Rules!$H$2:$H$982,"Built +*") | F42: =COUNTIFS(Rules!$B$2:$B$982,$A42,Rules!$H$2:$H$982,"Built,*") | G42: =COUNTIFS(Rules!$B$2:$B$982,$A42,Rules!$H$2:$H$982,"Verify*") | H42: =COUNTIFS(Rules!$B$2:$B$982,$A42,Rules!$H$2:$H$982,"Not started*") | I42: =IF(D42=0,"",E42/D42) | K42: ✅ Decided (8/8), 25 Sep 2026. Extended 26 Sep 2026 with GAP-REGISTER B5 (object detection, gaze, numeric integrity score) and C5 (keystroke-dynamics signal, AI-allowed test mode) — see §3 "Gap-register extensions" and §11. The session report PDF is in T05; the secure desktop client is T08 (not desig | L42: T04-proctoring-monitoring.md
A43: T05 | B43: T05 · Integrity, Evaluation & Outcomes | C43: 6+ | D43: 32 | E43: =COUNTIFS(Rules!$B$2:$B$982,$A43,Rules!$H$2:$H$982,"Built +*") | F43: =COUNTIFS(Rules!$B$2:$B$982,$A43,Rules!$H$2:$H$982,"Built,*") | G43: =COUNTIFS(Rules!$B$2:$B$982,$A43,Rules!$H$2:$H$982,"Verify*") | H43: =COUNTIFS(Rules!$B$2:$B$982,$A43,Rules!$H$2:$H$982,"Not started*") | I43: =IF(D43=0,"",E43/D43) | K43: ✅ Decided (8/8), 25 Sep 2026. Extended 26 Sep 2026 with GAP-REGISTER B5 (session report PDF), B6 (ATS connectors, assessment webhooks), B14 (CEFR and typing scoring), A13 (fairness & validity analytics), B15 (digital badges, LTI 1.3 tool) and C5 (AI-allowed mode scoring) — see §3 "Gap-register exten | L43: T05-integrity-evaluation-outcomes.md
A44: T06 | B44: T06 · Psychometric & Behavioural Assessments | C44: 6+ | D44: 11 | E44: =COUNTIFS(Rules!$B$2:$B$982,$A44,Rules!$H$2:$H$982,"Built +*") | F44: =COUNTIFS(Rules!$B$2:$B$982,$A44,Rules!$H$2:$H$982,"Built,*") | G44: =COUNTIFS(Rules!$B$2:$B$982,$A44,Rules!$H$2:$H$982,"Verify*") | H44: =COUNTIFS(Rules!$B$2:$B$982,$A44,Rules!$H$2:$H$982,"Not started*") | I44: =IF(D44=0,"",E44/D44) | K44: ✅ Decided (6/6), 26 Sep 2026. | L44: T06-psychometric-assessments.md
A45: T07 | B45: T07 · Project-Based Coding & Live Technical Interview | C45: 6+ | D45: 9 | E45: =COUNTIFS(Rules!$B$2:$B$982,$A45,Rules!$H$2:$H$982,"Built +*") | F45: =COUNTIFS(Rules!$B$2:$B$982,$A45,Rules!$H$2:$H$982,"Built,*") | G45: =COUNTIFS(Rules!$B$2:$B$982,$A45,Rules!$H$2:$H$982,"Verify*") | H45: =COUNTIFS(Rules!$B$2:$B$982,$A45,Rules!$H$2:$H$982,"Not started*") | I45: =IF(D45=0,"",E45/D45) | K45: ✅ Decided (6/6), 26 Sep 2026 — Q3, Q4, Q6 are company choices under D17. | L45: T07-project-coding-live-interview.md
... A53: APX-G | B53: Appendix G · Legal & trust artefacts | C53: 6+ | D53: 0 | E53: =COUNTIFS(Rules!$B$2:$B$982,$A53,Rules!$H$2:$H$982,"Built +*") | F53: =COUNTIFS(Rules!$B$2:$B$982,$A53,Rules!$H$2:$H$982,"Built,*") | G53: =COUNTIFS(Rules!$B$2:$B$982,$A53,Rules!$H$2:$H$982,"Verify*") | H53: =COUNTIFS(Rules!$B$2:$B$982,$A53,Rules!$H$2:$H$982,"Not started*") | I53: =IF(D53=0,"",E53/D53) | K53: 📋 Catalogue defined, 26 Sep 2026. Closes GAP-REGISTER H6. Feeds A2 (security programme, future P12) and B12 (DPDP / GDPR programme extras). Extended 26 Sep 2026 (gap register, user decision): eight artefacts for the new B / C features (G-24–G-31: EWA partner terms, field-force location consent, desk | L53: APX-G-legal-artefacts.md

Sheet Roadmap
A1: Step | B1: What | C1: Design docs | D1: Status | E1: Rules in its docs | F1: Built + tested | G1: Notes (you)
A2: 0 | B2: PostgreSQL 17 with forced row-level security on every tenant table | C2: spec D10, P01 | D2: Done | E2: =COUNTIF(Rules!$B$2:$B$982,"P01") | F2: =COUNTIFS(Rules!$B$2:$B$982,"P01",Rules!$H$2:$H$982,"Built +*")
A3: 1 | B3: Login: sessions, lockout (company-configurable within the YukthiX floor), password floor, MFA (passkeys, TOTP, recovery codes, step-up), OTP sign-in, Google / Microsoft / SAML SSO, login and security screens | C3: P12 | D3: Done | E3: =COUNTIF(Rules!$B$2:$B$982,"P12")+COUNTIF(Rules!$B$2:$B$982,"P04") | F3: =COUNTIFS(Rules!$B$2:$B$982,"P12",Rules!$H$2:$H$982,"Built +*")+COUNTIFS(Rules!$B$2:$B$982,"P04",Rules!$H$2:$H$982,"Built +*")
A4: 1+ | B4: Generic SMS channel (any gateway by configuration; shared YukthiX account, e.g. Zoho CPaaS, plus company-owned accounts) | C4: P04 §4.4–4.5a | D4: In PR #129
A5: — | B5: Design docs and full UI prototype in the repo | C5: — | D5: PR #130
A6: 2 | B6: Organisation and employee core: legal entities, locations, departments, positions, the employee record with effective-dated history, reporting lines, roles and field-level visibility | C6: P01, P02, P06, M01 | D6: Done | E6: =COUNTIF(Rules!$B$2:$B$982,"P01")+COUNTIF(Rules!$B$2:$B$982,"P02")+COUNTIF(Rules!$B$2:$B$982,"P06")+COUNTIF(Rules!$B$2:$B$982,"M01") | F6: =COUNTIFS(Rules!$B$2:$B$982,"P01",Rules!$H$2:$H$982,"Built +*")+COUNTIFS(Rules!$B$2:$B$982,"P02",Rules!$H$2:$H$982,"Built +*")+COUNTIFS(Rules!$B$2:$B$982,"P06",Rules!$H$2:$H$982,"Built +*")+COUNTIFS(Rules!$B$2:$B$982,"M01",Rules!$H$2:$H$982,"Built +*")
A7: 3 | B7: Platform console (YukthiX staff only, same codebase, separate locked-down area): companies and lifecycle, plans and prices, shared channel accounts (move the shared SMS account here), support sessions, audit; later billing, incidents, customer success | C7: P14, P02 support sessions, P12 Q7 | D7: After step 2 | E7: =COUNTIF(Rules!$B$2:$B$982,"P14")+COUNTIF(Rules!$B$2:$B$982,"P20") | F7: =COUNTIFS(Rules!$B$2:$B$982,"P14",Rules!$H$2:$H$982,"Built +*")+COUNTIFS(Rules!$B$2:$B$982,"P20",Rules!$H$2:$H$982,"Built +*")
A8: 3b | B8: YukthiX Service Desk: full ITSM + ESM (incident, request catalogue, problem, change / CAB, release, assets + CMDB, knowledge, SLA / OLA, portal, email / chat / WhatsApp / Teams, automation + AI, monitoring events, on-call, status page, vendors). One engine for company helpdesks (HR / IT / Admin), YukthiX's own customer support, and a standalone product | C8: M14, M08 | D8: After step 3 | E8: =COUNTIF(Rules!$B$2:$B$982,"M14")+COUNTIF(Rules!$B$2:$B$982,"M08") | F8: =COUNTIFS(Rules!$B$2:$B$982,"M14",Rules!$H$2:$H$982,"Built +*")+COUNTIFS(Rules!$B$2:$B$982,"M08",Rules!$H$2:$H$982,"Built +*")
A9: 4 | B9: Time and leave: attendance, regularisation, shifts and rosters, leave and balances, overtime | C9: M02, P03, P07 | D9: Not started | E9: =COUNTIF(Rules!$B$2:$B$982,"M02")+COUNTIF(Rules!$B$2:$B$982,"P03")+COUNTIF(Rules!$B$2:$B$982,"P07") | F9: =COUNTIFS(Rules!$B$2:$B$982,"M02",Rules!$H$2:$H$982,"Built +*")+COUNTIFS(Rules!$B$2:$B$982,"P03",Rules!$H$2:$H$982,"Built +*")+COUNTIFS(Rules!$B$2:$B$982,"P07",Rules!$H$2:$H$982,"Built +*")
A10: 5 | B10: Payroll and statutory: inputs, calculation (PF, ESI, PT, TDS), approve and lock, bank file, payslips | C10: M03, P07, P08 | D10: Not started | E10: =COUNTIF(Rules!$B$2:$B$982,"M03")+COUNTIF(Rules!$B$2:$B$982,"P07")+COUNTIF(Rules!$B$2:$B$982,"P08") | F10: =COUNTIFS(Rules!$B$2:$B$982,"M03",Rules!$H$2:$H$982,"Built +*")+COUNTIFS(Rules!$B$2:$B$982,"P07",Rules!$H$2:$H$982,"Built +*")+COUNTIFS(Rules!$B$2:$B$982,"P08",Rules!$H$2:$H$982,"Built +*")
A11: 6+ | B11: Lifecycle (onboarding, exit, F&F), expenses, performance, learning, engage, benefits, projects and timesheets, contract labour, ATS, mobile | C11: M04–M13, P-series | D11: Not started

Sheet Open work
A1: ID | B1: Area | C1: What | D1: Status (start) | E1: Status (you) | F1: Next action | G1: Owner (you) | H1: Notes (you)
A2: W-001 | B2: Step 2 · Org & employee core | C2: Parts 2c employee record, 2d access & field visibility, 2e People/Settings screens wired; then independent security review, fix every finding, push feat/yukthix-org | D2: Done | F2: PR #131 opened 7 Oct 2026 (stacked on #130); 15 review findings fixed; all suites green
A3: W-002 | B3: CI · dependencies | C3: Upgrade jest 29 → 30 and tailwind 3 → 4 so the strict audit gate (high/critical) passes on the full tree; push #129 with the security fix 377eca4c | D3: Done | F3: Jest 30 + Tailwind 4 + security patches pushed to #129 (CI passing) and merged into #130; being ported to #128
A4: W-003 | B4: Branches | C4: Merge feat/yukthix-login into feat/yukthix-workspace (#130); resolve GO-LIVE-CHECKLIST.md (login branch created its own copy) | D4: Done | F4: Merged 7 Oct 2026 (e27b49c9); checklist kept both versions (item 11 + sign-in section)
A5: W-004 | B5: Branches | C5: Merge order to main: #128 PostgreSQL → #129 login → #130 workspace → #131 step 2 | D5: Open | F5: Founder approval per PR
A6: W-005 | B6: Security review | C6: Email-first sign-in: platform staff (super admin) accounts appear as a 'YukthiX' choice in the company picker when email and password match. Staff should sign in only through the locked-down console path with hardware keys (P12) | D6: Open | F6: Decide and fix before merge of #129
A7: W-006 | B7: Security review | C7: Verified email domains are never re-checked; a lapsed domain keeps routing to SSO until removed. Add a periodic DNS re-check | D7: Open | F7: Fix in login branch
A8: W-007 | B8: UI | C8: 1,039 prototype buttons outside pay/auth have no action yet; each is wired when its backend step lands (scan-dead-buttons.mjs per wired screen must be 0) | D8: Open | F8: Per step
A9: W-008 | B9: UI · Payroll | C9: Payroll screen fixes parked by founder until the payroll backend (step 5) | D9: Parked | F9: Step 5
A10: W-009 | B10: Step 3 · Platform console | C10: Companies & lifecycle, plans & prices, shared channel accounts (move the shared Zoho SMS account here), support sessions, audit | D10: Not started | F10: After step 2
A11: W-010 | B11: Step 3b · Service Desk (M14) | C11: Full ITSM + ESM in four phases (core → ESM → ITIL → operations); one open decision: live chat transport | D11: Not started | F11: Write the detailed M14 design before the build
A12: W-011 | B12: Steps 4–6+ | C12: Time & leave (4), payroll & statutory (5), then lifecycle, expenses, performance, learning, engage, benefits, projects, contract labour, ATS, mobile | D12: Not started | F12: See Roadmap sheet
A13: W-012 | B13: Infrastructure (P13) | C13: Gap register A3: infrastructure & operations parked for the engineering team (P13 team brief) | D13: Parked | F13: Engineering team
... A16: W-015 | B16: CI · dependencies | C16: Port the same dependency fixes (security patches, Jest 30, Tailwind 4) to #128 PostgreSQL so its CI passes | D16: Done | F16: Ported to #128; CI passing

Sheet Deferred
A1: ID | B1: Step | C1: Build job | D1: Date | E1: Left out / not finished (as reported by the build job) | F1: Status (start) | G1: Status (you) | H1: Owner (you) | I1: Notes (you)
A2: D-001 | B2: UI | C2: yx-ui-merge | D2: 2026-10-06 | E2: Dead-button scan finds 1039 buttons with no action outside pay and auth (same count as the source); getting to 0 means wiring real actions across 10 modules, which I did not attempt | F2: Open (verify)
A3: D-002 | B3: UI | C3: yx-ui-merge | D3: 2026-10-06 | E3: Screenshot and axe tests (test:visual, test:a11y) were added but not run; the baselines exist for Windows only, so Linux CI would need its own | F3: Open (verify)
A4: D-003 | B4: UI | C4: yx-ui-merge | D4: 2026-10-06 | E4: Untracked docs/yukthix/GO-LIVE-CHECKLIST.md in the worktree is not from this task and was left alone | F4: Open (verify)
A5: D-004 | B5: UI | C5: yx-ui-merge | D5: 2026-10-06 | E5: Not pushed | F5: Open (verify)
A6: D-005 | B6: 0 | C6: step0-e2e | D6: 2026-10-05 | E6: Recruiter live leaderboard can stay stale (left as is, product decision needed): the push after each answer reads the deliberate 15 s shared cache (ADO #6828). If the last answers of an exam land within 15 s of the previous computation, the recruiter's board stays stale until they rejoin, because the 15 s roster tick does not re-send the leaderboard. A cheap fix is to also emit leaderboard:update from tickRoster. I did not change it because the cache is a deliberate performance trade-off. | F6: Open (verify)
A7: D-006 | B7: 0 | C7: step0-e2e | D7: 2026-10-05 | E7: e2e now runs in a single Jest worker (maxWorkers 1). Every booted app runs real BullMQ workers on one shared Redis, so parallel workers stole each other's jobs. Running suites in parallel would need per-worker queue prefixes. | F7: Open (verify)
A8: D-007 | B8: 0 | C8: step0-e2e | D8: 2026-10-05 | E8: exam-runtime e2e still prints Jest's 'did not exit one second after the test run' warning, though the run exits by itself in about 28 s. I did not trace which timer causes it. | F8: Open (verify)
A9: D-008 | B9: 0 | C9: step0-e2e | D9: 2026-10-05 | E9: Fire-and-forget analyses (for example insight generation) can still log an error after a suite's cleanup deletes the exam. It is log noise only and does not fail tests. | F9: Open (verify)
A10: D-009 | B10: 0 | C10: step0-e2e | D10: 2026-10-05 | E10: Delete the dead /uploads static file server (see security issues). | F10: Open (verify)
A11: D-010 | B11: 0 | C11: step0-postgres | D11: 2026-10-05 | E11: 21 api e2e suites (42 tests) and 1 exam-runtime e2e suite (2 tests) still fail. I left them because the code shows deliberate app changes the tests were never updated for, and rewriting the assertions would bake in product decisions without your input. Not individually traced: the AI evaluation insight cases, the webhook result left at pending, proctoring analysis stuck at processing (timeouts), the audit-log response-shape case, and the branding public-by-slug assertion. The evidence I found for the rest is: | F11: Open (verify)
A12: D-011 | B12: 0 | C12: step0-postgres | D12: 2026-10-05 | E12: Roles now have permissions the tests expect to be denied (expected 403, got 200/201 in question-bank, exam-builder, candidates, ai-jobs, exam-reporting, session-enforcement and ai-insight). | F12: Open (verify)
A13: D-012 | B13: 0 | C13: step0-postgres | D13: 2026-10-05 | E13: API responses changed shape: dashboard now requires ?window=, audit logs return {data}, and branding, compare and preview return extra fields. | F13: Open (verify)
... A106: D-105 | B106: 1 | C106: login:fix-review | D106: 2026-10-06 | E106: Some commits are grouped by area rather than one per finding, and intermediate commits may not compile on their own; the branch tip is green. | F106: Open (verify)

Sheet Go-live
A1: # | B1: Item | C1: What to do | D1: Notes | E1: Status (start) | F1: Status (you) | G1: Owner (you) | H1: Target date (you)
A2: 1 | B2: Domain | C2: Buy the app domain (e.g. app.yukthix.com) and point it at Cloudflare | D2: Needed by Turnstile, SSO redirect URLs, passkeys (WebAuthn RP ID), email sender, cookies | E2: Open
A3: 2 | B3: Cloudflare Turnstile | C3: Dashboard › Turnstile › Add widget (name "YukthiX sign-in", hostname = the domain, mode Managed). Put the secret in the API host's secret settings as TURNSTILE_SECRET_KEY and the site key as NEXT_PUBLIC_TURNSTILE_SITE_KEY | D3: Never paste the secret into chat or commit it. Local dev uses Cloudflare's always-pass test keys | E3: Open
A4: 3 | B4: New-country sign-in alerts | C4: Run the app behind Cloudflare's proxy, then set GEO_COUNTRY_HEADER=cf-ipcountry | D4: Only set it when traffic really goes through Cloudflare, or the header can be forged | E4: Open
A5: 4 | B5: SMS provider + DLT | C5: Sign up with one SMS gateway (any; the generic HTTP adapter fits MSG91, Gupshup, Kaleyra, Exotel, Textlocal; Twilio for other countries). Register YukthiX on a DLT portal: entity (company PAN/GST), sender header (6 letters), OTP template text | D5: DLT approval takes 2–7 days. Until done, codes go by email only | E5: Open
A6: 4a | B6: Shared SMS account = Zoho CPaaS | C6: Zoho CPaaS account in the India DC; DLT registration through Zoho (sender + OTP template). A YukthiX platform admin adds it as the shared http account (example config in docs/sms-gateways/examples.json), types the API token as the token secret, sends a test, and points Zoho's delivery-report webhook at the account's callback URL | D6: Confirm Zoho's reply format (success value and message-id path) against their API reference once access is granted | E6: Open
A7: 5 | B7: WhatsApp (optional) | C7: Each company connects its own WhatsApp Business number (P04 Q2) | D7: Meta bills the company directly | E7: Open
A8: 6 | B8: Google / Microsoft SSO | C8: Create OAuth apps in Google Cloud and Microsoft Entra with the real redirect URL | D8: Per-company IdPs are configured by each company's admin in Settings › Security | E8: Open
A9: 7 | B9: Database roles | C9: Create the owner, app login and app_runtime roles before the first prisma migrate deploy (see README › Database) | D9: The app role must not be superuser or BYPASSRLS | E9: Open
A10: 8 | B10: Secrets | C10: JWT secrets, TOTP encryption key, OTP HMAC key, org-secrets key, DB/Redis passwords in a secrets manager | D10: Rotate per schedule (P12 YX-SECOPS-03) | E10: Open
A11: 9 | B11: After first deploy | C11: Everyone signs in once more (old tokens had no session); admins review email domains on existing SSO providers | D11: From the login PR (#129) | E11: Open
A12: 10 | B12: Security programme | C12: Pen test before the payroll pilot; incident plan and CERT-In 6-hour process; log retention ≥ 1 year | D12: P12 §8 | E12: Open
A13: 11 | B13: Company sign-in addresses | C13: Set YX_BASE_DOMAIN, wildcard DNS + wildcard TLS certificate, and have SSO companies verify their email domains (details below) | D13: Needed once the domain (item 1) exists; until then sign-in is email-first | E13: Open

Sheet Screens
A1: Screen file | B1: Group | C1: Components | D1: Wired to API | E1: Wired components | F1: Notes (you)
A2: packages/yx-ui/src/screens/access/access-log.tsx | B2: access | C2: 1 | D2: Yes | E2: AccessLogScreen
A3: packages/yx-ui/src/screens/access/profile-requests.tsx | B3: access | C3: 1 | D3: Yes | E3: ProfileRequestsScreen
A4: packages/yx-ui/src/screens/access/profile.tsx | B4: access | C4: 1 | D4: Yes | E4: ProfileScreen
A5: packages/yx-ui/src/screens/access/roles-access.tsx | B5: access | C5: 1 | D5: Yes | E5: RolesAccessScreen
A6: packages/yx-ui/src/screens/auth/kit.tsx | B6: auth | C6: 4 | D6: No
A7: packages/yx-ui/src/screens/auth/login-activity.tsx | B7: auth | C7: 3 | D7: Yes | E7: LoginActivityScreen, NO_FILTERS
A8: packages/yx-ui/src/screens/auth/me-security.tsx | B8: auth | C8: 1 | D8: Yes | E8: MeSecurityScreen
A9: packages/yx-ui/src/screens/auth/mfa.tsx | B9: auth | C9: 4 | D9: Yes | E9: MfaChallengeScreen, MfaEnrolScreen
A10: packages/yx-ui/src/screens/auth/security-settings.tsx | B10: auth | C10: 2 | D10: Yes | E10: SecuritySettingsScreen
A11: packages/yx-ui/src/screens/auth/shell.tsx | B11: auth | C11: 1 | D11: Yes | E11: SecurityShell
A12: packages/yx-ui/src/screens/auth/sign-in.tsx | B12: auth | C12: 2 | D12: Yes | E12: ForgotPasswordScreen, SignInScreen
A13: packages/yx-ui/src/screens/auth/tables.tsx | B13: auth | C13: 2 | D13: No
A14: packages/yx-ui/src/screens/growth/engage-feed.tsx | B14: growth | C14: 4 | D14: No
A15: packages/yx-ui/src/screens/growth/engage-recognition.tsx | B15: growth | C15: 4 | D15: No
A16: packages/yx-ui/src/screens/growth/engage-surveys.tsx | B16: growth | C16: 5 | D16: No
A17: packages/yx-ui/src/screens/growth/learn-admin.tsx | B17: growth | C17: 9 | D17: No
A18: packages/yx-ui/src/screens/growth/learn-me.tsx | B18: growth | C18: 7 | D18: No
A19: packages/yx-ui/src/screens/growth/perf-goals.tsx | B19: growth | C19: 5 | D19: No
A20: packages/yx-ui/src/screens/growth/perf-people.tsx | B20: growth | C20: 5 | D20: No
A21: packages/yx-ui/src/screens/growth/perf-reviews.tsx | B21: growth | C21: 7 | D21: No
A22: packages/yx-ui/src/screens/growth/perf-talent.tsx | B22: growth | C22: 2 | D22: No
A23: packages/yx-ui/src/screens/hiring/hiring-offers.tsx | B23: hiring | C23: 7 | D23: No
A24: packages/yx-ui/src/screens/hiring/hiring-pipeline.tsx | B24: hiring | C24: 11 | D24: No
... A29: packages/yx-ui/src/screens/history/hire.tsx | B29: history | C29: 2 | D29: No
A30: packages/yx-ui/src/screens/history/job-changes.tsx | B30: history | C30: 1 | D30: Yes | E30: JobChangesScreen
A31: packages/yx-ui/src/screens/history/person-history.tsx | B31: history | C31: 1 | D31: Yes | E31: PersonHistoryScreen
A32: packages/yx-ui/src/screens/notifications/sms-settings.tsx | B32: notifications | C32: 2 | D32: Yes | E32: SmsSettingsScreen
A33: packages/yx-ui/src/screens/ops/cases-more.tsx | B33: ops | C33: 4 | D33: No
A34: packages/yx-ui/src/screens/ops/cases.tsx | B34: ops | C34: 12 | D34: No
A35: packages/yx-ui/src/screens/ops/compliance.tsx | B35: ops | C35: 10 | D35: No
A36: packages/yx-ui/src/screens/ops/contract.tsx | B36: ops | C36: 8 | D36: No
A37: packages/yx-ui/src/screens/ops/expenses-finance.tsx | B37: ops | C37: 4 | D37: No
A38: packages/yx-ui/src/screens/ops/expenses.tsx | B38: ops | C38: 8 | D38: No
A39: packages/yx-ui/src/screens/ops/helpdesk.tsx | B39: ops | C39: 11 | D39: No
A40: packages/yx-ui/src/screens/ops/posh.tsx | B40: ops | C40: 3 | D40: No
A41: packages/yx-ui/src/screens/ops/visitors.tsx | B41: ops | C41: 6 | D41: No
A42: packages/yx-ui/src/screens/org/entities.tsx | B42: org | C42: 1 | D42: Yes | E42: LegalEntitiesScreen
A43: packages/yx-ui/src/screens/org/locations.tsx | B43: org | C43: 1 | D43: Yes | E43: LocationsScreen
A44: packages/yx-ui/src/screens/org/settings.tsx | B44: org | C44: 3 | D44: No
A45: packages/yx-ui/src/screens/org/structure.tsx | B45: org | C45: 3 | D45: Yes | E45: KINDS, StructureScreen
A46: packages/yx-ui/src/screens/pay/admin-tax-loans.tsx | B46: pay | C46: 6 | D46: No
A47: packages/yx-ui/src/screens/pay/comp-setup.tsx | B47: pay | C47: 8 | D47: No
A48: packages/yx-ui/src/screens/pay/employee-pay.tsx | B48: pay | C48: 11 | D48: No
A49: packages/yx-ui/src/screens/pay/offcycle.tsx | B49: pay | C49: 10 | D49: No
A50: packages/yx-ui/src/screens/pay/payroll-inputs.tsx | B50: pay | C50: 11 | D50: No
A51: packages/yx-ui/src/screens/pay/payroll-run.tsx | B51: pay | C51: 15 | D51: No
A52: packages/yx-ui/src/screens/pay/special-pay.tsx | B52: pay | C52: 12 | D52: No
A53: packages/yx-ui/src/screens/people/assets.tsx | B53: people | C53: 3 | D53: No
A54: packages/yx-ui/src/screens/people/changes.tsx | B54: people | C54: 7 | D54: No
A55: packages/yx-ui/src/screens/people/directory.tsx | B55: people | C55: 4 | D55: Yes | E55: DirectoryScreen, OrgChartScreen
A56: packages/yx-ui/src/screens/people/documents.tsx | B56: people | C56: 11 | D56: No
A57: packages/yx-ui/src/screens/people/exits.tsx | B57: people | C57: 11 | D57: No
A58: packages/yx-ui/src/screens/people/onboarding.tsx | B58: people | C58: 11 | D58: No
A59: packages/yx-ui/src/screens/people/record.tsx | B59: people | C59: 6 | D59: No
A60: packages/yx-ui/src/screens/people/relations.tsx | B60: people | C60: 5 | D60: No
A61: packages/yx-ui/src/screens/people/selfservice.tsx | B61: people | C61: 12 | D61: No
A62: packages/yx-ui/src/screens/platform-a/custom.tsx | B62: platform-a | C62: 8 | D62: No
A63: packages/yx-ui/src/screens/platform-a/governance.tsx | B63: platform-a | C63: 9 | D63: No
A64: packages/yx-ui/src/screens/platform-a/inbox.tsx | B64: platform-a | C64: 13 | D64: No
A65: packages/yx-ui/src/screens/platform-a/integrations.tsx | B65: platform-a | C65: 5 | D65: No
A66: packages/yx-ui/src/screens/platform-a/setup-admin.tsx | B66: platform-a | C66: 8 | D66: Yes | E66: RolesAccessScreen
A67: packages/yx-ui/src/screens/platform-a/shell-home.tsx | B67: platform-a | C67: 12 | D67: No
A68: packages/yx-ui/src/screens/platform-b/growth-screens.tsx | B68: platform-b | C68: 15 | D68: No
A69: packages/yx-ui/src/screens/platform-b/region-agent-screens.tsx | B69: platform-b | C69: 9 | D69: No
A70: packages/yx-ui/src/screens/platform-b/rules-screens.tsx | B70: platform-b | C70: 10 | D70: No
A71: packages/yx-ui/src/screens/platform-b/studio-screens.tsx | B71: platform-b | C71: 11 | D71: No
A72: packages/yx-ui/src/screens/portals/console-finance.tsx | B72: portals | C72: 6 | D72: No
A73: packages/yx-ui/src/screens/portals/console-ops.tsx | B73: portals | C73: 12 | D73: No
A74: packages/yx-ui/src/screens/portals/console-rules.tsx | B74: portals | C74: 4 | D74: No
A75: packages/yx-ui/src/screens/portals/mobile-shell.tsx | B75: portals | C75: 3 | D75: No
A76: packages/yx-ui/src/screens/portals/partner.tsx | B76: portals | C76: 11 | D76: No
A77: packages/yx-ui/src/screens/portals/t9-business.tsx | B77: portals | C77: 4 | D77: No
A78: packages/yx-ui/src/screens/portals/t9-candidate.tsx | B78: portals | C78: 9 | D78: No
... A98: packages/yx-ui/src/screens/time/roster.tsx | B98: time | C98: 17 | D98: No
A99: packages/yx-ui/src/screens/workforce/bulk.tsx | B99: workforce | C99: 2 | D99: Yes | E99: BulkChangesScreen
A100: packages/yx-ui/src/screens/workforce/directory.tsx | B100: workforce | C100: 1 | D100: Yes | E100: DirectoryScreen
A101: packages/yx-ui/src/screens/workforce/org-chart.tsx | B101: workforce | C101: 1 | D101: Yes | E101: OrgChartScreen
A102: packages/yx-ui/src/screens/workforce/probation.tsx | B102: workforce | C102: 1 | D102: Yes | E102: ProbationScreen
A103: packages/yx-ui/src/screens/workforce/team.tsx | B103: workforce | C103: 1 | D103: Yes | E103: TeamScreen

Sheet PRs
A1: PR | B1: Title | C1: State | D1: CI | E1: Branch | F1: Base | G1: Updated | H1: Link | I1: Notes (you)
A2: 131 | B2: Step 2: organisation and employee core with People and Settings screens | C2: OPEN | D2: running | E2: feat/yukthix-org | F2: feat/yukthix-workspace | G2: 2026-10-07 | H2: https://github.com/hari9495/exam-app/pull/131
A3: 130 | B3: Bring YukthiX design docs and the full UI prototype into the monorepo | C3: OPEN | D3: passing | E3: feat/yukthix-workspace | F3: feat/yukthix-login | G3: 2026-10-06 | H3: https://github.com/hari9495/exam-app/pull/130
A4: 129 | B4: Login to the P12 security spec: sessions, MFA, OTP, SSO and YukthiX screens | C4: OPEN | D4: passing | E4: feat/yukthix-login | F4: feat/yukthix-postgres | G4: 2026-10-06 | H4: https://github.com/hari9495/exam-app/pull/129
A5: 128 | B5: Move platform to PostgreSQL with forced row-level security | C5: OPEN | D5: passing | E5: feat/yukthix-postgres | F5: main | G5: 2026-10-06 | H5: https://github.com/hari9495/exam-app/pull/128

Sheet Code scanned
A1: Checkout | B1: Branch | C1: Last commit
A2: exam-app-org | B2: feat/yukthix-org | C2: b376dd80 Merge remote-tracking branch 'origin/feat/yukthix-workspace' into feat/yukthix-org (2026-10-07)
A3: exam-app-ws | B3: feat/yukthix-workspace | C3: 1af52c91 docs(yukthix): M14 decisions Q6-Q9 (device link only, identity actions with controls, one plan, AI by own key or paid credits) and their stories (2026-10-07)

Sheet Backlog
A1: ID | B1: Order | C1: Type | D1: Title | E1: Epic | F1: Feature | G1: State (start) | H1: State (you) | I1: State | J1: Phase | K1: Points | L1: Priority | M1: User story | N1: Acceptance criteria | O1: Rules | P1: Design docs | Q1: Depends on | R1: Evidence | S1: Notes (you)
A2: EP-A-1 | B2: 0 | C2: Epic | D2: Step 0 · PostgreSQL and tenant isolation | E2: Step 0 · PostgreSQL and tenant isolation | G2: Done | I2: =IF(H2<>"",H2,G2) | J2: Step 0 | L2: 1 | P2: P01 §5, spec D10 | R2: PR #128 · branch feat/yukthix-postgres
A3: FT-A-001 | B3: 10 | C3: Feature | D3: Move the database to PostgreSQL 17 | E3: Step 0 · PostgreSQL and tenant isolation | F3: Move the database to PostgreSQL 17 | G3: Done | I3: =IF(H3<>"",H3,G3) | J3: Step 0 | L3: 1 | P3: spec D10, P01 §9 | R3: PR #128 · d35ec1f4 · 19e8f2a9
A4: US-A-001 | B4: 11 | C4: Story | D4: The product runs on PostgreSQL 17 | E4: Step 0 · PostgreSQL and tenant isolation | F4: Move the database to PostgreSQL 17 | G4: Done | I4: =IF(H4<>"",H4,G4) | J4: Step 0 | K4: 5 | L4: 1 | M4: As a company admin, I want YukthiX to run on PostgreSQL so that we get one database that supports row-level security for every company. | N4: • Given a fresh environment, when docker-compose starts, then PostgreSQL 17 runs instead of SQL Server. • Given the Prisma schema, when migrations run, then one fresh PostgreSQL baseline creates every table. • Given unbounded text columns and the real ON DELETE actions, when the schema is compared with SQL Server, then no column is cut short and no delete rule is lost. • Given an org slug or email typed in another case, when it is looked up, then it still matches. | P4: spec D10, P01 §9 | R4: PR #128 · d35ec1f4 · 19e8f2a9 · f06de45f · 351b2f1f
A5: US-A-002 | B5: 12 | C5: Story | D5: Existing exam-app features keep working on PostgreSQL | E5: Step 0 · PostgreSQL and tenant isolation | F5: Move the database to PostgreSQL 17 | G5: Done | I5: =IF(H5<>"",H5,G5) | J5: Step 0 | K5: 5 | L5: 1 | M5: As a recruiter, I want every exam-app screen to keep working after the move so that nothing breaks for current customers. | N5: • Given raw SQL, the seed and scripts, when they run on PostgreSQL, then they give the same results as before. • Given staff and admin search, when a user types any case, then the search is case-insensitive. • Given the recycle bin, when rows are purged, then each row is purged in its own transaction. • Given the e2e suites, when they run in one worker with AI calls offline, then they pass or assert the current behaviour. | P5: spec D10 | R5: PR #128 · 34cba973 · 11c0966d · e9612d6e · 52535396 · f95e0cb6 · 81cb4073
A6: FT-A-002 | B6: 20 | C6: Feature | D6: Tenant isolation with forced row-level security | E6: Step 0 · PostgreSQL and tenant isolation | F6: Tenant isolation with forced row-level security | G6: Done | I6: =IF(H6<>"",H6,G6) | J6: Step 0 | L6: 1 | P6: P01 §5 | R6: PR #128 · bf1441bd · ffedebe0 · e4c00860
A7: US-A-003 | B7: 21 | C7: Story | D7: Every company table has forced row-level security | E7: Step 0 · PostgreSQL and tenant isolation | F7: Tenant isolation with forced row-level security | G7: Done | I7: =IF(H7<>"",H7,G7) | J7: Step 0 | K7: 5 | L7: 1 | M7: As a company admin, I want the database itself to stop any other company from reading our rows so that a coding mistake can never leak our data. | N7: • Given any table with organization_id, when the app role reads it without a company set, then it gets no rows (fail-closed) (YX-ORG-14). • Given company A's context, when the app reads or writes company B's rows, then the database refuses (YX-ORG-14). • Given child tables like attempts, answers and results, when they are checked, then they also carry organization_id and forced RLS (YX-ORG-14). • Given a new model without organization_id or forced RLS, when CI runs rls-isolation.e2e-spec.ts, then the build fails (YX-ORG-14). | O7: YX-ORG-14 | P7: P01 §5 #1–2, P01 §9 | R7: PR #128 · bf1441bd · e4c00860 · 002c83a7 · test/rls-isolation.e2e-spec.ts, test/tenant-isolation.e2e-spec.ts
A8: US-A-004 | B8: 22 | C8: Story | D8: Company context is set per transaction | E8: Step 0 · PostgreSQL and tenant isolation | F8: Tenant isolation with forced row-level security | G8: Done | I8: =IF(H8<>"",H8,G8) | J8: Step 0 | K8: 3 | L8: 1 | M8: As a company admin, I want the company context to live only inside one database transaction so that a pooled connection can never carry another company's context. | N8: • Given forTenant(), when a transaction opens, then the company and user are set with set_config local to that transaction (YX-ORG-14). • Given the transaction ends, when the same pooled connection is reused, then no company context remains (YX-ORG-14). • Given soft-delete queries, when they run inside forTenant(), then they keep the company filter (YX-ORG-14). | O8: YX-ORG-14 | P8: P01 §5 #3 | R8: PR #128 · ffedebe0 · packages/shared/src/prisma/tenant-prisma.service.spec.ts
A9: US-A-005 | B9: 23 | C9: Story | D9: The app connects as a non-owner role | E9: Step 0 · PostgreSQL and tenant isolation | F9: Tenant isolation with forced row-level security | G9: Done | I9: =IF(H9<>"",H9,G9) | J9: Step 0 | K9: 2 | L9: 1 | M9: As YukthiX staff, I want the app to use a database role that cannot bypass RLS so that only migrations run with owner rights. | N9: • Given CI, when migrations run, then they run as the owner role (YX-ORG-14). • Given CI, when the app and tests run, then they use the NOBYPASSRLS app role (YX-ORG-14). • Given a production deploy, when the README is followed, then the three database roles (owner, app login, app_runtime) are created before the first migrate deploy. | O9: YX-ORG-14 | P9: P01 §5 #4 | R9: PR #128 · 002c83a7 · .github/workflows/ci.yml · README deploy notes
A10: US-A-006 | B10: 24 | C10: Story | D10: Security fixes found while moving to PostgreSQL | E10: Step 0 · PostgreSQL and tenant isolation | F10: Tenant isolation with forced row-level security | G10: Done | I10: =IF(H10<>"",H10,G10) | J10: Step 0 | K10: 2 | L10: 1 | M10: As a company admin, I want the issues found during the move fixed so that the new base is safe. | N10: • Given an org webhook URL, when it is saved, then it must be a public https endpoint. • Given a code review regeneration, when it is asked for, then attempt ownership is checked first. • Given the monitoring socket, when a user joins, then permission profiles and org overrides apply (YX-SEC-05). | O10: YX-SEC-05 | P10: P01 §5 | R10: PR #128 · c4f6935f · 0b105ead · c9566ce1
A11: US-A-007 | B11: 90 | C11: Story | D11: Move live customer data from SQL Server to PostgreSQL | E11: Step 0 · PostgreSQL and tenant isolation | F11: Tenant isolation with forced row-level security | G11: New | I11: =IF(H11<>"",H11,G11) | J11: Step 0 | K11: 5 | L11: 1 | M11: As YukthiX staff, I want a tested export, load and cut-over plan so that current customers move to PostgreSQL without data loss. | N11: • Given a copy of production, when the export and load run, then row counts match for every table. • Given the loaded data, when rls-isolation checks run, then every company sees only its own rows (YX-ORG-14). • Given the cut-over rehearsal, when it finishes, then the downtime and rollback steps are written down. | O11: YX-ORG-14 | P11: P01 §9, deferred D-019
A12: EP-A-2 | B12: 100 | C12: Epic | D12: Step 1 · Login and security | E12: Step 1 · Login and security | G12: Done | I12: =IF(H12<>"",H12,G12) | J12: Step 1 | L12: 1 | P12: P12, P04 §4.4–4.5a | R12: PR #129 · branch feat/yukthix-login
A13: FT-A-010 | B13: 110 | C13: Feature | D13: Sessions and login protection | E13: Step 1 · Login and security | F13: Sessions and login protection | G13: Done | I13: =IF(H13<>"",H13,G13) | J13: Step 1a | L13: 1 | P13: P12 §5, P12 Q8 | R13: PR #129 · 7a194c11 · 87ce70ff
A14: US-A-010 | B14: 111 | C14: Story | D14: See and sign out my active sessions | E14: Step 1 · Login and security | F14: Sessions and login protection | G14: Done | I14: =IF(H14<>"",H14,G14) | J14: Step 1a | K14: 3 | L14: 1 | M14: As an employee, I want to see where I am signed in and sign out any session so that a lost device cannot stay signed in. | N14: • Given I sign in, when the session is created, then it is stored server-side with device, IP, idle and absolute expiry (YX-IAM-06). • Given my session is idle longer than the limit, when I make a request, then I get 'Session expired' (YX-IAM-06). • Given Me › Security, when I click 'Sign out' on a session, then its tokens stop working at once (YX-IAM-06). • Given an admin, when they revoke a session in their company, then that user is signed out (YX-IAM-06). | O14: YX-IAM-06 | P14: P12 §5, P12 §7 | R14: PR #129 · 7a194c11 · 87ce70ff · f8c813f0 · test/login-sessions.e2e-spec.ts · sessions.service.spec.ts
A15: US-A-011 | B15: 112 | C15: Story | D15: Login history for me and for admins | E15: Step 1 · Login and security | F15: Sessions and login protection | G15: Done | I15: =IF(H15<>"",H15,G15) | J15: Step 1a | K15: 3 | L15: 1 | M15: As an HR admin, I want to see every login attempt in my company so that I can spot attacks. | N15: • Given any sign-in attempt, when it ends, then an append-only login_events row records result, method, IP and time (YX-IAM-10). • Given Me › Security, when I open login history, then I see only my own events (YX-IAM-10). • Given Admin › Login activity, when an admin filters by method or 'unsuccessful', then they see their company's events only (YX-IAM-10). • Given a session revocation or MFA change, when it happens, then it is logged too (YX-IAM-10). | O15: YX-IAM-10 | P15: P12 §5, P12 §7 | R15: PR #129 · 87ce70ff · 8395d394 · 07fad7b4 · test/login-sessions.e2e-spec.ts
A16: US-A-012 | B16: 113 | C16: Story | D16: Account lockout the company can tune within the YukthiX floor | E16: Step 1 · Login and security | F16: Sessions and login protection | G16: Done | I16: =IF(H16<>"",H16,G16) | J16: Step 1 lockout-policy | K16: 3 | L16: 1 | M16: As a company admin, I want to set how many failed logins lock an account so that we stop guessing attacks without locking people out too easily. | N16: • Given repeated failed logins, when the company limit is reached, then the account is locked for the set time (YX-IAM-07). • Given the lockout settings, when an admin enters values weaker than the YukthiX minimum, then saving is refused (YX-IAM-07). • Given a locked account, when an admin clicks 'Unlock' on Login activity, then the person can sign in again and the action is logged (YX-IAM-07, YX-IAM-10). • Given many parallel failed attempts, when they race, then the lock is applied atomically (YX-IAM-07). | O16: YX-IAM-07, YX-IAM-10 | P16: P12 §5 | R16: PR #129 · a9b3f128 · 45fa6929 · dc998422 · 9460a7af · 349e80e9 · test/account-lockout.e2e-spec.ts · login-protection.service.spec.ts
A17: US-A-013 | B17: 114 | C17: Story | D17: Bot check and new-device / new-country alerts | E17: Step 1 · Login and security | F17: Sessions and login protection | G17: Done | I17: =IF(H17<>"",H17,G17) | J17: Step 1 fix-review | K17: 3 | L17: 1 | M17: As an employee, I want to be told when someone signs in to my account from a new device or country so that I can act fast. | N17: • Given a sign-in from a new device, when it succeeds, then I get a notification (YX-IAM-07). • Given a sign-in from a new country (geo header), when it succeeds, then I get a notification (YX-IAM-07). • Given the public login page is under attack and Turnstile keys are set, when someone signs in, then a bot check is shown (YX-IAM-07). • Given the sign-in API, when an unknown email is tried, then the reply does not reveal which company exists (YX-IAM-07). | O17: YX-IAM-07 | P17: P12 §5 | R17: PR #129 · 31e289f6 · 8916e0c8 · bot-challenge.spec.ts · test/login-protection.e2e-spec.ts
A18: FT-A-011 | B18: 120 | C18: Feature | D18: Passwords and company security policy | E18: Step 1 · Login and security | F18: Passwords and company security policy | G18: Done | I18: =IF(H18<>"",H18,G18) | J18: Step 1b | L18: 1 | P18: P12 §5, P12 Q8 | R18: PR #129 · 8a37fee7 · 724a4762
A19: US-A-014 | B19: 121 | C19: Story | D19: Strong passwords with a breached-password check | E19: Step 1 · Login and security | F19: Passwords and company security policy | G19: Done | I19: =IF(H19<>"",H19,G19) | J19: Step 1b | K19: 3 | L19: 1 | M19: As an employee, I want the system to refuse weak or leaked passwords so that my account is hard to break. | N19: • Given a new password shorter than 12 characters, when I save it, then it is refused (YX-IAM-08). • Given a password found in a breach list, when I set or change it, then it is refused (YX-IAM-08). • Given an existing breached password, when I sign in, then I must change it first (YX-IAM-08). • Given passwords, when stored, then they use argon2 and never expire on a timer (YX-IAM-08). | O19: YX-IAM-08 | P19: P12 §5, P12 Q8 | R19: PR #129 · 8a37fee7 · a50e83e7 · 34f19553 · password-policy.service.spec.ts · test/security-policy.e2e-spec.ts
A20: US-A-015 | B20: 122 | C20: Story | D20: Company security policy page with the YukthiX minimum shown | E20: Step 1 · Login and security | F20: Passwords and company security policy | G20: Done | I20: =IF(H20<>"",H20,G20) | J20: Step 1b | K20: 5 | L20: 1 | M20: As a company admin, I want one page to set MFA scope, session limits and password rules so that our company can be stricter than the YukthiX floor. | N20: • Given Settings › Security, when I open it, then each setting shows the YukthiX minimum next to it (YX-IAM-06). • Given an idle limit above 8 h or an absolute limit above 12 h, when I save, then it is refused (YX-IAM-06). • Given MFA scope 'everyone', when saved, then every user must use two-step sign-in (YX-IAM-01). • Given a policy change, when saved, then it needs step-up and is logged (YX-IAM-02, YX-IAM-10). • Given the policy, when a request arrives, then it is enforced at sign-in and on every request (YX-IAM-06). | O20: YX-IAM-06, YX-IAM-01, YX-IAM-02, YX-IAM-10 | P20: P12 §7 | R20: PR #129 · 19f4540b · 5919361c · 724a4762 · tenant-security-policy.spec.ts · security-policy.service.spec.ts · test/security-policy.e2e-spec.ts
A21: US-A-016 | B21: 123 | C21: Story | D21: IP allow-lists for desk, admin console and API | E21: Step 1 · Login and security | F21: Passwords and company security policy | G21: Done | I21: =IF(H21<>"",H21,G21) | J21: Step 1b | K21: 3 | L21: 1 | M21: As a company admin, I want to allow sign-in only from our office networks so that stolen passwords are useless elsewhere. | N21: • Given a desk allow-list, when a staff request comes from outside it, then it is refused (YX-IAM-09). • Given an admin allow-list, when any admin-grade permission is used from outside it, then it is refused (YX-IAM-09). • Given an API allow-list, when an API key is used from outside it, then it is refused (YX-IAM-09). • Given candidate and external portals, when no list includes them, then they are not blocked (YX-IAM-09). | O21: YX-IAM-09 | P21: P12 §5 | R21: PR #129 · 19f4540b · 1a79f4b7 · api-key-auth.guard.spec.ts · permissions.guard.spec.ts
A22: FT-A-012 | B22: 130 | C22: Feature | D22: Two-step verification and step-up | E22: Step 1 · Login and security | F22: Two-step verification and step-up | G22: Done | I22: =IF(H22<>"",H22,G22) | J22: Step 1c | L22: 1 | P22: P12 §5, P12 Q1 | R22: PR #129 · 515085cb · 036b227a
A23: US-A-017 | B23: 131 | C23: Story | D23: Passkeys, authenticator apps and recovery codes | E23: Step 1 · Login and security | F23: Two-step verification and step-up | G23: Done | I23: =IF(H23<>"",H23,G23) | J23: Step 1c | K23: 5 | L23: 1 | M23: As an HR admin, I want to add a passkey or an authenticator app so that my account needs two steps to sign in. | N23: • Given Me › Security, when I add a passkey or TOTP app, then it is saved as a factor (YX-IAM-03). • Given I enrol my first factor, when it is saved, then recovery codes are shown once and each works only once (YX-IAM-11). • Given a second sign-in step, when I use the passkey or TOTP, then the session reaches AAL2 (YX-IAM-03). • Given first-factor enrolment, when I do it, then it needs a fresh sign-in and never counts as step-up (YX-IAM-02). | O23: YX-IAM-03, YX-IAM-11, YX-IAM-02 | P23: P12 §5, P12 §6 | R23: PR #129 · 2fe4bbb3 · 515085cb · b1f073a8 · bccaa019 · test/mfa.e2e-spec.ts · mfa.service.spec.ts · TwoStepSection.test.tsx
A24: US-A-018 | B24: 132 | C24: Story | D24: MFA is mandatory for sensitive roles | E24: Step 1 · Login and security | F24: Two-step verification and step-up | G24: Done | I24: =IF(H24<>"",H24,G24) | J24: Step 1c | K24: 3 | L24: 1 | M24: As a company admin, I want people in sensitive roles to use two-step sign-in so that HR and payroll data stay safe. | N24: • Given a user with a sensitive permission and no factor, when they use it, then it is refused until they enrol (YX-IAM-01). • Given an existing user in a sensitive role, when they sign in, then they get a 14-day grace to enrol, then it is enforced (YX-IAM-01). • Given YukthiX staff, when they sign in, then they get no grace (YX-IAM-01). • Given a role or permission-profile change, when saved, then the person's sessions end (YX-IAM-06). | O24: YX-IAM-01, YX-IAM-06 | P24: P12 §5, P12 §8 | R24: PR #129 · a4341228 · 036b227a · 49c5a896 · mfa.spec.ts · permissions.guard.spec.ts
A25: US-A-019 | B25: 133 | C25: Story | D25: Step-up before sensitive actions | E25: Step 1 · Login and security | F25: Two-step verification and step-up | G25: Done | I25: =IF(H25<>"",H25,G25) | J25: Step 1c | K25: 3 | L25: 1 | M25: As an HR admin, I want to re-verify before a sensitive action so that a left-open session cannot be misused. | N25: • Given a step-up action, when my last AAL2 check is older than 15 minutes, then I am asked to re-verify (YX-IAM-02). • Given I re-verified within 15 minutes, when I do another step-up action, then I am not asked again (YX-IAM-02). • Given a step-up, when it succeeds, then the audit entry records it (YX-IAM-02). • Given a one-time code, when used as step-up, then it is refused (YX-IAM-03). | O25: YX-IAM-02, YX-IAM-03 | P25: P12 §5 | R25: PR #129 · 036b227a · 8d171bdf · StepUpProvider.test.tsx · test/mfa.e2e-spec.ts
A26: US-A-020 | B26: 134 | C26: Story | D26: Admin MFA reset needs a second admin | E26: Step 1 · Login and security | F26: Two-step verification and step-up | G26: Done | I26: =IF(H26<>"",H26,G26) | J26: Step 1c | K26: 2 | L26: 1 | M26: As a company admin, I want a lost-device reset for a sensitive-role user to need a second admin so that one person cannot take over an account. | N26: • Given a sensitive-role user lost their factors, when admin A asks for a reset, then admin B must approve (YX-IAM-11). • Given the reset is approved, when it completes, then the user's sessions end and it is logged (YX-IAM-10). • Given admin A, when they try to approve their own request, then it is refused (YX-SEC-11). | O26: YX-IAM-11, YX-IAM-10, YX-SEC-11 | P26: P12 §5 | R26: PR #129 · 515085cb · mfa.service.spec.ts · test/mfa.e2e-spec.ts
A27: FT-A-013 | B27: 140 | C27: Feature | D27: One-time codes and the generic SMS channel | E27: Step 1 · Login and security | F27: One-time codes and the generic SMS channel | G27: Done | I27: =IF(H27<>"",H27,G27) | J27: Step 1d / sms-channel | L27: 1 | P27: P12 Q1, P04 §4.4–4.5a | R27: PR #129 · 6e99a91f · cb8c1e6d
A28: US-A-021 | B28: 141 | C28: Story | D28: Sign in with a one-time code by email or mobile | E28: Step 1 · Login and security | F28: One-time codes and the generic SMS channel | G28: Done | I28: =IF(H28<>"",H28,G28) | J28: Step 1d | K28: 5 | L28: 1 | M28: As an employee without a work email, I want to sign in with a code sent to my verified mobile so that I can use YukthiX in the field. | N28: • Given a verified email or mobile, when I ask for a code, then it is sent at once and expires quickly (YX-NTF-13). • Given the code message, when it is sent, then it carries only the code, its purpose and expiry, no other data (YX-NTF-04, YX-NTF-13). • Given System Admin or Payroll Admin, when they choose OTP as the only second factor, then it is refused (YX-IAM-03). • Given repeated code requests, when the per-identifier cap is reached, then more codes are refused for the hour (YX-IAM-07). | O28: YX-NTF-13, YX-NTF-04, YX-IAM-03, YX-IAM-07 | P28: P12 §3, P04 §4.5a | R28: PR #129 · 9d9961ee · f6a5559c · 6e99a91f · 5c8cd1d0 · test/otp-sign-in.e2e-spec.ts · otp.service.spec.ts
A29: US-A-022 | B29: 142 | C29: Story | D29: Connect any SMS gateway by configuration | E29: Step 1 · Login and security | F29: One-time codes and the generic SMS channel | G29: Done | I29: =IF(H29<>"",H29,G29) | J29: Step 1 sms-channel | K29: 5 | L29: 1 | M29: As a company admin, I want to plug in our own SMS gateway, or use YukthiX's shared account, so that codes reach our people. | N29: • Given a gateway's HTTP config, when it is saved, then the templated adapter sends through it without code changes (YX-NTF-07). • Given an SMS, when it is sent, then it uses a DLT-registered template (YX-NTF-07). • Given no valid template for the type, when a send is tried, then it falls back to email and the reason is logged (YX-NTF-07). • Given secrets, when an admin views the account, then they are write-only and never shown back. | O29: YX-NTF-07 | P29: P04 §4.4 | R29: PR #129 · 37c15118 · 45178a02 · e57c7aa7 · http-gateways.spec.ts · http-provider.spec.ts · twilio-provider.spec.ts
A30: US-A-023 | B30: 143 | C30: Story | D30: SMS failover, delivery log and delivery reports | E30: Step 1 · Login and security | F30: One-time codes and the generic SMS channel | G30: Done | I30: =IF(H30<>"",H30,G30) | J30: Step 1 sms-channel | K30: 3 | L30: 1 | M30: As a company admin, I want to see every SMS attempt and its status so that I can fix delivery problems. | N30: • Given a failed send, when another account is set, then the message fails over to it (YX-NTF-10). • Given every attempt, when it ends, then the delivery log records status and provider id (YX-NTF-10). • Given a delivery report callback, when it arrives with a valid token, then the status is updated (YX-NTF-10). • Given an opt-out report from the provider, when it arrives, then that number is no longer used (YX-NTF-11). | O30: YX-NTF-10, YX-NTF-11 | P30: P04 §4.4, P04 §6 | R30: PR #129 · cb8c1e6d · dc83450a · sms-callbacks.spec.ts · test/sms-channel.e2e-spec.ts
A31: US-A-024 | B31: 144 | C31: Story | D31: SMS consent, metering and a monthly cap | E31: Step 1 · Login and security | F31: One-time codes and the generic SMS channel | G31: Done | I31: =IF(H31<>"",H31,G31) | J31: Step 1 sms-channel | K31: 3 | L31: 1 | M31: As a company admin, I want SMS sent only to people who agreed and within our monthly cap so that we follow TRAI rules and control cost. | N31: • Given no active SMS consent, when a code would go by SMS, then it goes only if the person asked for SMS (YX-NTF-14). • Given each SMS, when sent, then it is metered for the company with its parts (YX-NTF-12). • Given the monthly cap is reached, when another SMS is due, then it is not sent and the fallback is logged (YX-NTF-12). • Given an OTP SMS, when sent, then it counts toward the quota but skips quiet hours and digests (YX-NTF-13). | O31: YX-NTF-14, YX-NTF-12, YX-NTF-13 | P31: P04 §4.4, P04 §4.5a | R31: PR #129 · 37c15118 · cb8c1e6d · 9182ed3d · 9be582ad · test/sms-channel.e2e-spec.ts
A32: US-A-025 | B32: 145 | C32: Story | D32: Settings › Notifications › SMS screen | E32: Step 1 · Login and security | F32: One-time codes and the generic SMS channel | G32: Done | I32: =IF(H32<>"",H32,G32) | J32: Step 1 sms-channel | K32: 3 | L32: 1 | M32: As a company admin, I want a screen to manage SMS accounts, test a send and read the delivery log so that I don't need YukthiX support. | N32: • Given the SMS page, when I add an account, then secrets are write-only (YX-NTF-07). • Given 'Test send', when I send to my number, then the result shows in the delivery log (YX-NTF-10). • Given a phone-width screen, when I open the log, then rows show as cards with masked numbers (YX-NTF-10). | O32: YX-NTF-07, YX-NTF-10 | P32: P04 §7 | R32: PR #129 · f1f084e2 · 634f1e8b · sms-settings.test.tsx
A33: US-A-026 | B33: 195 | C33: Story | D33: WhatsApp authentication codes | E33: Step 1 · Login and security | F33: One-time codes and the generic SMS channel | G33: New | I33: =IF(H33<>"",H33,G33) | J33: Step 1 follow-up | K33: 3 | L33: 3 | M33: As an employee, I want to get my sign-in code on WhatsApp so that I get it even when SMS is slow. | N33: • Given a company WhatsApp number with an approved authentication template, when I ask for a code on WhatsApp, then it is sent at once (YX-NTF-13, YX-NTF-07). • Given no approved template, when a WhatsApp code is due, then it falls back to SMS or email and logs why (YX-NTF-07). • Given I never opted in or asked on WhatsApp, when a code is due, then WhatsApp is not used (YX-NTF-14). | O33: YX-NTF-13, YX-NTF-07, YX-NTF-14 | P33: P04 §4.4, P04 §4.5a, deferred D-080 | Q33: US-A-021
A34: FT-A-014 | B34: 150 | C34: Feature | D34: Single sign-on | E34: Step 1 · Login and security | F34: Single sign-on | G34: Done | I34: =IF(H34<>"",H34,G34) | J34: Step 1e | L34: 1 | P34: P12 §5, P12 Q2 | R34: PR #129 · 2411c632 · 272ffe08
A35: US-A-027 | B35: 151 | C35: Story | D35: Several identity providers per company | E35: Step 1 · Login and security | F35: Single sign-on | G35: Done | I35: =IF(H35<>"",H35,G35) | J35: Step 1e | K35: 5 | L35: 1 | M35: As a company admin, I want to connect Google, Microsoft Entra and SAML providers so that each email domain signs in with its own provider. | N35: • Given several providers, when each maps its own email domains, then a user is sent to the right one (YX-IAM-04). • Given Google, Entra or a generic OIDC issuer, when a user signs in, then the OIDC flow completes (YX-IAM-04). • Given any provider change, when saved, then every company admin gets an email (YX-IAM-10). • Given a generic issuer, when saved, then its discovery URLs are DNS-checked and pinned (YX-IAM-04). | O35: YX-IAM-04, YX-IAM-10 | P35: P12 §5, P12 §6 | R35: PR #129 · 26fd22ed · 2411c632 · 272ffe08 · 0f211510 · test/sso-oidc.e2e-spec.ts · test/saml-sso.e2e-spec.ts · identity-providers.service.spec.ts
A36: US-A-028 | B36: 152 | C36: Story | D36: Create users on first SSO sign-in (JIT) | E36: Step 1 · Login and security | F36: Single sign-on | G36: Done | I36: =IF(H36<>"",H36,G36) | J36: Step 1e | K36: 3 | L36: 1 | M36: As a company admin, I want new staff to get an account on their first SSO sign-in so that IT doesn't create each one. | N36: • Given an allowed domain, when a new person signs in by SSO, then a user is created with the default role (YX-IAM-05). • Given a domain not allowed, when someone signs in, then no user is created (YX-IAM-05). • Given JIT rules, when a user is created, then a sensitive role is never given automatically (YX-IAM-05). • Given the provider asserts MFA with fixed values, when the user signs in, then the session counts as AAL2 (YX-IAM-01). | O36: YX-IAM-05, YX-IAM-01 | P36: P12 §5 | R36: PR #129 · 2411c632 · 8edd092e · 0728daa0 · test/sso-oidc.e2e-spec.ts
A37: US-A-029 | B37: 153 | C37: Story | D37: SSO-only with break-glass admins | E37: Step 1 · Login and security | F37: Single sign-on | G37: Done | I37: =IF(H37<>"",H37,G37) | J37: Step 1e | K37: 3 | L37: 1 | M37: As a company admin, I want to switch off passwords for normal users so that everyone must use our identity provider. | N37: • Given SSO-only on, when a normal user tries a password, then it fails (YX-IAM-04). • Given fewer than 2 break-glass admins, when I turn on SSO-only, then saving is refused (YX-IAM-04). • Given a break-glass admin signs in with a password and MFA, when it succeeds, then all admins are alerted (YX-IAM-04). • Given SSO-only is turned on or a provider is disabled, when saved, then sessions opened through it end (YX-IAM-06). | O37: YX-IAM-04, YX-IAM-06 | P37: P12 §5 | R37: PR #129 · 8b952b70 · saml-sso.e2e-spec.ts · sso.service.spec.ts
A38: US-A-030 | B38: 154 | C38: Story | D38: SSO hardening from the security review | E38: Step 1 · Login and security | F38: Single sign-on | G38: Done | I38: =IF(H38<>"",H38,G38) | J38: Step 1 fix-review | K38: 3 | L38: 1 | M38: As a company admin, I want our SSO to resist known attacks so that nobody can sign in as our staff through another provider. | N38: • Given a provider, when it asserts an email outside its own domains, then sign-in is refused (YX-IAM-04). • Given the SSO code in the callback, when it is redeemed, then it is device-bound, in the URL fragment and used once (YX-IAM-04). • Given a replayed SAML assertion, when it arrives, then the atomic replay check refuses it (YX-IAM-04). • Given an IdP change, when it is made, then it needs user-admin rights (YX-IAM-05). | O38: YX-IAM-04, YX-IAM-05 | P38: P12 §5 | R38: PR #129 · de02f469 · 834105c4 · 4d0c6d98 · 7164745b · saml-cache.provider.spec.ts · page.test.tsx (sso/callback)
A39: FT-A-015 | B39: 160 | C39: Feature | D39: Sign in without a company code | E39: Step 1 · Login and security | F39: Sign in without a company code | G39: Done | I39: =IF(H39<>"",H39,G39) | J39: Step 1 login-no-code | L39: 1 | P39: P12 §6 | R39: PR #129 · 5dbcd4ee · c1d694ff
A40: US-A-031 | B40: 161 | C40: Story | D40: Email-first sign-in with a company picker | E40: Step 1 · Login and security | F40: Sign in without a company code | G40: Done | I40: =IF(H40<>"",H40,G40) | J40: Step 1 login-no-code | K40: 5 | L40: 1 | M40: As an employee, I want to sign in with just my work email so that I never need to know a company code. | N40: • Given my email belongs to one company, when I enter it and my password, then I sign in to that company (YX-IAM-04). • Given my email is in several companies, when the password matches more than one, then a company picker shows only those (YX-IAM-07). • Given 0 or 1 matching accounts, when I sign in, then the response takes about the same time (YX-IAM-07). • Given the picker, when I choose, then a one-use selection token tied to my device and valid 2 minutes completes sign-in (YX-IAM-07). | O40: YX-IAM-04, YX-IAM-07 | P40: P12 §6 | R40: PR #129 · 5dbcd4ee · de468070 · 3bfa5fca · 25b85613 · test/email-first-sign-in.e2e-spec.ts · auth.test.tsx
A41: US-A-032 | B41: 162 | C41: Story | D41: Company from the web address or a remembered company | E41: Step 1 · Login and security | F41: Sign in without a company code | G41: Done | I41: =IF(H41<>"",H41,G41) | J41: Step 1 login-no-code | K41: 3 | L41: 1 | M41: As an employee, I want my company's own address or my last company to be remembered so that sign-in is one step. | N41: • Given a company subdomain under YX_BASE_DOMAIN, when I open it, then the sign-in page is for that company (YX-IAM-04). • Given I signed in before on this device, when I return, then my company is remembered and can be changed (YX-IAM-04). • Given forgot password, when I enter my work email only, then a reset link is sent without asking for a company (YX-IAM-08). | O41: YX-IAM-04, YX-IAM-08 | P41: P12 §6 | R41: PR #129 · 5dbcd4ee · e3661bfc · 2b42bd8e · company-scope.spec.ts
A42: US-A-033 | B42: 163 | C42: Story | D42: Verify company email domains by DNS TXT | E42: Step 1 · Login and security | F42: Sign in without a company code | G42: Done | I42: =IF(H42<>"",H42,G42) | J42: Step 1 login-no-code | K42: 3 | L42: 1 | M42: As a company admin, I want to prove we own our email domain so that only verified domains send people to our SSO. | N42: • Given a domain, when I add it, then the TXT record to publish is shown (YX-IAM-04). • Given 'Check record', when the TXT record is found, then the domain is marked verified (YX-IAM-04). • Given an unverified domain, when someone signs in email-first, then it does not route them to our provider (YX-IAM-04). | O42: YX-IAM-04 | P42: P12 §5 | R42: PR #129 · c1d694ff · 1fdd57c9 · c729d661
A43: US-A-034 | B43: 170 | C43: Story | D43: Staff accounts never show in the company picker | E43: Step 1 · Login and security | F43: Sign in without a company code | G43: New | I43: =IF(H43<>"",H43,G43) | J43: Step 1 follow-up | K43: 2 | L43: 1 | M43: As YukthiX staff, I want my staff account kept out of the company sign-in so that staff only sign in through the locked-down console path with hardware keys. | N43: • Given a staff account with the same email and password as a company account, when that email signs in email-first, then no 'YukthiX' choice is shown (YX-SECOPS-08). • Given a staff account, when it tries to sign in on a company page, then it is refused with a neutral message (YX-SECOPS-08). • Given the console sign-in path, when a staff member signs in, then a hardware security key is required (YX-SECOPS-08, YX-IAM-01). | O43: YX-SECOPS-08, YX-IAM-01 | P43: P12 Q7, open-work W-005, deferred D-050
A44: US-A-035 | B44: 171 | C44: Story | D44: Re-check verified email domains regularly | E44: Step 1 · Login and security | F44: Sign in without a company code | G44: New | I44: =IF(H44<>"",H44,G44) | J44: Step 1 follow-up | K44: 2 | L44: 1 | M44: As a company admin, I want verified domains re-checked so that a lapsed domain stops routing people to our SSO. | N44: • Given a verified domain, when the scheduled DNS re-check runs, then it still needs the TXT record (YX-IAM-04). • Given the record is missing on two checks in a row, when the job runs, then the domain is marked unverified and admins are emailed (YX-IAM-04, YX-IAM-10). • Given an unverified domain, when someone signs in email-first, then it no longer routes to SSO (YX-IAM-04). | O44: YX-IAM-04, YX-IAM-10 | P44: P12 §5, open-work W-006, deferred D-046 | Q44: US-A-033
A45: FT-A-016 | B45: 180 | C45: Feature | D45: Login and security screens | E45: Step 1 · Login and security | F45: Login and security screens | G45: Done | I45: =IF(H45<>"",H45,G45) | J45: Step 1g | L45: 1 | P45: P12 §7 | R45: PR #129 · d6ea28d4 · 07fad7b4
A46: US-A-036 | B46: 181 | C46: Story | D46: YukthiX sign-in, second step and Me › Security screens | E46: Step 1 · Login and security | F46: Login and security screens | G46: Done | I46: =IF(H46<>"",H46,G46) | J46: Step 1g | K46: 5 | L46: 1 | M46: As an employee, I want clear sign-in and security screens so that I can manage my factors, sessions and history myself. | N46: • Given /yx/sign-in, when I sign in, then the second step and step-up prompt use the YukthiX design (YX-IAM-02). • Given Me › Security, when I open it, then I see passkeys, TOTP, recovery codes, sessions and login history (YX-IAM-06, YX-IAM-10). • Given Admin › Login activity, when an admin opens it, then failed-login spikes and sessions are listed (YX-IAM-10). • Given a phone width, when a table is shown, then it turns into cards without page side-scrolling. | O46: YX-IAM-02, YX-IAM-06, YX-IAM-10 | P46: P12 §7 | R46: PR #129 · d6ea28d4 · 111c9d4a · 07fad7b4 · e82cd72a · yx-pages.test.tsx · auth.test.tsx · SecondFactorForm.test.tsx
A47: FT-A-017 | B47: 190 | C47: Feature | D47: Step 1 security review and follow-ups | E47: Step 1 · Login and security | F47: Step 1 security review and follow-ups | G47: Done | I47: =IF(H47<>"",H47,G47) | J47: Step 1 fix-review | L47: 1 | P47: P12 | R47: PR #129 · 31e289f6 · bccaa019 · 377eca4c
A48: US-A-037 | B48: 191 | C48: Story | D48: Fix every finding of the step 1 security review | E48: Step 1 · Login and security | F48: Step 1 security review and follow-ups | G48: Done | I48: =IF(H48<>"",H48,G48) | J48: Step 1 fix-review | K48: 5 | L48: 1 | M48: As a company admin, I want the independent review's findings fixed before release so that login is safe on day one. | N48: • Given a sign-in, when an org does not exist, then the reply gives no hint (YX-IAM-07). • Given YukthiX super admins, when they enrol MFA, then only device-bound security keys are accepted (YX-SECOPS-08). • Given the dependency audit gate, when CI runs, then no high or critical advisory is open (YX-SECOPS-04). • Given the monitoring socket, when the roster ticks, then each socket is re-validated (YX-IAM-06). | O48: YX-IAM-07, YX-SECOPS-08, YX-SECOPS-04, YX-IAM-06 | P48: P12 §5 | R48: PR #129 · 31e289f6 · bccaa019 · c6219563 · 377eca4c · 65817257 · dcd9593f
A49: US-A-038 | B49: 192 | C49: Story | D49: Identity re-verification as a recovery route | E49: Step 1 · Login and security | F49: Step 1 security review and follow-ups | G49: New | I49: =IF(H49<>"",H49,G49) | J49: Step 1 follow-up | K49: 3 | L49: 2 | M49: As an HR admin who lost every factor, I want to recover by re-verifying my identity so that I am not stuck when no second admin is available. | N49: • Given a sensitive-role user with no factors, when no second admin can approve, then they can recover by identity re-verification (YX-IAM-11). • Given the re-verification passes, when recovery completes, then old factors and sessions are revoked and all admins are alerted (YX-IAM-11, YX-IAM-10). • Given a sensitive-role account with no factor, when someone uses the email reset link, then it does not bypass MFA enrolment (YX-IAM-11). | O49: YX-IAM-11, YX-IAM-10 | P49: P12 §5, deferred D-077 | Q49: US-A-020
A50: US-A-039 | B50: 193 | C50: Story | D50: Passkey-only sign-in | E50: Step 1 · Login and security | F50: Step 1 security review and follow-ups | G50: New | I50: =IF(H50<>"",H50,G50) | J50: Step 1 follow-up | K50: 3 | L50: 3 | M50: As an employee, I want to sign in with only my passkey so that I don't need a password at all. | N50: • Given a registered discoverable passkey, when I choose 'Sign in with passkey', then I sign in without a password at AAL2 (YX-IAM-03). • Given a company with SSO-only on, when a normal user tries passkey-only, then the company rule applies (YX-IAM-04). • Given the sign-in, when it ends, then a login event records method 'passkey' (YX-IAM-10). | O50: YX-IAM-03, YX-IAM-04, YX-IAM-10 | P50: P12 §3, deferred D-075 | Q50: US-A-017
A51: US-A-040 | B51: 194 | C51: Story | D51: Keep login logs at least one year, then purge | E51: Step 1 · Login and security | F51: Step 1 security review and follow-ups | G51: New | I51: =IF(H51<>"",H51,G51) | J51: Step 1 follow-up | K51: 2 | L51: 1 | M51: As a company admin, I want login logs kept for at least a year so that we can investigate incidents and meet DPDP rules. | N51: • Given a login event 11 months old, when an investigator searches, then it is found (YX-SECOPS-07). • Given the retention job, when it runs, then it purges only events and expired sessions older than the 1-year minimum (YX-SECOPS-07). • Given the purge, when it runs, then it uses its own audited database role (YX-SECOPS-07). | O51: YX-SECOPS-07 | P51: P12 §5, P12 §9, deferred D-063
A52: EP-A-3 | B52: 200 | C52: Epic | D52: Design docs and UI prototype | E52: Design docs and UI prototype | G52: Done | I52: =IF(H52<>"",H52,G52) | J52: UI prototype | L52: 1 | P52: packages/yx-ui, docs/yukthix/design | R52: PR #130 · branch feat/yukthix-workspace
A53: FT-A-020 | B53: 210 | C53: Feature | D53: YukthiX design system package | E53: Design docs and UI prototype | F53: YukthiX design system package | G53: Done | I53: =IF(H53<>"",H53,G53) | J53: UI prototype | L53: 1 | P53: brand/DESIGN-SYSTEM.md | R53: PR #129 · a9869401 · PR #130
A54: US-A-050 | B54: 211 | C54: Story | D54: Design system in the monorepo as packages/yx-ui | E54: Design docs and UI prototype | F54: YukthiX design system package | G54: Done | I54: =IF(H54<>"",H54,G54) | J54: UI prototype | K54: 3 | L54: 1 | M54: As a developer, I want one shared component package so that every YukthiX screen looks and behaves the same. | N54: • Given packages/yx-ui, when an app imports it, then tokens, shell and components work under Next's React types. • Given the token check, when a component uses a raw colour, then check-tokens fails. • Given the component tests, when vitest runs, then components, data, overlay, shell and charts tests pass. | P54: brand/DESIGN-SYSTEM.md, packages/yx-ui/README.md | R54: PR #129 · a9869401 · aaedb2c2 · components.test.tsx · shell.test.tsx · scripts/check-tokens.mjs
A55: FT-A-021 | B55: 220 | C55: Feature | D55: Screen prototypes for every module | E55: Design docs and UI prototype | F55: Screen prototypes for every module | G55: Done | I55: =IF(H55<>"",H55,G55) | J55: UI prototype | L55: 1 | P55: APX-D, packages/yx-ui/docs/SCREENS-BRIEF.md | R55: PR #130 · 5b607e04
A56: US-A-051 | B56: 221 | C56: Story | D56: 2,946 Storybook stories over 16 screen groups | E56: Design docs and UI prototype | F56: Screen prototypes for every module | G56: Done | I56: =IF(H56<>"",H56,G56) | J56: UI prototype | K56: 8 | L56: 1 | M56: As the founder, I want every planned screen as a clickable prototype so that I can review the product before the backend is built. | N56: • Given Storybook, when it is built, then 2,946 stories render across 16 screen groups (auth, people, time, pay, hiring, settings, platform and more). • Given each screen, when opened, then it uses only yx-ui components and tokens. • Given the screens, when exported, then apps can import them and wire them to real APIs. | P56: APX-D, packages/yx-ui/docs/SCREENS-BRIEF.md | R56: PR #130 · 5b607e04 · e4a858ad · storybook-static
A57: FT-A-022 | B57: 230 | C57: Feature | D57: Screen review tooling | E57: Design docs and UI prototype | F57: Screen review tooling | G57: Done | I57: =IF(H57<>"",H57,G57) | J57: UI prototype | L57: 1 | P57: packages/yx-ui/review/RULES.md | R57: PR #130 · ab2b9928 · 3f37d883
A58: US-A-052 | B58: 231 | C58: Story | D58: Screen review rules R1–R11 and checklists | E58: Design docs and UI prototype | F58: Screen review tooling | G58: Done | I58: =IF(H58<>"",H58,G58) | J58: UI prototype | K58: 3 | L58: 1 | M58: As the founder, I want fixed review rules so that every reviewer checks every screen the same way in one go. | N58: • Given review/RULES.md, when a reviewer starts, then rules R1–R11 apply in full (e.g. R11: pick-one uses the joined Segment control). • Given the pay checklist, when a pay story is reviewed, then every item is recorded pass or fail. • Given the time review reports, when read, then each finding names the screen and width. | P58: packages/yx-ui/review/RULES.md, PAY-CHECKLIST.md | R58: PR #130 · ab2b9928 · review/RULES.md · review/TIME-REVIEW.md
A59: US-A-053 | B59: 232 | C59: Story | D59: Responsive and dead-button checks | E59: Design docs and UI prototype | F59: Screen review tooling | G59: Done | I59: =IF(H59<>"",H59,G59) | J59: UI prototype | K59: 3 | L59: 1 | M59: As the founder, I want automatic checks for phone layouts and dead buttons so that problems are found without manual clicking. | N59: • Given check-responsive, when it runs over all stories and widths, then 14,560 of 14,560 checks pass (no page side-scroll). • Given scan-dead-buttons, when it runs, then it lists every button with no action. • Given the PAY-33 incentive table, when shown at phone width, then it scrolls inside its box. | P59: packages/yx-ui/scripts | R59: PR #130 · 3f37d883 · ad7fb32a · scripts/check-responsive.mjs · scripts/scan-dead-buttons.mjs
A60: US-A-054 | B60: 260 | C60: Story | D60: Run screenshot and accessibility tests in CI | E60: Design docs and UI prototype | F60: Screen review tooling | G60: New | I60: =IF(H60<>"",H60,G60) | J60: UI prototype | K60: 3 | L60: 2 | M60: As the founder, I want screenshot and axe tests to run in CI so that visual and accessibility regressions are caught. | N60: • Given test:visual, when CI runs on Linux, then it compares against Linux baselines. • Given test:a11y, when CI runs, then axe finds no serious or critical issue on wired screens. • Given a failure, when CI ends, then the diff image is attached to the run. | P60: deferred D-002
A61: FT-A-023 | B61: 240 | C61: Feature | D61: Design docs and tracker in the repo | E61: Design docs and UI prototype | F61: Design docs and tracker in the repo | G61: Done | I61: =IF(H61<>"",H61,G61) | J61: UI prototype | L61: 1 | P61: docs/yukthix | R61: PR #130 · 7ccb1d98 · 351edcae
A62: US-A-055 | B62: 241 | C62: Story | D62: Design docs, roadmap, go-live checklist and tracker in the repo | E62: Design docs and UI prototype | F62: Design docs and tracker in the repo | G62: Done | I62: =IF(H62<>"",H62,G62) | J62: UI prototype | K62: 3 | L62: 1 | M62: As the founder, I want all design docs and the tracker next to the code so that every build step cites the doc it follows. | N62: • Given docs/yukthix/design, when opened, then every P, M, T and APX doc is present. • Given BACKEND-ROADMAP.md, when read, then each step lists its design docs and status. • Given the tracker, when build_tracker.py runs, then the workbook lists rules, steps, screens, deferred items and PRs. | P62: BACKEND-ROADMAP.md, GO-LIVE-CHECKLIST.md, tracker | R62: PR #130 · 7ccb1d98 · cebf68f2 · b7f88606 · 351edcae · bd6143d0
A63: FT-A-024 | B63: 250 | C63: Feature | D63: Wire the prototype buttons step by step | E63: Design docs and UI prototype | F63: Wire the prototype buttons step by step | G63: New | I63: =IF(H63<>"",H63,G63) | J63: UI prototype | L63: 1 | P63: open-work W-007, deferred D-001
A64: US-A-056 | B64: 251 | C64: Story | D64: CI fails when a wired screen has a dead button | E64: Design docs and UI prototype | F64: Wire the prototype buttons step by step | G64: New | I64: =IF(H64<>"",H64,G64) | J64: UI prototype | K64: 2 | L64: 1 | M64: As the founder, I want a CI gate on wired screens so that no screen ships with buttons that do nothing. | N64: • Given a list of wired screens, when scan-dead-buttons runs in CI, then any dead button on them fails the build. • Given an unwired prototype screen, when the scan runs, then it is reported but does not fail the build. • Given the scan report, when published, then it shows the remaining count (1,039 at start). | P64: open-work W-007
A65: US-A-057 | B65: 480 | C65: Story | D65: Wire the platform screens (platform-a, platform-b) | E65: Design docs and UI prototype | F65: Wire the prototype buttons step by step | G65: New | I65: =IF(H65<>"",H65,G65) | J65: Step 3 | K65: 8 | L65: 2 | M65: As an HR admin, I want every button on the platform screens (platform-a, platform-b) to do its real action so that I can use the product, not a demo. | N65: • Given the Step 3 backend step is merged, when the screens are wired, then each button calls its real API or opens its real page. • Given the wired screens, when scan-dead-buttons runs, then it finds 0 dead buttons on them. • Given a button whose feature is not built yet, when shown, then it is hidden or disabled with a reason, never silent. | P65: open-work W-007, deferred D-001 | Q65: US-A-056
A66: US-A-058 | B66: 580 | C66: Story | D66: Wire the service desk and ops screens | E66: Design docs and UI prototype | F66: Wire the prototype buttons step by step | G66: New | I66: =IF(H66<>"",H66,G66) | J66: Step 3b | K66: 8 | L66: 2 | M66: As an HR admin, I want every button on the service desk and ops screens to do its real action so that I can use the product, not a demo. | N66: • Given the Step 3b backend step is merged, when the screens are wired, then each button calls its real API or opens its real page. • Given the wired screens, when scan-dead-buttons runs, then it finds 0 dead buttons on them. • Given a button whose feature is not built yet, when shown, then it is hidden or disabled with a reason, never silent. | P66: open-work W-007, deferred D-001 | Q66: US-A-056
A67: US-A-059 | B67: 680 | C67: Story | D67: Wire the time and leave screens | E67: Design docs and UI prototype | F67: Wire the prototype buttons step by step | G67: New | I67: =IF(H67<>"",H67,G67) | J67: Step 4 | K67: 8 | L67: 2 | M67: As an HR admin, I want every button on the time and leave screens to do its real action so that I can use the product, not a demo. | N67: • Given the Step 4 backend step is merged, when the screens are wired, then each button calls its real API or opens its real page. • Given the wired screens, when scan-dead-buttons runs, then it finds 0 dead buttons on them. • Given a button whose feature is not built yet, when shown, then it is hidden or disabled with a reason, never silent. | P67: open-work W-007, deferred D-001 | Q67: US-A-056
A68: US-A-060 | B68: 780 | C68: Story | D68: Wire the pay screens | E68: Design docs and UI prototype | F68: Wire the prototype buttons step by step | G68: New | I68: =IF(H68<>"",H68,G68) | J68: Step 5 | K68: 8 | L68: 2 | M68: As an HR admin, I want every button on the pay screens to do its real action so that I can use the product, not a demo. | N68: • Given the Step 5 backend step is merged, when the screens are wired, then each button calls its real API or opens its real page. • Given the wired screens, when scan-dead-buttons runs, then it finds 0 dead buttons on them. • Given a button whose feature is not built yet, when shown, then it is hidden or disabled with a reason, never silent. | P68: open-work W-007, deferred D-001 | Q68: US-A-056
A69: US-A-061 | B69: 1480 | C69: Story | D69: Wire the hiring, proctoring, growth, portals and notification screens | E69: Design docs and UI prototype | F69: Wire the prototype buttons step by step | G69: New | I69: =IF(H69<>"",H69,G69) | J69: Step 6+ | K69: 13 | L69: 2 | M69: As an HR admin, I want every button on the hiring, proctoring, growth, portals and notification screens to do its real action so that I can use the product, not a demo. | N69: • Given the Step 6+ backend step is merged, when the screens are wired, then each button calls its real API or opens its real page. • Given the wired screens, when scan-dead-buttons runs, then it finds 0 dead buttons on them. • Given a button whose feature is not built yet, when shown, then it is hidden or disabled with a reason, never silent. | P69: open-work W-007, deferred D-001 | Q69: US-A-056
A70: EP-A-4 | B70: 300 | C70: Epic | D70: Step 2 · Organisation and employee core | E70: Step 2 · Organisation and employee core | G70: Active | I70: =IF(H70<>"",H70,G70) | J70: Step 2 | L70: 1 | P70: P01, P02, P06, M01 §3.1–3.4, §3.9–3.10 | R70: branch feat/yukthix-org · 20 commits (3d325fba…95573e26)
A71: FT-A-030 | B71: 310 | C71: Feature | D71: 2a · Organisation structure | E71: Step 2 · Organisation and employee core | F71: 2a · Organisation structure | G71: Done | I71: =IF(H71<>"",H71,G71) | J71: Step 2a | L71: 1 | P71: P01 §4.1–4.3, §4.6 | R71: feat/yukthix-org · 58d87661 · 670ac48a · 10b3cfe4
A72: US-A-070 | B72: 311 | C72: Story | D72: Legal entities with one default and a fixed data region | E72: Step 2 · Organisation and employee core | F72: 2a · Organisation structure | G72: Done | I72: =IF(H72<>"",H72,G72) | J72: Step 2a | K72: 3 | L72: 1 | M72: As a company admin, I want to add our registered companies so that payroll and statutory work per employer. | N72: • Given a company, when it is created, then it gets one default legal entity (YX-ORG-01). • Given several entities, when I mark one default, then exactly one stays default (YX-ORG-01). • Given a legal entity, when created, then its country and data region are set and cannot be edited later (YX-ORG-30, YX-SEC-19). • Given PAN, TAN, GSTIN or CIN, when entered, then the format is validated. | O72: YX-ORG-01, YX-ORG-30, YX-SEC-19 | P72: P01 §4.1, P01 Q2 | R72: feat/yukthix-org · 58d87661 · 670ac48a · test/org-structure.e2e-spec.ts · org-structure.spec.ts
A73: US-A-071 | B73: 312 | C73: Story | D73: Locations belong to one legal entity | E73: Step 2 · Organisation and employee core | F73: 2a · Organisation structure | G73: Done | I73: =IF(H73<>"",H73,G73) | J73: Step 2a | K73: 2 | L73: 1 | M73: As an HR admin, I want to add work locations with state and time zone so that holidays, PT and times follow the right place. | N73: • Given a location, when saved without state or time zone, then it is refused (YX-ORG-02). • Given a location, when saved, then it belongs to exactly one legal entity (YX-ORG-02). • Given a geofence and network ranges, when entered, then they are stored on the location. | O73: YX-ORG-02 | P73: P01 §4.2 | R73: feat/yukthix-org · 58d87661 · 670ac48a · test/org-structure.e2e-spec.ts
A74: US-A-072 | B74: 313 | C74: Story | D74: Department tree with divisions | E74: Step 2 · Organisation and employee core | F74: 2a · Organisation structure | G74: Done | I74: =IF(H74<>"",H74,G74) | J74: Step 2a | K74: 3 | L74: 1 | M74: As an HR admin, I want departments in a tree so that reports and visibility work on a department and its subtree. | N74: • Given a department move, when it would create a cycle, then it is refused (YX-ORG-03). • Given a department move, when saved, then its whole subtree moves with it (YX-ORG-03). • Given a top-level department, when flagged as division, then it is only a label (P01 Q7). | O74: YX-ORG-03 | P74: P01 §4.3, P01 Q7 | R74: feat/yukthix-org · 58d87661 · 670ac48a · org-structure.spec.ts
A75: US-A-073 | B75: 314 | C75: Story | D75: Shared or entity-only masters with unique codes | E75: Step 2 · Organisation and employee core | F75: 2a · Organisation structure | G75: Done | I75: =IF(H75<>"",H75,G75) | J75: Step 2a | K75: 3 | L75: 1 | M75: As an HR admin, I want designations, grades and types shared across the group or kept to one entity so that groups keep one structure. | N75: • Given a shared master, when limited to some entities, then only those entities can use it (YX-ORG-15). • Given an entity-only master, when used for another entity's employee, then it is refused (YX-ORG-15). • Given a blank code, when saved, then the system generates one unique in its scope (YX-ORG-05). • Given a duplicate name or code in the same scope, when saved, then it is refused (YX-ORG-05). | O75: YX-ORG-15, YX-ORG-05 | P75: P01 §4.3, P01 Q3 | R75: feat/yukthix-org · 58d87661 · 670ac48a · org-structure.spec.ts
A76: US-A-074 | B76: 315 | C76: Story | D76: Used masters are archived, not deleted | E76: Step 2 · Organisation and employee core | F76: 2a · Organisation structure | G76: Done | I76: =IF(H76<>"",H76,G76) | J76: Step 2a | K76: 2 | L76: 1 | M76: As an HR admin, I want used masters archived instead of deleted so that history stays correct. | N76: • Given a master used by any record, when I delete it, then it is refused and I can archive it (YX-ORG-04). • Given an archived master, when someone picks it for a new assignment, then it is not offered (YX-ORG-04). • Given an archived master, when restored, then it can be used again (YX-ORG-04). | O76: YX-ORG-04 | P76: P01 §4 | R76: feat/yukthix-org · 670ac48a · 10b3cfe4 · test/org-structure.e2e-spec.ts
A77: US-A-075 | B77: 316 | C77: Story | D77: Cost centres and dated grade pay ranges | E77: Step 2 · Organisation and employee core | F77: 2a · Organisation structure | G77: Done | I77: =IF(H77<>"",H77,G77) | J77: Step 2a | K77: 3 | L77: 1 | M77: As a payroll admin, I want cost centres per entity and pay ranges per grade by date so that cost and pay checks are correct. | N77: • Given a cost centre, when its parent is in another entity, then it is refused (YX-ORG-08). • Given grade pay ranges, when two ranges overlap for the same grade, entity and currency, then it is refused (YX-HIS-02). • Given a range in force or in the past, when edited, then the past is never rewritten (YX-HIS-07). • Given a user without pay access, when they open grades, then pay ranges are hidden (YX-SEC-07). | O77: YX-ORG-08, YX-HIS-02, YX-HIS-07, YX-SEC-07 | P77: P01 §4.3 | R77: feat/yukthix-org · 58d87661 · 670ac48a · org-structure.spec.ts
A78: US-A-076 | B78: 317 | C78: Story | D78: Entity statutory identifiers are Confidential | E78: Step 2 · Organisation and employee core | F78: 2a · Organisation structure | G78: Done | I78: =IF(H78<>"",H78,G78) | J78: Step 2a | K78: 2 | L78: 1 | M78: As a company admin, I want our entity's statutory numbers protected so that only the right people see them. | N78: • Given statutory identifiers, when a user without org.entity.statutory.manage opens the entity, then only 'on file / missing' shows (YX-SEC-07). • Given an allowed user, when they open the identifiers, then step-up is asked (YX-IAM-02). • Given the identifiers are read, when shown, then the read is audited (YX-SEC-09). | O78: YX-SEC-07, YX-SEC-09, YX-IAM-02 | P78: P02 §4.4 | R78: feat/yukthix-org · 3d325fba · 670ac48a · 10b3cfe4
A79: US-A-077 | B79: 318 | C79: Story | D79: Scoped settings show where a value comes from | E79: Step 2 · Organisation and employee core | F79: 2a · Organisation structure | G79: Done | I79: =IF(H79<>"",H79,G79) | J79: Step 2a | K79: 3 | L79: 1 | M79: As an HR admin, I want a setting to resolve from the most specific scope and show its source so that I know why a value applies. | N79: • Given a value at tenant and entity, when resolved for that entity, then the entity value wins (YX-ORG-12, YX-ORG-18). • Given an employee, when a setting resolves, then it uses the assignment in force on the as-of date (YX-ORG-18). • Given a dated setting, when resolved for a past period, then the value in force then is used (YX-ORG-18). • Given the settings screen, when a value is inherited, then it says from where (YX-ORG-12). | O79: YX-ORG-12, YX-ORG-18 | P79: P01 §4.6 | R79: feat/yukthix-org · 670ac48a · 7e8bfb52 · org-settings.service.ts · settings-registry.ts
A80: US-A-078 | B80: 319 | C80: Story | D80: Settings › Organisation screens wired | E80: Step 2 · Organisation and employee core | F80: 2a · Organisation structure | G80: Done | I80: =IF(H80<>"",H80,G80) | J80: Step 2a | K80: 5 | L80: 1 | M80: As a company admin, I want working screens for entities, locations and structure so that I set up the company without support. | N80: • Given Settings › Organisation, when opened, then legal entities, locations and structure tabs load from the API (YX-ORG-12). • Given archive, restore and delete, when chosen in a row menu, then each asks to confirm (YX-ORG-04). • Given my permissions, when navigation renders, then only pages I can open are shown (GET /rbac/me/permissions) (YX-SEC-01). • Given every structure change, when saved, then an audit entry is written in the same transaction. | O80: YX-ORG-12, YX-ORG-04, YX-SEC-01 | P80: P01 §8 | R80: feat/yukthix-org · 10b3cfe4 · b090e49b · ea573922 · org.test.tsx · yx-org-pages.test.tsx · audit.service.spec.ts
A81: US-A-079 | B81: 320 | C81: Story | D81: Pick parents in a tree and set entity-specific settings | E81: Step 2 · Organisation and employee core | F81: 2a · Organisation structure | G81: New | I81: =IF(H81<>"",H81,G81) | J81: Step 2a follow-up | K81: 3 | L81: 3 | M81: As an HR admin, I want to pick a parent department from a tree and set a rule for one entity so that set-up matches how we think. | N81: • Given the department form, when I choose a parent, then a tree view is shown, not a flat list (YX-ORG-03). • Given a scoped setting, when I open an entity, then I can set or reset its own value (YX-ORG-12). • Given an override, when saved, then the screen shows the source changing from tenant to entity (YX-ORG-12). | O81: YX-ORG-03, YX-ORG-12 | P81: P01 §8, deferred D-030, deferred D-031 | Q81: US-A-078
A82: FT-A-031 | B82: 330 | C82: Feature | D82: 2b · Effective-dated history | E82: Step 2 · Organisation and employee core | F82: 2b · Effective-dated history | G82: Done | I82: =IF(H82<>"",H82,G82) | J82: Step 2b | L82: 1 | P82: P06 | R82: feat/yukthix-org · 1c41b543 · 7e8bfb52 · 8bbb7018
A83: US-A-080 | B83: 331 | C83: Story | D83: Employees join through a join change | E83: Step 2 · Organisation and employee core | F83: 2b · Effective-dated history | G83: Done | I83: =IF(H83<>"",H83,G83) | J83: Step 2b | K83: 3 | L83: 1 | M83: As an HR admin, I want to add an employee with a joining date so that their employment and first assignment start correctly. | N83: • Given a new joiner, when added, then an employment and first assignment are created by a join change (YX-HIS-01). • Given an employee code, when blank, then it is generated per entity or per company as set (YX-ORG-16). • Given an employee with an open employment, when another is opened in the company, then it is refused (YX-ORG-06). • Given the new rows, when stored, then they carry forced RLS (YX-ORG-14). | O83: YX-HIS-01, YX-ORG-16, YX-ORG-06, YX-ORG-14 | P83: P01 §4.4, P06 §4.3 | R83: feat/yukthix-org · 1c41b543 · 7e8bfb52 · test/employee-history.e2e-spec.ts · test/rls-isolation.e2e-spec.ts
A84: US-A-081 | B84: 332 | C84: Story | D84: Job changes are requested and approved by someone else | E84: Step 2 · Organisation and employee core | F84: 2b · Effective-dated history | G84: Done | I84: =IF(H84<>"",H84,G84) | J84: Step 2b | K84: 5 | L84: 1 | M84: As an HR admin, I want every promotion, transfer or revision to be a change approved by another person so that nobody edits history alone. | N84: • Given a dated fact, when anyone tries to write it outside an approved change, then the database trigger refuses (YX-HIS-01). • Given a change, when the requester or the subject tries to approve, then it is refused (YX-SEC-11). • Given an approval, when given, then step-up is asked (YX-IAM-02). • Given a promotion with a pay change, when approved, then compensation changes in the same change (YX-EMP-05). | O84: YX-HIS-01, YX-SEC-11, YX-IAM-02, YX-EMP-05 | P84: P06 §4.3, M01 §3.3 | R84: feat/yukthix-org · 1c41b543 · ddc92a0e · 7e8bfb52 · employee-history.service.spec.ts · test/employee-history.e2e-spec.ts
A85: US-A-082 | B85: 333 | C85: Story | D85: History has no gaps, overlaps or reporting loops | E85: Step 2 · Organisation and employee core | F85: 2b · Effective-dated history | G85: Done | I85: =IF(H85<>"",H85,G85) | J85: Step 2b | K85: 5 | L85: 1 | M85: As an HR admin, I want the system to keep job history clean so that payroll and reports can trust it. | N85: • Given current rows, when two overlap for the same person, then the GiST constraint refuses (YX-HIS-02). • Given an employment, when a change would leave a day without an assignment, then it is refused (YX-HIS-03, YX-ORG-07). • Given a manager, when they are not employed on every day or would create a loop, then it is refused (YX-ORG-09). • Given a location, cost centre or master, when not live or not open to the employer, then it is refused (YX-ORG-04, YX-ORG-08, YX-ORG-15). | O85: YX-HIS-02, YX-HIS-03, YX-ORG-07, YX-ORG-09, YX-ORG-04, YX-ORG-08, YX-ORG-15 | P85: P06 §4.2, P01 §6 | R85: feat/yukthix-org · 1c41b543 · 7e8bfb52 · history-rules.spec.ts · test/employee-history.e2e-spec.ts
A86: US-A-083 | B86: 334 | C86: Story | D86: Scheduled changes apply on their date | E86: Step 2 · Organisation and employee core | F86: 2b · Effective-dated history | G86: Done | I86: =IF(H86<>"",H86,G86) | J86: Step 2b | K86: 3 | L86: 1 | M86: As an HR admin, I want a promotion approved today for 1 Oct to apply by itself on 1 Oct so that I don't need to remember it. | N86: • Given a future change, when approved, then it shows as scheduled (YX-ORG-10). • Given the effective date, when 00:00 arrives in the employee's location time zone, then the change becomes effective (YX-HIS-04). • Given the sweep runs twice, when it re-runs, then no row is applied twice (YX-HIS-05). • Given applying, when it runs, then rows close and open in one transaction (YX-HIS-05). | O86: YX-ORG-10, YX-HIS-04, YX-HIS-05 | P86: P06 §4.3, P06 Q3 | R86: feat/yukthix-org · 7e8bfb52 · scheduled-sweeps.worker.service.spec.ts · test/employee-history.e2e-spec.ts
A87: US-A-084 | B87: 335 | C87: Story | D87: Earlier changes rebase later scheduled ones | E87: Step 2 · Organisation and employee core | F87: 2b · Effective-dated history | G87: Done | I87: =IF(H87<>"",H87,G87) | J87: Step 2b | K87: 3 | L87: 1 | M87: As an HR admin, I want a new transfer dated before a scheduled increment to recalculate that increment so that values stay right. | N87: • Given a scheduled % increment, when a change is inserted before it, then the increment keeps its % on the new base (YX-HIS-06). • Given the rebase, when I approve, then I see the recalculated values and confirm first (YX-HIS-06). • Given a scheduled change, when I move its date or values, then it goes back for approval; cancel needs a reason (YX-HIS-01). | O87: YX-HIS-06, YX-HIS-01 | P87: P06 §4.4, P06 Q7 | R87: feat/yukthix-org · 7e8bfb52 · 8bbb7018 · employee-history.service.spec.ts
A88: US-A-085 | B88: 336 | C88: Story | D88: Past corrections supersede, never delete | E88: Step 2 · Organisation and employee core | F88: 2b · Effective-dated history | G88: Done | I88: =IF(H88<>"",H88,G88) | J88: Step 2b | K88: 3 | L88: 1 | M88: As an HR admin, I want to correct a past mistake while keeping what we believed before so that audits stay explainable. | N88: • Given a past-dated change, when approved, then replaced rows are marked superseded with who, when and why (YX-HIS-07). • Given recorded and superseded times, when stored, then they come from the database clock (YX-HIS-07). • Given a change before the company's retro limit, when sent, then only a System Admin override with a reason is allowed (YX-HIS-12, YX-ORG-10). • Given a past change, when saved, then the affected payroll months are flagged on it (YX-HIS-12). | O88: YX-HIS-07, YX-HIS-12, YX-ORG-10 | P88: P06 §4.5, P06 Q5 | R88: feat/yukthix-org · 1c41b543 · 7e8bfb52 · dde92c0b · test/employee-history.e2e-spec.ts
A89: US-A-086 | B89: 337 | C89: Story | D89: Read history as on any date | E89: Step 2 · Organisation and employee core | F89: 2b · Effective-dated history | G89: Done | I89: =IF(H89<>"",H89,G89) | J89: Step 2b | K89: 3 | L89: 1 | M89: As a manager, I want to see my team member's job as on a date so that I can answer 'who was their manager on 1 Jul?'. | N89: • Given as-of, when asked 'as corrected now' or 'as recorded at T', then the right values return (YX-HIS-10). • Given a manager, when they read a person's history, then only the periods they managed are visible (YX-SEC-06, YX-HIS-10). • Given segments(from, to), when called, then each period where a fact changed is returned (YX-HIS-10). • Given the person or their manager, when they read history, then only approved changes show, without the impact (YX-SEC-06). | O89: YX-HIS-10, YX-SEC-06 | P89: P06 §4.7 | R89: feat/yukthix-org · 7e8bfb52 · 63ec5516 · test/employee-history.e2e-spec.ts
A90: US-A-087 | B90: 338 | C90: Story | D90: Impact preview and 'Show pay' | E90: Step 2 · Organisation and employee core | F90: 2b · Effective-dated history | G90: Done | I90: =IF(H90<>"",H90,G90) | J90: Step 2b | K90: 2 | L90: 1 | M90: As an HR admin, I want to see what else a change affects before approving, and see pay only when I ask, so that I approve with care and pay stays private. | N90: • Given a change, when reviewed, then the impact preview lists derived effects before approval (YX-HIS-11). • Given job history, when opened, then pay is hidden until 'Show pay' and only for pay access (YX-SEC-07). • Given someone views another person's pay, when shown, then the view is audited (YX-SEC-09). | O90: YX-HIS-11, YX-SEC-07, YX-SEC-09 | P90: P06 §4.3, P02 §4.4 | R90: feat/yukthix-org · 7e8bfb52 · 39c0229c · employee-history.service.spec.ts
A91: US-A-088 | B91: 339 | C91: Story | D91: People › Job history and Job changes screens | E91: Step 2 · Organisation and employee core | F91: 2b · Effective-dated history | G91: Done | I91: =IF(H91<>"",H91,G91) | J91: Step 2b | K91: 5 | L91: 1 | M91: As an HR admin, I want screens to see a timeline and handle waiting, scheduled and done changes so that I can run job changes daily. | N91: • Given Job history, when I pick a date, then the record as on that date shows, with scheduled changes styled differently (YX-HIS-10). • Given a change that touches the past, when listed, then it is marked 'Changes the past' (YX-HIS-07). • Given Review, when opened, then the impact shows and Approve confirms recalculated later changes (YX-HIS-11, YX-HIS-06). • Given the change form, when before the retro limit, then it asks for the override reason (YX-HIS-12). | O91: YX-HIS-10, YX-HIS-07, YX-HIS-11, YX-HIS-06, YX-HIS-12 | P91: P06 §7 | R91: feat/yukthix-org · 8bbb7018 · 7c246268 · history.test.tsx · yx-people-pages.test.tsx
A92: FT-A-032 | B92: 340 | C92: Feature | D92: 2c · Employee record, persons, org chart, probation and bulk changes | E92: Step 2 · Organisation and employee core | F92: 2c · Employee record, persons, org chart, probation and bulk changes | G92: Active | I92: =IF(H92<>"",H92,G92) | J92: Step 2c | L92: 1 | P92: P01 §4.4–4.5a, M01 §3.1–3.4, §3.10 | R92: feat/yukthix-org · dde92c0b · 33b18e60 · 0b1f1f94 · 95573e26
A93: US-A-090 | B93: 341 | C93: Story | D93: One person record per human | E93: Step 2 · Organisation and employee core | F93: 2c · Employee record, persons, org chart, probation and bulk changes | G93: Done | I93: =IF(H93<>"",H93,G93) | J93: Step 2c | K93: 5 | L93: 1 | M93: As an HR admin, I want each human to have one person record in our company so that a candidate who joins keeps one history. | N93: • Given a hire, when saved, then a person with employee and login roles is created (YX-ORG-26). • Given an email or phone of an existing person, when a new hire uses it, then it is not linked silently (409 POSSIBLE_SAME_PERSON) (YX-ORG-27). • Given HR links by personId, when confirmed, then person_link_log records it as confirmed (YX-ORG-27). • Given persons, when read, then they never cross companies (YX-ORG-26, YX-ORG-14). | O93: YX-ORG-26, YX-ORG-27, YX-ORG-14 | P93: P01 §4.5a | R93: feat/yukthix-org · dde92c0b · 33b18e60 · test/people-core.e2e-spec.ts · test/rls-isolation.e2e-spec.ts
A94: US-A-091 | B94: 342 | C94: Story | D94: 'Possible same person' queue with reversible merge | E94: Step 2 · Organisation and employee core | F94: 2c · Employee record, persons, org chart, probation and bulk changes | G94: New | I94: =IF(H94<>"",H94,G94) | J94: Step 2c | K94: 5 | L94: 2 | M94: As an HR admin, I want to confirm or reject possible duplicates and undo a wrong merge so that no two records describe one person. | N94: • Given verified email, phone, PAN or UAN, when a new role record matches, then it auto-links (YX-ORG-27). • Given conflicting keys or name + DOB similarity, when found, then a proposal appears in the queue; a name alone never links (YX-ORG-27). • Given a merge, when undone, then each role and its records go back to the original person (YX-ORG-27). • Given any link, merge or unmerge, when done, then person_link_log records basis, actor and reason (YX-ORG-27). | O94: YX-ORG-27 | P94: P01 §4.5a | Q94: US-A-090
A95: US-A-092 | B95: 343 | C95: Story | D95: Dotted-line managers | E95: Step 2 · Organisation and employee core | F95: 2c · Employee record, persons, org chart, probation and bulk changes | G95: Done | I95: =IF(H95<>"",H95,G95) | J95: Step 2c | K95: 2 | L95: 1 | M95: As an HR admin, I want to add a secondary manager to an assignment so that project leads can see and give feedback. | N95: • Given a dotted-line manager, when saved with an assignment, then they must be employed on every day (YX-ORG-09). • Given a dotted-line manager, when approvals route, then they are never in the chain unless a policy names them (YX-EMP-04). • Given a person, when they are made their own dotted-line manager, then it is refused (YX-ORG-09). | O95: YX-EMP-04, YX-ORG-09 | P95: M01 §3.2, M01 Q5 | R95: feat/yukthix-org · dde92c0b · 33b18e60 · test/people-core.e2e-spec.ts
A96: US-A-093 | B96: 344 | C96: Story | D96: Org chart as on any date | E96: Step 2 · Organisation and employee core | F96: 2c · Employee record, persons, org chart, probation and bulk changes | G96: Active | I96: =IF(H96<>"",H96,G96) | J96: Step 2c | K96: 3 | L96: 1 | M96: As an employee, I want an org chart with search and expand so that I know who reports to whom. | N96: • Given the org chart, when opened, then managers, dotted lines and report counts show (YX-EMP-04). • Given an HR admin, when they pick a past date, then the chart shows as on that date (YX-HIS-10). • Given any viewer, when the chart loads, then only Public fields show and no pay (YX-SEC-07). | O96: YX-EMP-04, YX-HIS-10, YX-SEC-07 | P96: M01 §3.2 | R96: feat/yukthix-org · 0b1f1f94 (API) · org-chart screen in progress (uncommitted)
A97: US-A-094 | B97: 345 | C97: Story | D97: Colleague directory | E97: Step 2 · Organisation and employee core | F97: 2c · Employee record, persons, org chart, probation and bulk changes | G97: Active | I97: =IF(H97<>"",H97,G97) | J97: Step 2c | K97: 3 | L97: 1 | M97: As an employee, I want to search colleagues by name, entity, location or department so that I can find and contact people. | N97: • Given the directory, when I search, then only Public fields show (YX-SEC-17). • Given HR, when they search, then codes and joining dates also show (YX-SEC-07). • Given a search with % or _, when run, then wildcards are escaped. • Given a department filter, when chosen, then its whole subtree is included. | O97: YX-SEC-17, YX-SEC-07 | P97: P02 Q4, M01 §1 | R97: feat/yukthix-org · 0b1f1f94 (API) · people/directory screen and workforce screens uncommitted
A98: US-A-095 | B98: 346 | C98: Story | D98: Manager Team page | E98: Step 2 · Organisation and employee core | F98: 2c · Employee record, persons, org chart, probation and bulk changes | G98: Active | I98: =IF(H98<>"",H98,G98) | J98: Step 2c | K98: 3 | L98: 1 | M98: As a manager, I want a team page with direct, indirect and dotted-line reports so that I see my people and their probation ends. | N98: • Given my team, when opened, then direct, indirect and dotted-line reports show (YX-SEC-05). • Given a report on probation, when listed, then the end date shows (YX-LC-01). • Given my reports, when listed, then no pay shows without the team-salary grant (YX-SEC-07). | O98: YX-SEC-05, YX-LC-01, YX-SEC-07 | P98: M01 §3.10, P02 Q2 | R98: feat/yukthix-org · 0b1f1f94 (API employees/:id/reports, team) · team screen in progress
A99: US-A-096 | B99: 347 | C99: Story | D99: Managers raise job changes for their team | E99: Step 2 · Organisation and employee core | F99: 2c · Employee record, persons, org chart, probation and bulk changes | G99: Done | I99: =IF(H99<>"",H99,G99) | J99: Step 2c | K99: 3 | L99: 1 | M99: As a manager, I want to start a promotion, transfer or manager change for my team so that HR gets a complete request. | N99: • Given request.raise_on_behalf, when I raise a change, then the subject must be in my current subtree (YX-SEC-27). • Given a pay field, when I lack the pay grant, then I cannot change it (YX-SEC-27). • Given a change I raised, when it is up for approval, then I can never approve it (YX-SEC-11, YX-SEC-27). • Given my raised changes, when listed, then I see and can withdraw only those I raised. | O99: YX-SEC-27, YX-SEC-11 | P99: M01 §3.10, P02 §4.6 | R99: feat/yukthix-org · 33b18e60 · 95573e26 (Team Manager profile) · test/people-core.e2e-spec.ts
A100: US-A-097 | B100: 348 | C100: Story | D100: Probation plans, reviews and confirmation | E100: Step 2 · Organisation and employee core | F100: 2c · Employee record, persons, org chart, probation and bulk changes | G100: Active | I100: =IF(H100<>"",H100,G100) | J100: Step 2c | K100: 3 | L100: 1 | M100: As an HR admin, I want probation tracked with reminders so that no confirmation is missed. | N100: • Given a joiner on probation, when added, then a plan with the default length per type or grade is created (YX-LC-01). • Given N days before the end, when the sweep runs, then the manager gets a review reminder once (YX-LC-01). • Given no action by the end date, when the sweep runs, then it escalates to HR; auto-confirm only if switched on (YX-LC-01). • Given an extension, when beyond the company maximum, then it is refused (YX-LC-01). | O100: YX-LC-01 | P100: M01 §3.4, M01 Q3 | R100: feat/yukthix-org · dde92c0b · 33b18e60 · 0b1f1f94 · test/people-core.e2e-spec.ts · probation screen in progress
...

Sheet Plan
A1: Phase | B1: Roadmap step | C1: Starts at order | D1: Epics | E1: Stories | F1: Points | G1: Done | H1: Active | I1: New | J1: % done (points)
A2: Step 0 | B2: Step 0 | C2: 11 | D2: Step 0 · PostgreSQL and tenant isolation | E2: =COUNTIFS(Backlog!$J$2:$J$1564,$A2,Backlog!$C$2:$C$1564,"Story") | F2: =SUMIFS(Backlog!$K$2:$K$1564,Backlog!$J$2:$J$1564,$A2,Backlog!$C$2:$C$1564,"Story") | G2: =COUNTIFS(Backlog!$J$2:$J$1564,$A2,Backlog!$C$2:$C$1564,"Story",Backlog!$I$2:$I$1564,"Done") | H2: =COUNTIFS(Backlog!$J$2:$J$1564,$A2,Backlog!$C$2:$C$1564,"Story",Backlog!$I$2:$I$1564,"Active") | I2: =COUNTIFS(Backlog!$J$2:$J$1564,$A2,Backlog!$C$2:$C$1564,"Story",Backlog!$I$2:$I$1564,"New") | J2: =IF(F2=0,"",SUMIFS(Backlog!$K$2:$K$1564,Backlog!$J$2:$J$1564,$A2,Backlog!$C$2:$C$1564,"Story",Backlog!$I$2:$I$1564,"Done")/F2)
A3: Step 1a | B3: Step 1 | C3: 111 | D3: Step 1 · Login and security | E3: =COUNTIFS(Backlog!$J$2:$J$1564,$A3,Backlog!$C$2:$C$1564,"Story") | F3: =SUMIFS(Backlog!$K$2:$K$1564,Backlog!$J$2:$J$1564,$A3,Backlog!$C$2:$C$1564,"Story") | G3: =COUNTIFS(Backlog!$J$2:$J$1564,$A3,Backlog!$C$2:$C$1564,"Story",Backlog!$I$2:$I$1564,"Done") | H3: =COUNTIFS(Backlog!$J$2:$J$1564,$A3,Backlog!$C$2:$C$1564,"Story",Backlog!$I$2:$I$1564,"Active") | I3: =COUNTIFS(Backlog!$J$2:$J$1564,$A3,Backlog!$C$2:$C$1564,"Story",Backlog!$I$2:$I$1564,"New") | J3: =IF(F3=0,"",SUMIFS(Backlog!$K$2:$K$1564,Backlog!$J$2:$J$1564,$A3,Backlog!$C$2:$C$1564,"Story",Backlog!$I$2:$I$1564,"Done")/F3)
A4: Step 1 lockout-policy | B4: Step 1 | C4: 113 | D4: Step 1 · Login and security | E4: =COUNTIFS(Backlog!$J$2:$J$1564,$A4,Backlog!$C$2:$C$1564,"Story") | F4: =SUMIFS(Backlog!$K$2:$K$1564,Backlog!$J$2:$J$1564,$A4,Backlog!$C$2:$C$1564,"Story") | G4: =COUNTIFS(Backlog!$J$2:$J$1564,$A4,Backlog!$C$2:$C$1564,"Story",Backlog!$I$2:$I$1564,"Done") | H4: =COUNTIFS(Backlog!$J$2:$J$1564,$A4,Backlog!$C$2:$C$1564,"Story",Backlog!$I$2:$I$1564,"Active") | I4: =COUNTIFS(Backlog!$J$2:$J$1564,$A4,Backlog!$C$2:$C$1564,"Story",Backlog!$I$2:$I$1564,"New") | J4: =IF(F4=0,"",SUMIFS(Backlog!$K$2:$K$1564,Backlog!$J$2:$J$1564,$A4,Backlog!$C$2:$C$1564,"Story",Backlog!$I$2:$I$1564,"Done")/F4)
A5: Step 1 fix-review | B5: Step 1 | C5: 114 | D5: Step 1 · Login and security | E5: =COUNTIFS(Backlog!$J$2:$J$1564,$A5,Backlog!$C$2:$C$1564,"Story") | F5: =SUMIFS(Backlog!$K$2:$K$1564,Backlog!$J$2:$J$1564,$A5,Backlog!$C$2:$C$1564,"Story") | G5: =COUNTIFS(Backlog!$J$2:$J$1564,$A5,Backlog!$C$2:$C$1564,"Story",Backlog!$I$2:$I$1564,"Done") | H5: =COUNTIFS(Backlog!$J$2:$J$1564,$A5,Backlog!$C$2:$C$1564,"Story",Backlog!$I$2:$I$1564,"Active") | I5: =COUNTIFS(Backlog!$J$2:$J$1564,$A5,Backlog!$C$2:$C$1564,"Story",Backlog!$I$2:$I$1564,"New") | J5: =IF(F5=0,"",SUMIFS(Backlog!$K$2:$K$1564,Backlog!$J$2:$J$1564,$A5,Backlog!$C$2:$C$1564,"Story",Backlog!$I$2:$I$1564,"Done")/F5)
A6: Step 1b | B6: Step 1 | C6: 121 | D6: Step 1 · Login and security | E6: =COUNTIFS(Backlog!$J$2:$J$1564,$A6,Backlog!$C$2:$C$1564,"Story") | F6: =SUMIFS(Backlog!$K$2:$K$1564,Backlog!$J$2:$J$1564,$A6,Backlog!$C$2:$C$1564,"Story") | G6: =COUNTIFS(Backlog!$J$2:$J$1564,$A6,Backlog!$C$2:$C$1564,"Story",Backlog!$I$2:$I$1564,"Done") | H6: =COUNTIFS(Backlog!$J$2:$J$1564,$A6,Backlog!$C$2:$C$1564,"Story",Backlog!$I$2:$I$1564,"Active") | I6: =COUNTIFS(Backlog!$J$2:$J$1564,$A6,Backlog!$C$2:$C$1564,"Story",Backlog!$I$2:$I$1564,"New") | J6: =IF(F6=0,"",SUMIFS(Backlog!$K$2:$K$1564,Backlog!$J$2:$J$1564,$A6,Backlog!$C$2:$C$1564,"Story",Backlog!$I$2:$I$1564,"Done")/F6)
A7: Step 1c | B7: Step 1 | C7: 131 | D7: Step 1 · Login and security | E7: =COUNTIFS(Backlog!$J$2:$J$1564,$A7,Backlog!$C$2:$C$1564,"Story") | F7: =SUMIFS(Backlog!$K$2:$K$1564,Backlog!$J$2:$J$1564,$A7,Backlog!$C$2:$C$1564,"Story") | G7: =COUNTIFS(Backlog!$J$2:$J$1564,$A7,Backlog!$C$2:$C$1564,"Story",Backlog!$I$2:$I$1564,"Done") | H7: =COUNTIFS(Backlog!$J$2:$J$1564,$A7,Backlog!$C$2:$C$1564,"Story",Backlog!$I$2:$I$1564,"Active") | I7: =COUNTIFS(Backlog!$J$2:$J$1564,$A7,Backlog!$C$2:$C$1564,"Story",Backlog!$I$2:$I$1564,"New") | J7: =IF(F7=0,"",SUMIFS(Backlog!$K$2:$K$1564,Backlog!$J$2:$J$1564,$A7,Backlog!$C$2:$C$1564,"Story",Backlog!$I$2:$I$1564,"Done")/F7)
A8: Step 1d | B8: Step 1 | C8: 141 | D8: Step 1 · Login and security | E8: =COUNTIFS(Backlog!$J$2:$J$1564,$A8,Backlog!$C$2:$C$1564,"Story") | F8: =SUMIFS(Backlog!$K$2:$K$1564,Backlog!$J$2:$J$1564,$A8,Backlog!$C$2:$C$1564,"Story") | G8: =COUNTIFS(Backlog!$J$2:$J$1564,$A8,Backlog!$C$2:$C$1564,"Story",Backlog!$I$2:$I$1564,"Done") | H8: =COUNTIFS(Backlog!$J$2:$J$1564,$A8,Backlog!$C$2:$C$1564,"Story",Backlog!$I$2:$I$1564,"Active") | I8: =COUNTIFS(Backlog!$J$2:$J$1564,$A8,Backlog!$C$2:$C$1564,"Story",Backlog!$I$2:$I$1564,"New") | J8: =IF(F8=0,"",SUMIFS(Backlog!$K$2:$K$1564,Backlog!$J$2:$J$1564,$A8,Backlog!$C$2:$C$1564,"Story",Backlog!$I$2:$I$1564,"Done")/F8)
A9: Step 1 sms-channel | B9: Step 1 | C9: 142 | D9: Step 1 · Login and security | E9: =COUNTIFS(Backlog!$J$2:$J$1564,$A9,Backlog!$C$2:$C$1564,"Story") | F9: =SUMIFS(Backlog!$K$2:$K$1564,Backlog!$J$2:$J$1564,$A9,Backlog!$C$2:$C$1564,"Story") | G9: =COUNTIFS(Backlog!$J$2:$J$1564,$A9,Backlog!$C$2:$C$1564,"Story",Backlog!$I$2:$I$1564,"Done") | H9: =COUNTIFS(Backlog!$J$2:$J$1564,$A9,Backlog!$C$2:$C$1564,"Story",Backlog!$I$2:$I$1564,"Active") | I9: =COUNTIFS(Backlog!$J$2:$J$1564,$A9,Backlog!$C$2:$C$1564,"Story",Backlog!$I$2:$I$1564,"New") | J9: =IF(F9=0,"",SUMIFS(Backlog!$K$2:$K$1564,Backlog!$J$2:$J$1564,$A9,Backlog!$C$2:$C$1564,"Story",Backlog!$I$2:$I$1564,"Done")/F9)
A10: Step 1e | B10: Step 1 | C10: 151 | D10: Step 1 · Login and security | E10: =COUNTIFS(Backlog!$J$2:$J$1564,$A10,Backlog!$C$2:$C$1564,"Story") | F10: =SUMIFS(Backlog!$K$2:$K$1564,Backlog!$J$2:$J$1564,$A10,Backlog!$C$2:$C$1564,"Story") | G10: =COUNTIFS(Backlog!$J$2:$J$1564,$A10,Backlog!$C$2:$C$1564,"Story",Backlog!$I$2:$I$1564,"Done") | H10: =COUNTIFS(Backlog!$J$2:$J$1564,$A10,Backlog!$C$2:$C$1564,"Story",Backlog!$I$2:$I$1564,"Active") | I10: =COUNTIFS(Backlog!$J$2:$J$1564,$A10,Backlog!$C$2:$C$1564,"Story",Backlog!$I$2:$I$1564,"New") | J10: =IF(F10=0,"",SUMIFS(Backlog!$K$2:$K$1564,Backlog!$J$2:$J$1564,$A10,Backlog!$C$2:$C$1564,"Story",Backlog!$I$2:$I$1564,"Done")/F10)
A11: Step 1 login-no-code | B11: Step 1 | C11: 161 | D11: Step 1 · Login and security | E11: =COUNTIFS(Backlog!$J$2:$J$1564,$A11,Backlog!$C$2:$C$1564,"Story") | F11: =SUMIFS(Backlog!$K$2:$K$1564,Backlog!$J$2:$J$1564,$A11,Backlog!$C$2:$C$1564,"Story") | G11: =COUNTIFS(Backlog!$J$2:$J$1564,$A11,Backlog!$C$2:$C$1564,"Story",Backlog!$I$2:$I$1564,"Done") | H11: =COUNTIFS(Backlog!$J$2:$J$1564,$A11,Backlog!$C$2:$C$1564,"Story",Backlog!$I$2:$I$1564,"Active") | I11: =COUNTIFS(Backlog!$J$2:$J$1564,$A11,Backlog!$C$2:$C$1564,"Story",Backlog!$I$2:$I$1564,"New") | J11: =IF(F11=0,"",SUMIFS(Backlog!$K$2:$K$1564,Backlog!$J$2:$J$1564,$A11,Backlog!$C$2:$C$1564,"Story",Backlog!$I$2:$I$1564,"Done")/F11)
A12: Step 1 follow-up | B12: Step 1 | C12: 170 | D12: Step 1 · Login and security | E12: =COUNTIFS(Backlog!$J$2:$J$1564,$A12,Backlog!$C$2:$C$1564,"Story") | F12: =SUMIFS(Backlog!$K$2:$K$1564,Backlog!$J$2:$J$1564,$A12,Backlog!$C$2:$C$1564,"Story") | G12: =COUNTIFS(Backlog!$J$2:$J$1564,$A12,Backlog!$C$2:$C$1564,"Story",Backlog!$I$2:$I$1564,"Done") | H12: =COUNTIFS(Backlog!$J$2:$J$1564,$A12,Backlog!$C$2:$C$1564,"Story",Backlog!$I$2:$I$1564,"Active") | I12: =COUNTIFS(Backlog!$J$2:$J$1564,$A12,Backlog!$C$2:$C$1564,"Story",Backlog!$I$2:$I$1564,"New") | J12: =IF(F12=0,"",SUMIFS(Backlog!$K$2:$K$1564,Backlog!$J$2:$J$1564,$A12,Backlog!$C$2:$C$1564,"Story",Backlog!$I$2:$I$1564,"Done")/F12)
A13: Step 1g | B13: Step 1 | C13: 181 | D13: Step 1 · Login and security | E13: =COUNTIFS(Backlog!$J$2:$J$1564,$A13,Backlog!$C$2:$C$1564,"Story") | F13: =SUMIFS(Backlog!$K$2:$K$1564,Backlog!$J$2:$J$1564,$A13,Backlog!$C$2:$C$1564,"Story") | G13: =COUNTIFS(Backlog!$J$2:$J$1564,$A13,Backlog!$C$2:$C$1564,"Story",Backlog!$I$2:$I$1564,"Done") | H13: =COUNTIFS(Backlog!$J$2:$J$1564,$A13,Backlog!$C$2:$C$1564,"Story",Backlog!$I$2:$I$1564,"Active") | I13: =COUNTIFS(Backlog!$J$2:$J$1564,$A13,Backlog!$C$2:$C$1564,"Story",Backlog!$I$2:$I$1564,"New") | J13: =IF(F13=0,"",SUMIFS(Backlog!$K$2:$K$1564,Backlog!$J$2:$J$1564,$A13,Backlog!$C$2:$C$1564,"Story",Backlog!$I$2:$I$1564,"Done")/F13)
... A87: Proctoring track · phase 2 | B87: ATS & assessments | C87: 1710 | D87: Assessments & proctoring | E87: =COUNTIFS(Backlog!$J$2:$J$1564,$A87,Backlog!$C$2:$C$1564,"Story") | F87: =SUMIFS(Backlog!$K$2:$K$1564,Backlog!$J$2:$J$1564,$A87,Backlog!$C$2:$C$1564,"Story") | G87: =COUNTIFS(Backlog!$J$2:$J$1564,$A87,Backlog!$C$2:$C$1564,"Story",Backlog!$I$2:$I$1564,"Done") | H87: =COUNTIFS(Backlog!$J$2:$J$1564,$A87,Backlog!$C$2:$C$1564,"Story",Backlog!$I$2:$I$1564,"Active") | I87: =COUNTIFS(Backlog!$J$2:$J$1564,$A87,Backlog!$C$2:$C$1564,"Story",Backlog!$I$2:$I$1564,"New") | J87: =IF(F87=0,"",SUMIFS(Backlog!$K$2:$K$1564,Backlog!$J$2:$J$1564,$A87,Backlog!$C$2:$C$1564,"Story",Backlog!$I$2:$I$1564,"Done")/F87)

Sheet Coverage
A1: Rule ID | B1: Doc | C1: Rule | D1: Problem
